Workbook

Sheet Exec Summary
A1: Anthropic, PBC (Claude) | $ANT | Valuation Executive Summary
A2: ="Prepared: "&TEXT(TODAY(),"d-mmm-yyyy")&" | Source: Form S-1 filed 26-Oct-2026 | 15-year DCF, Bear / Base / Bull, probability-weighted | $ in Millions except per share" -> Prepared: 28-Oct-2026 | Source: Form S-1 filed 26-Oct-2026 | 15-year DCF, Bear / Base / Bull, probability-weighted | $ in Millions except per share
A4: INVESTMENT THESIS
A5: ="Anthropic is filing to IPO after revenue went from $4.6B in FY2025 to $"&TEXT(Historicals!F7/1000,"0.0")&"B in 1H26 alone. The Q2'26 run-rate is $"&TEXT(Historicals!G33*4/1000,"0")&"B, and Q2 was the first quarter with a GAAP operating profit ($"&TEXT(Historicals!G41,"#,##0")&"M)." -> Anthropic is filing to IPO after revenue went from $4.6B in FY2025 to $16.3B in 1H26 alone. The Q2'26 run-rate is $46B, and Q2 was the first quarter with a GAAP operating profit ($974M).
A6: =" (1) Demand: over "&TEXT(Historicals!H168,"#,##0")&" customers spend ≥$100K a year (up from ~950 a year earlier) and Net Revenue Retention is ~"&TEXT(Historicals!H171,"0%")&". Consumption (API / pay-for-intelligence) is "&TEXT(Historicals!F72/Historicals!F7,"0%")&" of 1H26 revenue." -> (1) Demand: over 11,900 customers spend ≥$100K a year (up from ~950 a year earlier) and Net Revenue Retention is ~900%. Consumption (API / pay-for-intelligence) is 80% of 1H26 revenue.
A7: =" (2) Compute: compute & infrastructure costs fell from 251% of revenue (Q1'25) to "&TEXT(Historicals!G35/Historicals!G33,"0%")&" (Q2'26). We model inference and training compute separately, the GW of capacity in service, and the move to owned capacity (Anthropic Direct)." -> (2) Compute: compute & infrastructure costs fell from 251% of revenue (Q1'25) to 48% (Q2'26). We model inference and training compute separately, the GW of capacity in service, and the move to owned capacity (Anthropic Direct).
A8: =" (3) Cash: about $"&TEXT((WACC!B56+WACC!B57)/1000,"#,##0.0")&"B of cash + short-term investments at "&Actuals!B7&" (pre-IPO); "&TEXT(WACC!B40,"0%")&" of the convertible notes are assumed to convert at the IPO. Compute commitments are large, and many are prepaid 12-18 months ahead." -> (3) Cash: about $131.7B of cash + short-term investments at Jun 2026A (pre-IPO); 100% of the convertible notes are assumed to convert at the IPO. Compute commitments are large, and many are prepaid 12-18 months ahead.
A9: =" View: the probability-weighted value of $"&TEXT(Dashboard!D12,"#,##0")&"/share compares with an entry price of $"&TEXT(Dashboard!B5,"#,##0")&". Base case "&TEXT(Dashboard!D10,"$#,##0")&"; Base IRR to FY2031E "&TEXT(Dashboard!G10,"0.0%")&" vs a "&TEXT(Dashboard!B16,"0%")&" hurdle → "&Dashboard!B21&"." -> View: the probability-weighted value of $139/share compares with an entry price of $59. Base case $112; Base IRR to FY2031E 23.3% vs a 13% hurdle → BUY – start / add to position.
A11: VALUATION CONCLUSION (implied value per share, fully diluted post-IPO)
A12: Measure | B12: Bear | C12: Base | D12: Bull | E12: Prob-weighted | G12: Notes
A13: Value per share – blended (50% GG / 50% exit) | B13: =Dashboard!D9 -> 30.494614 | C13: =Dashboard!D10 -> 111.87893 | D13: =Dashboard!D11 -> 301.27484 | E13: =Dashboard!D12 -> 138.88183 | G13: Blend weight: DCF engines, cell B153
A14: Value per share – Gordon Growth | B14: =Dashboard!B9 -> 29.192587 | C14: =Dashboard!B10 -> 102.40074 | D14: =Dashboard!B11 -> 263.7759 | E14: =Dashboard!B12 -> 124.44249 | G14: Terminal value capitalised at the terminal-period WACC
A15: Value per share – Exit multiple | B15: =Dashboard!C9 -> 31.79664 | C15: =Dashboard!C10 -> 121.35712 | D15: =Dashboard!C11 -> 338.77377 | E15: =Dashboard!C12 -> 153.32116 | G15: Exit EV/EBITDA applied to FY2040E EBITDA
A16: Upside / (downside) to entry price | B16: =Dashboard!E9 -> -0.48226462 | C16: =Dashboard!E10 -> 0.89947251 | D16: =Dashboard!E11 -> 4.1150227 | E16: =Dashboard!E12 -> 1.3579258
A17: Expected IRR to FY2031E | B17: =Dashboard!G9 -> -0.04679228 | C17: =Dashboard!G10 -> 0.23308319 | D17: =Dashboard!G11 -> 0.48464665 | E17: =Dashboard!G12 -> 0.28133475 | G17: Exit at FY2031E EBITDA × scenario exit multiple
A18: Enterprise value – blended ($M) | B18: ='DCF Bear'!D160 -> 307080.55 | C18: ='DCF Base'!D160 -> 1530280.2 | D18: ='DCF Bull'!D160 -> 4376885.1 | E18: =B18*Dashboard!F9+C18*Dashboard!F10+D18*Dashboard!F11 -> 1936131.5
A19: Entry / IPO price | B19: =Dashboard!B5 -> 58.9
A20: Recommendation | B20: =Dashboard!B21 -> BUY – start / add to position
A22: KEY ASSUMPTIONS (Base case – edit on Drivers / WACC)
A23: Item | B23: Value | G23: Source
A24: FY2026E revenue ($M) | B24: ='DCF Base'!E65 -> 54504.162 | G24: 1H26A + Q3/Q4 QoQ build
A25: FY2027E revenue growth | B25: ='DCF Base'!F66 -> 1.08 | G25: Drivers
A26: FY2030E revenue ($M) | B26: ='DCF Base'!I65 -> 326334.3 | G26: Consumption + subscription build
A27: FY2040E revenue ($M) | B27: ='DCF Base'!S65 -> 902029.72
A28: FY2040E compute need % of revenue | B28: ='DCF Base'!S79 -> 0.31 | G28: Inference + training
A29: FY2040E compute capacity (GW) | B29: ='DCF Base'!S80 -> 30.91978 | G29: Rental-equivalent cost per GW-yr
A30: FY2040E EBIT margin | B30: ='DCF Base'!S120 -> 0.45170842 | G30: SBC treated as a cost
A31: WACC (explicit period) | B31: =WACC!B23 -> 0.13367493 | G31: ="CAPM; βu "&TEXT(WACC!B15,"0.00")&" (peer median), Rf "&TEXT(WACC!B7,"0.0%")&", ERP "&TEXT(WACC!B8,"0.0%")&", +"&TEXT(WACC!B10,"0.0%")&" specific" -> CAPM; βu 1.38 (peer median), Rf 5.0%, ERP 5.0%, +1.5% specific
A32: Terminal-period WACC | B32: =WACC!B70 -> 0.10015294 | G32: Mature βu 1.00
A33: Terminal growth / exit EV/EBITDA | B33: =TEXT(WACC!C28,"0.0%")&" / "&TEXT(WACC!D28,"0.0x") -> 3.5% / 14.0x | G33: Drivers
A34: Fully diluted shares post-IPO (M) | B34: =WACC!B52 -> 15663.257 | G34: Split-adjusted (10-for-1, Sep-2026): common + preferred×10 + notes + options (TSM) + RSUs + IPO shares
A36: S-1 ACTUALS SNAPSHOT
A37: Metric | B37: Value | G37: Period / source
A38: Revenue ($M) | B38: =Historicals!D7 -> 4585 | G38: FY2025A
A39: Revenue ($M) | B39: =Historicals!F7 -> 16286 | G39: 6M 2026A (vs $1,163M 6M 2025A)
A40: Quarterly revenue run-rate ($M) | B40: =Historicals!G33*4 -> 46220 | G40: Q2 2026A × 4
A41: Adjusted operating income ($M) | B41: =Historicals!F27 -> 1618 | G41: 6M 2026A
A42: Operating cash flow ($M) | B42: =Historicals!F128 -> 3929 | G42: 6M 2026A
A43: Cash + short-term investments ($M) | B43: =Historicals!D82+Historicals!D83 -> 131651 | G43: 46203
A44: Customers ≥$100K TTM revenue | B44: =Historicals!H168 -> 11900 | G44: 46295
A45: Net Revenue Retention | B45: =Historicals!H171 -> 9 | G45: 46295
A47: KEY RISKS & WHAT WOULD CHANGE OUR VIEW
A48: Risk | G48: Impact
A49: Compute overhang: capacity is committed 12-18 months ahead; if demand slows, fixed compute cost compresses margins (S-1: margins expected to fluctuate) | G49: High – Bear engine
A50: Pricing and competition from other frontier labs and open-weight models erode revenue per token faster than compute efficiency improves | G50: High
A51: Dilution: preferred conversion, note conversion, RSU settlement, Public Benefit Issuance, and the Broadcom/Google NPAs ($62B) that can be settled in shares | G51: High – share count
A52: Governance: PBC status and the Long-Term Benefit Trust may put the mission ahead of shareholder returns | G52: Medium
A53: Concentration among compute and cloud partners (AWS, Google, Microsoft/NVIDIA, Broadcom) for both supply and distribution | G53: Medium
A54: Legal and regulatory: copyright (Bartz $1.5B precedent), AI safety regulation, export controls | G54: Medium
A56: MODEL MAP
A57: Sheet | G57: Purpose
A58: Dashboard | G58: Price input, scenario values, probability weighting, investment decision, sensitivities
A59: Graphs | G59: Quarterly revenue & margins, opex mix, revenue & UFCF by scenario, compute build-out, value vs entry price
A60: DCF Base / DCF Bear / DCF Bull | G60: Identical 15-year engines: quarterly FY26 build → revenue → compute & GPU → opex → IS → NOL → UFCF → TV → bridge → reverse DCF → IRR
A61: Drivers | G61: Granular Bear / Base / Bull assumptions plus a live historical reference
A62: WACC | G62: CAPM, terminal-period WACC, fully diluted share bridge, net cash bridge
A63: Comps | G63: Three-tier trading comps (market data) → beta and EV/revenue cross-check
A64: Ratios | G64: Quarterly, annual, balance-sheet and forecast unit economics – auto-fills from Historicals
A65: Commitments | G65: S-1 Notes 7 & 13 commitments (leases, purchase commitments, leases not yet commenced), financing facilities, Bear coverage test
A66: Actuals | G66: Update controls, annual & quarterly variance, how-to-update playbook
A67: Historicals | G67: S-1 statements as reported, with pre-labelled columns for future 10-Q/10-K
A69: All historical figures are from the Anthropic, PBC Form S-1 (SEC EDGAR, filed 26-Oct-2026). Forecasts are analyst estimates, not company guidance.
A100: Created by: Rifat Tahmid

Sheet Dashboard
A1: Anthropic, PBC (Claude) | $ANT | DCF Valuation Dashboard (Bear / Base / Bull)
A2: Single-segment DCF, 3 scenario engines, probability-weighted | Form S-1 filed 26-Oct-2026 | $ in Millions except per share
A4: ① ENTER PRICE TO SEE UPSIDE / DOWNSIDE
A5: Entry / IPO price ($ per share) | B5: =ROUND(Historicals!B178/WACC!B37,2) -> 58.9 | C5: ← Placeholder = Series H-1 $589.01 ÷ 10 (split-adjusted $/common). Overwrite with IPO price once set
A7: ② IMPLIED VALUE PER SHARE BY SCENARIO (fully diluted, post-IPO)
A8: Scenario | B8: Gordon Growth | C8: Exit Multiple | D8: Blended | E8: Upside / (Down) | F8: Probability | G8: IRR to FY2031E (from purchase date) | H8: MOIC
A9: Bear | B9: ='DCF Bear'!B165 -> 29.192587 | C9: ='DCF Bear'!C165 -> 31.79664 | D9: ='DCF Bear'!D165 -> 30.494614 | E9: =D9/$B$5-1 -> -0.48226462 | F9: =WACC!E27 -> 0.25 | G9: ='DCF Bear'!B184 -> -0.04679228 | H9: ='DCF Bear'!B185 -> 0.78014334
A10: Base | B10: ='DCF Base'!B165 -> 102.40074 | C10: ='DCF Base'!C165 -> 121.35712 | D10: ='DCF Base'!D165 -> 111.87893 | E10: =D10/$B$5-1 -> 0.89947251 | F10: =WACC!E28 -> 0.5 | G10: ='DCF Base'!B184 -> 0.23308319 | H10: ='DCF Base'!B185 -> 2.9608424
A11: Bull | B11: ='DCF Bull'!B165 -> 263.7759 | C11: ='DCF Bull'!C165 -> 338.77377 | D11: ='DCF Bull'!D165 -> 301.27484 | E11: =D11/$B$5-1 -> 4.1150227 | F11: =WACC!E29 -> 0.25 | G11: ='DCF Bull'!B184 -> 0.48464665 | H11: ='DCF Bull'!B185 -> 7.7472707
A12: Probability-weighted | B12: =SUMPRODUCT(B9:B11,$F$9:$F$11) -> 124.44249 | C12: =SUMPRODUCT(C9:C11,$F$9:$F$11) -> 153.32116 | D12: =SUMPRODUCT(D9:D11,$F$9:$F$11) -> 138.88183 | E12: =D12/$B$5-1 -> 1.3579258 | F12: =SUM(F9:F11) -> 1 | G12: =((F9*'DCF Bear'!B182+F10*'DCF Base'!B182+F11*'DCF Bull'!B182)/$B$5)^(1/'DCF Base'!B183)-1 -> 0.28133475 | H12: =SUMPRODUCT(H9:H11,$F$9:$F$11) -> 3.6122747
A14: ③ INVESTMENT DECISION (personal underwriting rules)
A15: Item | B15: Value | H15: Note
A16: Hurdle rate (required annual return) | B16: =WACC!B18 -> 0.13496243 | H16: Linked to CAPM cost of equity (WACC!B18) – only override upward
A17: Required margin of safety vs probability-weighted value | B17: 0.2 | H17: Frontier-AI model risk; compute commitments
A18: Probability-weighted value per share | B18: =D12 -> 138.88183
A19: Maximum entry price (value × (1 − margin of safety)) | B19: =B18*(1-B17) -> 111.10546 | H19: Price discipline anchor
A20: Base-case IRR minus hurdle | B20: =G10-B16 -> 0.098120755
A21: Recommendation | B21: =IF(AND($B$5<=B19,G10>=B16),"BUY – start / add to position",IF($B$5<=B18,"HOLD – watchlist, thin margin of safety","PASS at this price")) -> BUY – start / add to position | H21: Driven by entered price vs value & IRR
A22: Market-implied perpetual growth (Base engine reverse DCF) | B22: ='DCF Base'!B178 -> -0.24921136 | H22: vs Base terminal growth assumption
A23: Market-implied FY2040E exit EV / EBITDA (Base) | B23: ='DCF Base'!B179 -> 1.3755728 | H23: vs Base exit multiple
A24: Market-implied EV / FY2027E revenue | B24: =Comps!K43 -> 6.4745512 | H24: Cross-check vs comps medians
A26: ④ BASE CASE – ENTERPRISE VALUE TO EQUITY BRIDGE
A27: ($M) | B27: Gordon Growth | C27: Exit Multiple | D27: Blended
A28: Sum of PV of UFCF | B28: ='DCF Base'!B155 -> 631726.52 | C28: ='DCF Base'!C155 -> 631726.52 | D28: ='DCF Base'!D155 -> 631726.52
A29: PV of terminal value | B29: ='DCF Base'!B159 -> 756097.19 | C29: ='DCF Base'!C159 -> 1041010.1 | D29: ='DCF Base'!D159 -> 898553.65
A30: Enterprise value | B30: ='DCF Base'!B160 -> 1387823.7 | C30: ='DCF Base'!C160 -> 1672736.6 | D30: ='DCF Base'!D160 -> 1530280.2
A31: TV % of EV | B31: ='DCF Base'!B161 -> 0.54480781 | C31: ='DCF Base'!C161 -> 0.62233952 | D31: ='DCF Base'!D161 -> 0.58718244
A32: (+) Net cash incl. IPO proceeds | B32: ='DCF Base'!B162 -> 151251 | C32: ='DCF Base'!C162 -> 151251 | D32: ='DCF Base'!D162 -> 151251
A33: Equity value | B33: ='DCF Base'!B163 -> 1603929.1 | C33: ='DCF Base'!C163 -> 1900847.9 | D33: ='DCF Base'!D163 -> 1752388.5
A34: Fully diluted shares (M) | B34: ='DCF Base'!B164 -> 15663.257 | C34: ='DCF Base'!C164 -> 15663.257 | D34: ='DCF Base'!D164 -> 15663.257
A35: Implied value per share | B35: ='DCF Base'!B165 -> 102.40074 | C35: ='DCF Base'!C165 -> 121.35712 | D35: ='DCF Base'!D165 -> 111.87893
A37: ⑤ SENSITIVITY (Base) – value per share, Gordon Growth: WACC vs terminal growth
A38: ='DCF Base'!A188 -> WACC ↓ \ Tg → | B38: ='DCF Base'!B188 -> 0.025 | C38: ='DCF Base'!C188 -> 0.03 | D38: ='DCF Base'!D188 -> 0.035 | E38: ='DCF Base'!E188 -> 0.04 | F38: ='DCF Base'!F188 -> 0.045
A39: ='DCF Base'!A189 -> 0.11367493 | B39: ='DCF Base'!B189 -> 135.85865 | C39: ='DCF Base'!C189 -> 143.86295 | D39: ='DCF Base'!D189 -> 153.63995 | E39: ='DCF Base'!E189 -> 165.85189 | F39: ='DCF Base'!F189 -> 181.53778
A40: ='DCF Base'!A190 -> 0.12367493 | B40: ='DCF Base'!B190 -> 112.34621 | C40: ='DCF Base'!C190 -> 117.35452 | D40: ='DCF Base'!D190 -> 123.2709 | E40: ='DCF Base'!E190 -> 130.36695 | F40: ='DCF Base'!F190 -> 139.03456
A41: ='DCF Base'!A191 -> 0.13367493 | B41: ='DCF Base'!B191 -> 95.285528 | C41: ='DCF Base'!C191 -> 98.589573 | D41: ='DCF Base'!D191 -> 102.40074 | E41: ='DCF Base'!E191 -> 106.84548 | F41: ='DCF Base'!F191 -> 112.09612
A42: ='DCF Base'!A192 -> 0.14367493 | B42: ='DCF Base'!B192 -> 82.390462 | C42: ='DCF Base'!C192 -> 84.657866 | D42: ='DCF Base'!D192 -> 87.226975 | E42: ='DCF Base'!E192 -> 90.1623 | F42: ='DCF Base'!F192 -> 93.548153
A43: ='DCF Base'!A193 -> 0.15367493 | B43: ='DCF Base'!B193 -> 72.337188 | C43: ='DCF Base'!C193 -> 73.94155 | D43: ='DCF Base'!D193 -> 75.734322 | E43: ='DCF Base'!E193 -> 77.750762 | F43: ='DCF Base'!F193 -> 80.035515
A45: ⑥ SENSITIVITY (Base) – value per share, Exit Multiple: WACC vs exit EV/EBITDA
A46: ='DCF Base'!A196 -> WACC ↓ \ Exit multiple → | B46: ='DCF Base'!B196 -> 10 | C46: ='DCF Base'!C196 -> 12 | D46: ='DCF Base'!D196 -> 14 | E46: ='DCF Base'!E196 -> 16 | F46: ='DCF Base'!F196 -> 18
A47: ='DCF Base'!A197 -> 0.11367493 | B47: ='DCF Base'!B197 -> 123.71587 | C47: ='DCF Base'!C197 -> 136.52497 | D47: ='DCF Base'!D197 -> 149.33406 | E47: ='DCF Base'!E197 -> 162.14316 | F47: ='DCF Base'!F197 -> 174.95226
A48: ='DCF Base'!A198 -> 0.12367493 | B48: ='DCF Base'!B198 -> 111.95179 | C48: ='DCF Base'!C198 -> 123.20328 | D48: ='DCF Base'!D198 -> 134.45476 | E48: ='DCF Base'!E198 -> 145.70625 | F48: ='DCF Base'!F198 -> 156.95774
A49: ='DCF Base'!A199 -> 0.13367493 | B49: ='DCF Base'!B199 -> 101.56783 | C49: ='DCF Base'!C199 -> 111.46248 | D49: ='DCF Base'!D199 -> 121.35712 | E49: ='DCF Base'!E199 -> 131.25177 | F49: ='DCF Base'!F199 -> 141.14642
A50: ='DCF Base'!A200 -> 0.14367493 | B50: ='DCF Base'!B200 -> 92.38694 | C50: ='DCF Base'!C200 -> 101.0982 | D50: ='DCF Base'!D200 -> 109.80945 | E50: ='DCF Base'!E200 -> 118.52071 | F50: ='DCF Base'!F200 -> 127.23196
A51: ='DCF Base'!A201 -> 0.15367493 | B51: ='DCF Base'!B201 -> 84.256421 | C51: ='DCF Base'!C201 -> 91.934328 | D51: ='DCF Base'!D201 -> 99.612235 | E51: ='DCF Base'!E201 -> 107.29014 | F51: ='DCF Base'!F201 -> 114.96805
A53: ⑦ KEY FINANCIALS & COMPUTE – Base engine
A54: Metric | B54: FY2025A | C54: FY2026E | D54: FY2027E | E54: FY2028E | F54: FY2030E | G54: FY2035E | H54: FY2040E
A55: Revenue ($M) | B55: ='DCF Base'!D65 -> 4585 | C55: ='DCF Base'!E65 -> 54504.162 | D55: ='DCF Base'!F65 -> 113368.66 | E55: ='DCF Base'!G65 -> 180299.77 | F55: ='DCF Base'!I65 -> 326334.3 | G55: ='DCF Base'!N65 -> 673940.81 | H55: ='DCF Base'!S65 -> 902029.72
A56: % YoY growth | B56: ='DCF Base'!D66 -> 10.878238 | C56: ='DCF Base'!E66 -> 10.887495 | D56: ='DCF Base'!F66 -> 1.08 | E56: ='DCF Base'!G66 -> 0.59038462 | F56: ='DCF Base'!I66 -> 0.29629514 | G56: ='DCF Base'!N66 -> 0.098258432 | H56: ='DCF Base'!S66 -> 0.04
A57: Compute capacity in service (GW) | B57: ='DCF Base'!D80 -> 0.6105 | C57: ='DCF Base'!E80 -> 2.4981074 | D57: ='DCF Base'!F80 -> 4.868297 | E57: ='DCF Base'!G80 -> 7.274694 | F57: ='DCF Base'!I80 -> 11.793368 | G57: ='DCF Base'!N80 -> 21.89213 | H57: ='DCF Base'!S80 -> 30.91978
A58: Accelerators in service (000s) | B58: ='DCF Base'!D81 -> 396.825 | C58: ='DCF Base'!E81 -> 1623.7698 | D58: ='DCF Base'!F81 -> 3069.4612 | E58: ='DCF Base'!G81 -> 4449.2028 | F58: ='DCF Base'!I81 -> 6785.9042 | G58: ='DCF Base'!N81 -> 10819.091 | H58: ='DCF Base'!S81 -> 13119.263
A59: Owned (Anthropic Direct) share of fleet | C59: ='DCF Base'!E86 -> 0.0755615 | D59: ='DCF Base'!F86 -> 0.1361459 | E59: ='DCF Base'!G86 -> 0.19034722 | F59: ='DCF Base'!I86 -> 0.26088381 | G59: ='DCF Base'!N86 -> 0.32505761 | H59: ='DCF Base'!S86 -> 0.34693855
A60: Compute need % of revenue | B60: ='DCF Base'!D79 -> 1.597819 | C60: ='DCF Base'!E79 -> 0.55 | D60: ='DCF Base'!F79 -> 0.505 | E60: ='DCF Base'!G79 -> 0.465 | F60: ='DCF Base'!I79 -> 0.4 | G60: ='DCF Base'!N79 -> 0.325 | H60: ='DCF Base'!S79 -> 0.31
A61: Adjusted EBITDA margin | B61: ='DCF Base'!D117 -> -1.1694656 | C61: ='DCF Base'!E117 -> 0.12627611 | D61: ='DCF Base'!F117 -> 0.232328 | E61: ='DCF Base'!G117 -> 0.31551053 | F61: ='DCF Base'!I117 -> 0.42529258 | G61: ='DCF Base'!N117 -> 0.53586389 | H61: ='DCF Base'!S117 -> 0.53564086
A62: EBIT margin | B62: ='DCF Base'!D120 -> -1.7579062 | C62: ='DCF Base'!E120 -> 0.016799353 | D62: ='DCF Base'!F120 -> 0.13971791 | E62: ='DCF Base'!G120 -> 0.22206414 | F62: ='DCF Base'!I120 -> 0.32999515 | G62: ='DCF Base'!N120 -> 0.44801966 | H62: ='DCF Base'!S120 -> 0.45170842
A63: Unlevered FCF ($M) | C63: ='DCF Base'!E140 -> -7691.967 | D63: ='DCF Base'!F140 -> -4801.4883 | E63: ='DCF Base'!G140 -> 3968.3714 | F63: ='DCF Base'!I140 -> 52034.742 | G63: ='DCF Base'!N140 -> 209799.89 | H63: ='DCF Base'!S140 -> 293683.2
A64: UFCF margin | C64: ='DCF Base'!E141 -> -0.14112623 | D64: ='DCF Base'!F141 -> -0.042352872 | E64: ='DCF Base'!G141 -> 0.022009853 | F64: ='DCF Base'!I141 -> 0.15945226 | G64: ='DCF Base'!N141 -> 0.31130314 | H64: ='DCF Base'!S141 -> 0.3255804
A100: Created by: Rifat Tahmid

Sheet Graphs
A1: Anthropic ($ANT) – Charts
A2: Source: Historicals (Form S-1 filed 26-Oct-2026), DCF Bear / Base / Bull engines, Dashboard | $ in Millions unless stated | chart data block in columns U:AK (linked, do not overwrite)
U4: Chart 1 title (linked to chart):
U5: ="Income statement bridge – "&Actuals!B5&" ($M), as reported in S-1 / 10-Q" -> Income statement bridge – 6M 2026A ($M), as reported in S-1 / 10-Q
U6: CHART DATA 1: YTD INCOME STATEMENT BRIDGE (Historicals rows 7–22, 72–73; period = Actuals!B5)
U7: Type | V7: Value | W7: Start | X7: End | Y7: Low | Z7: High | AA7: Category | AB7: Inv + | AC7: Inv − | AD7: Consumption | AE7: Subscription | AF7: Costs | AG7: Costs | AH7: Income | AI7: Income | AJ7: Subtotal | AK7: Subtotal
U8: Rev | V8: =INDEX(Historicals!$B$7:$K$7,MATCH(Actuals!$B$5,Historicals!$B$6:$K$6,0)) -> 16286 | W8: =0 -> 0 | X8: =IF(U8="Total",V8,W8+V8) -> 16286 | Y8: =MIN(W8,X8) -> 0 | Z8: =MAX(W8,X8) -> 16286 | AA8: ="Revenue"&CHAR(10)&TEXT(V8,"$#,##0;($#,##0);-") -> Revenue $16,286 | AB8: =IF(U8="Rev",0,IF(Y8>0,Y8,0)) -> 0 | AC8: =IF(Z8<0,Z8,0) -> 0 | AD8: =IF(U8="Rev",INDEX(Historicals!$B$72:$K$72,MATCH(Actuals!$B$5,Historicals!$B$68:$K$68,0)),0) -> 13064 | AE8: =IF(U8="Rev",INDEX(Historicals!$B$73:$K$73,MATCH(Actuals!$B$5,Historicals!$B$68:$K$68,0)),0) -> 3222 | AF8: =IF(AND(U8="Step",V8<0),MAX(Z8,0)-MAX(Y8,0),0) -> 0 | AG8: =IF(AND(U8="Step",V8<0),MIN(Y8,0)-MIN(Z8,0),0) -> 0 | AH8: =IF(AND(U8="Step",V8>0),MAX(Z8,0)-MAX(Y8,0),0) -> 0 | AI8: =IF(AND(U8="Step",V8>0),MIN(Y8,0)-MIN(Z8,0),0) -> 0 | AJ8: =IF(U8="Total",MAX(Z8,0)-MAX(Y8,0),0) -> 0 | AK8: =IF(U8="Total",MIN(Y8,0)-MIN(Z8,0),0) -> 0
U9: Step | V9: =-INDEX(Historicals!$B$9:$K$9,MATCH(Actuals!$B$5,Historicals!$B$6:$K$6,0)) -> -8945 | W9: =IF(U9="Total",0,X8) -> 16286 | X9: =IF(U9="Total",V9,W9+V9) -> 7341 | Y9: =MIN(W9,X9) -> 7341 | Z9: =MAX(W9,X9) -> 16286 | AA9: ="Compute & infra"&CHAR(10)&TEXT(V9,"$#,##0;($#,##0);-") -> Compute & infra ($8,945) | AB9: =IF(U9="Rev",0,IF(Y9>0,Y9,0)) -> 7341 | AC9: =IF(Z9<0,Z9,0) -> 0 | AD9: =IF(U9="Rev",INDEX(Historicals!$B$72:$K$72,MATCH(Actuals!$B$5,Historicals!$B$68:$K$68,0)),0) -> 0 | AE9: =IF(U9="Rev",INDEX(Historicals!$B$73:$K$73,MATCH(Actuals!$B$5,Historicals!$B$68:$K$68,0)),0) -> 0 | AF9: =IF(AND(U9="Step",V9<0),MAX(Z9,0)-MAX(Y9,0),0) -> 8945 | AG9: =IF(AND(U9="Step",V9<0),MIN(Y9,0)-MIN(Z9,0),0) -> 0 | AH9: =IF(AND(U9="Step",V9>0),MAX(Z9,0)-MAX(Y9,0),0) -> 0 | AI9: =IF(AND(U9="Step",V9>0),MIN(Y9,0)-MIN(Z9,0),0) -> 0 | AJ9: =IF(U9="Total",MAX(Z9,0)-MAX(Y9,0),0) -> 0 | AK9: =IF(U9="Total",MIN(Y9,0)-MIN(Z9,0),0) -> 0
U10: Step | V10: =-INDEX(Historicals!$B$10:$K$10,MATCH(Actuals!$B$5,Historicals!$B$6:$K$6,0)) -> -3152 | W10: =IF(U10="Total",0,X9) -> 7341 | X10: =IF(U10="Total",V10,W10+V10) -> 4189 | Y10: =MIN(W10,X10) -> 4189 | Z10: =MAX(W10,X10) -> 7341 | AA10: ="Personnel"&CHAR(10)&TEXT(V10,"$#,##0;($#,##0);-") -> Personnel ($3,152) | AB10: =IF(U10="Rev",0,IF(Y10>0,Y10,0)) -> 4189 | AC10: =IF(Z10<0,Z10,0) -> 0 | AD10: =IF(U10="Rev",INDEX(Historicals!$B$72:$K$72,MATCH(Actuals!$B$5,Historicals!$B$68:$K$68,0)),0) -> 0 | AE10: =IF(U10="Rev",INDEX(Historicals!$B$73:$K$73,MATCH(Actuals!$B$5,Historicals!$B$68:$K$68,0)),0) -> 0 | AF10: =IF(AND(U10="Step",V10<0),MAX(Z10,0)-MAX(Y10,0),0) -> 3152 | AG10: =IF(AND(U10="Step",V10<0),MIN(Y10,0)-MIN(Z10,0),0) -> 0 | AH10: =IF(AND(U10="Step",V10>0),MAX(Z10,0)-MAX(Y10,0),0) -> 0 | AI10: =IF(AND(U10="Step",V10>0),MIN(Y10,0)-MIN(Z10,0),0) -> 0 | AJ10: =IF(U10="Total",MAX(Z10,0)-MAX(Y10,0),0) -> 0 | AK10: =IF(U10="Total",MIN(Y10,0)-MIN(Z10,0),0) -> 0
U11: Step | V11: =-INDEX(Historicals!$B$11:$K$11,MATCH(Actuals!$B$5,Historicals!$B$6:$K$6,0)) -> 0 | W11: =IF(U11="Total",0,X10) -> 4189 | X11: =IF(U11="Total",V11,W11+V11) -> 4189 | Y11: =MIN(W11,X11) -> 4189 | Z11: =MAX(W11,X11) -> 4189 | AA11: ="Bartz settlement"&CHAR(10)&TEXT(V11,"$#,##0;($#,##0);-") -> Bartz settlement - | AB11: =IF(U11="Rev",0,IF(Y11>0,Y11,0)) -> 4189 | AC11: =IF(Z11<0,Z11,0) -> 0 | AD11: =IF(U11="Rev",INDEX(Historicals!$B$72:$K$72,MATCH(Actuals!$B$5,Historicals!$B$68:$K$68,0)),0) -> 0 | AE11: =IF(U11="Rev",INDEX(Historicals!$B$73:$K$73,MATCH(Actuals!$B$5,Historicals!$B$68:$K$68,0)),0) -> 0 | AF11: =IF(AND(U11="Step",V11<0),MAX(Z11,0)-MAX(Y11,0),0) -> 0 | AG11: =IF(AND(U11="Step",V11<0),MIN(Y11,0)-MIN(Z11,0),0) -> 0 | AH11: =IF(AND(U11="Step",V11>0),MAX(Z11,0)-MAX(Y11,0),0) -> 0 | AI11: =IF(AND(U11="Step",V11>0),MIN(Y11,0)-MIN(Z11,0),0) -> 0 | AJ11: =IF(U11="Total",MAX(Z11,0)-MAX(Y11,0),0) -> 0 | AK11: =IF(U11="Total",MIN(Y11,0)-MIN(Z11,0),0) -> 0
U12: Step | V12: =-INDEX(Historicals!$B$12:$K$12,MATCH(Actuals!$B$5,Historicals!$B$6:$K$6,0)) -> -3168 | W12: =IF(U12="Total",0,X11) -> 4189 | X12: =IF(U12="Total",V12,W12+V12) -> 1021 | Y12: =MIN(W12,X12) -> 1021 | Z12: =MAX(W12,X12) -> 4189 | AA12: ="S&M & partnerships"&CHAR(10)&TEXT(V12,"$#,##0;($#,##0);-") -> S&M & partnerships ($3,168) | AB12: =IF(U12="Rev",0,IF(Y12>0,Y12,0)) -> 1021 | AC12: =IF(Z12<0,Z12,0) -> 0 | AD12: =IF(U12="Rev",INDEX(Historicals!$B$72:$K$72,MATCH(Actuals!$B$5,Historicals!$B$68:$K$68,0)),0) -> 0 | AE12: =IF(U12="Rev",INDEX(Historicals!$B$73:$K$73,MATCH(Actuals!$B$5,Historicals!$B$68:$K$68,0)),0) -> 0 | AF12: =IF(AND(U12="Step",V12<0),MAX(Z12,0)-MAX(Y12,0),0) -> 3168 | AG12: =IF(AND(U12="Step",V12<0),MIN(Y12,0)-MIN(Z12,0),0) -> 0 | AH12: =IF(AND(U12="Step",V12>0),MAX(Z12,0)-MAX(Y12,0),0) -> 0 | AI12: =IF(AND(U12="Step",V12>0),MIN(Y12,0)-MIN(Z12,0),0) -> 0 | AJ12: =IF(U12="Total",MAX(Z12,0)-MAX(Y12,0),0) -> 0 | AK12: =IF(U12="Total",MIN(Y12,0)-MIN(Z12,0),0) -> 0
U13: Step | V13: =-INDEX(Historicals!$B$13:$K$13,MATCH(Actuals!$B$5,Historicals!$B$6:$K$6,0)) -> -1714 | W13: =IF(U13="Total",0,X12) -> 1021 | X13: =IF(U13="Total",V13,W13+V13) -> -693 | Y13: =MIN(W13,X13) -> -693 | Z13: =MAX(W13,X13) -> 1021 | AA13: ="Other op. & admin"&CHAR(10)&TEXT(V13,"$#,##0;($#,##0);-") -> Other op. & admin ($1,714) | AB13: =IF(U13="Rev",0,IF(Y13>0,Y13,0)) -> 0 | AC13: =IF(Z13<0,Z13,0) -> 0 | AD13: =IF(U13="Rev",INDEX(Historicals!$B$72:$K$72,MATCH(Actuals!$B$5,Historicals!$B$68:$K$68,0)),0) -> 0 | AE13: =IF(U13="Rev",INDEX(Historicals!$B$73:$K$73,MATCH(Actuals!$B$5,Historicals!$B$68:$K$68,0)),0) -> 0 | AF13: =IF(AND(U13="Step",V13<0),MAX(Z13,0)-MAX(Y13,0),0) -> 1021 | AG13: =IF(AND(U13="Step",V13<0),MIN(Y13,0)-MIN(Z13,0),0) -> -693 | AH13: =IF(AND(U13="Step",V13>0),MAX(Z13,0)-MAX(Y13,0),0) -> 0 | AI13: =IF(AND(U13="Step",V13>0),MIN(Y13,0)-MIN(Z13,0),0) -> 0 | AJ13: =IF(U13="Total",MAX(Z13,0)-MAX(Y13,0),0) -> 0 | AK13: =IF(U13="Total",MIN(Y13,0)-MIN(Z13,0),0) -> 0
U14: Total | V14: =INDEX(Historicals!$B$15:$K$15,MATCH(Actuals!$B$5,Historicals!$B$6:$K$6,0)) -> -693 | W14: =IF(U14="Total",0,X13) -> 0 | X14: =IF(U14="Total",V14,W14+V14) -> -693 | Y14: =MIN(W14,X14) -> -693 | Z14: =MAX(W14,X14) -> 0 | AA14: ="Operating income"&CHAR(10)&TEXT(V14,"$#,##0;($#,##0);-") -> Operating income ($693) | AB14: =IF(U14="Rev",0,IF(Y14>0,Y14,0)) -> 0 | AC14: =IF(Z14<0,Z14,0) -> 0 | AD14: =IF(U14="Rev",INDEX(Historicals!$B$72:$K$72,MATCH(Actuals!$B$5,Historicals!$B$68:$K$68,0)),0) -> 0 | AE14: =IF(U14="Rev",INDEX(Historicals!$B$73:$K$73,MATCH(Actuals!$B$5,Historicals!$B$68:$K$68,0)),0) -> 0 | AF14: =IF(AND(U14="Step",V14<0),MAX(Z14,0)-MAX(Y14,0),0) -> 0 | AG14: =IF(AND(U14="Step",V14<0),MIN(Y14,0)-MIN(Z14,0),0) -> 0 | AH14: =IF(AND(U14="Step",V14>0),MAX(Z14,0)-MAX(Y14,0),0) -> 0 | AI14: =IF(AND(U14="Step",V14>0),MIN(Y14,0)-MIN(Z14,0),0) -> 0 | AJ14: =IF(U14="Total",MAX(Z14,0)-MAX(Y14,0),0) -> 0 | AK14: =IF(U14="Total",MIN(Y14,0)-MIN(Z14,0),0) -> -693
U15: Step | V15: =INDEX(Historicals!$B$16:$K$16,MATCH(Actuals!$B$5,Historicals!$B$6:$K$6,0)) -> 1111 | W15: =IF(U15="Total",0,X14) -> -693 | X15: =IF(U15="Total",V15,W15+V15) -> 418 | Y15: =MIN(W15,X15) -> -693 | Z15: =MAX(W15,X15) -> 418 | AA15: ="Interest income"&CHAR(10)&TEXT(V15,"$#,##0;($#,##0);-") -> Interest income $1,111 | AB15: =IF(U15="Rev",0,IF(Y15>0,Y15,0)) -> 0 | AC15: =IF(Z15<0,Z15,0) -> 0 | AD15: =IF(U15="Rev",INDEX(Historicals!$B$72:$K$72,MATCH(Actuals!$B$5,Historicals!$B$68:$K$68,0)),0) -> 0 | AE15: =IF(U15="Rev",INDEX(Historicals!$B$73:$K$73,MATCH(Actuals!$B$5,Historicals!$B$68:$K$68,0)),0) -> 0 | AF15: =IF(AND(U15="Step",V15<0),MAX(Z15,0)-MAX(Y15,0),0) -> 0 | AG15: =IF(AND(U15="Step",V15<0),MIN(Y15,0)-MIN(Z15,0),0) -> 0 | AH15: =IF(AND(U15="Step",V15>0),MAX(Z15,0)-MAX(Y15,0),0) -> 418 | AI15: =IF(AND(U15="Step",V15>0),MIN(Y15,0)-MIN(Z15,0),0) -> -693 | AJ15: =IF(U15="Total",MAX(Z15,0)-MAX(Y15,0),0) -> 0 | AK15: =IF(U15="Total",MIN(Y15,0)-MIN(Z15,0),0) -> 0
U16: Step | V16: =INDEX(Historicals!$B$17:$K$17,MATCH(Actuals!$B$5,Historicals!$B$6:$K$6,0)) -> -72388 | W16: =IF(U16="Total",0,X15) -> 418 | X16: =IF(U16="Total",V16,W16+V16) -> -71970 | Y16: =MIN(W16,X16) -> -71970 | Z16: =MAX(W16,X16) -> 418 | AA16: ="FV change – notes & SAFEs"&CHAR(10)&TEXT(V16,"$#,##0;($#,##0);-") -> FV change – notes & SAFEs ($72,388) | AB16: =IF(U16="Rev",0,IF(Y16>0,Y16,0)) -> 0 | AC16: =IF(Z16<0,Z16,0) -> 0 | AD16: =IF(U16="Rev",INDEX(Historicals!$B$72:$K$72,MATCH(Actuals!$B$5,Historicals!$B$68:$K$68,0)),0) -> 0 | AE16: =IF(U16="Rev",INDEX(Historicals!$B$73:$K$73,MATCH(Actuals!$B$5,Historicals!$B$68:$K$68,0)),0) -> 0 | AF16: =IF(AND(U16="Step",V16<0),MAX(Z16,0)-MAX(Y16,0),0) -> 418 | AG16: =IF(AND(U16="Step",V16<0),MIN(Y16,0)-MIN(Z16,0),0) -> -71970 | AH16: =IF(AND(U16="Step",V16>0),MAX(Z16,0)-MAX(Y16,0),0) -> 0 | AI16: =IF(AND(U16="Step",V16>0),MIN(Y16,0)-MIN(Z16,0),0) -> 0 | AJ16: =IF(U16="Total",MAX(Z16,0)-MAX(Y16,0),0) -> 0 | AK16: =IF(U16="Total",MIN(Y16,0)-MIN(Z16,0),0) -> 0
U17: Step | V17: =INDEX(Historicals!$B$18:$K$18,MATCH(Actuals!$B$5,Historicals!$B$6:$K$6,0)) -> -8757 | W17: =IF(U17="Total",0,X16) -> -71970 | X17: =IF(U17="Total",V17,W17+V17) -> -80727 | Y17: =MIN(W17,X17) -> -80727 | Z17: =MAX(W17,X17) -> -71970 | AA17: ="Other income (exp.)"&CHAR(10)&TEXT(V17,"$#,##0;($#,##0);-") -> Other income (exp.) ($8,757) | AB17: =IF(U17="Rev",0,IF(Y17>0,Y17,0)) -> 0 | AC17: =IF(Z17<0,Z17,0) -> -71970 | AD17: =IF(U17="Rev",INDEX(Historicals!$B$72:$K$72,MATCH(Actuals!$B$5,Historicals!$B$68:$K$68,0)),0) -> 0 | AE17: =IF(U17="Rev",INDEX(Historicals!$B$73:$K$73,MATCH(Actuals!$B$5,Historicals!$B$68:$K$68,0)),0) -> 0 | AF17: =IF(AND(U17="Step",V17<0),MAX(Z17,0)-MAX(Y17,0),0) -> 0 | AG17: =IF(AND(U17="Step",V17<0),MIN(Y17,0)-MIN(Z17,0),0) -> -8757 | AH17: =IF(AND(U17="Step",V17>0),MAX(Z17,0)-MAX(Y17,0),0) -> 0 | AI17: =IF(AND(U17="Step",V17>0),MIN(Y17,0)-MIN(Z17,0),0) -> 0 | AJ17: =IF(U17="Total",MAX(Z17,0)-MAX(Y17,0),0) -> 0 | AK17: =IF(U17="Total",MIN(Y17,0)-MIN(Z17,0),0) -> 0
U18: Total | V18: =INDEX(Historicals!$B$20:$K$20,MATCH(Actuals!$B$5,Historicals!$B$6:$K$6,0)) -> -80727 | W18: =IF(U18="Total",0,X17) -> 0 | X18: =IF(U18="Total",V18,W18+V18) -> -80727 | Y18: =MIN(W18,X18) -> -80727 | Z18: =MAX(W18,X18) -> 0 | AA18: ="Pre-tax loss"&CHAR(10)&TEXT(V18,"$#,##0;($#,##0);-") -> Pre-tax loss ($80,727) | AB18: =IF(U18="Rev",0,IF(Y18>0,Y18,0)) -> 0 | AC18: =IF(Z18<0,Z18,0) -> 0 | AD18: =IF(U18="Rev",INDEX(Historicals!$B$72:$K$72,MATCH(Actuals!$B$5,Historicals!$B$68:$K$68,0)),0) -> 0 | AE18: =IF(U18="Rev",INDEX(Historicals!$B$73:$K$73,MATCH(Actuals!$B$5,Historicals!$B$68:$K$68,0)),0) -> 0 | AF18: =IF(AND(U18="Step",V18<0),MAX(Z18,0)-MAX(Y18,0),0) -> 0 | AG18: =IF(AND(U18="Step",V18<0),MIN(Y18,0)-MIN(Z18,0),0) -> 0 | AH18: =IF(AND(U18="Step",V18>0),MAX(Z18,0)-MAX(Y18,0),0) -> 0 | AI18: =IF(AND(U18="Step",V18>0),MIN(Y18,0)-MIN(Z18,0),0) -> 0 | AJ18: =IF(U18="Total",MAX(Z18,0)-MAX(Y18,0),0) -> 0 | AK18: =IF(U18="Total",MIN(Y18,0)-MIN(Z18,0),0) -> -80727
U19: Step | V19: =-INDEX(Historicals!$B$21:$K$21,MATCH(Actuals!$B$5,Historicals!$B$6:$K$6,0)) -> -21 | W19: =IF(U19="Total",0,X18) -> -80727 | X19: =IF(U19="Total",V19,W19+V19) -> -80748 | Y19: =MIN(W19,X19) -> -80748 | Z19: =MAX(W19,X19) -> -80727 | AA19: ="Tax provision"&CHAR(10)&TEXT(V19,"$#,##0;($#,##0);-") -> Tax provision ($21) | AB19: =IF(U19="Rev",0,IF(Y19>0,Y19,0)) -> 0 | AC19: =IF(Z19<0,Z19,0) -> -80727 | AD19: =IF(U19="Rev",INDEX(Historicals!$B$72:$K$72,MATCH(Actuals!$B$5,Historicals!$B$68:$K$68,0)),0) -> 0 | AE19: =IF(U19="Rev",INDEX(Historicals!$B$73:$K$73,MATCH(Actuals!$B$5,Historicals!$B$68:$K$68,0)),0) -> 0 | AF19: =IF(AND(U19="Step",V19<0),MAX(Z19,0)-MAX(Y19,0),0) -> 0 | AG19: =IF(AND(U19="Step",V19<0),MIN(Y19,0)-MIN(Z19,0),0) -> -21 | AH19: =IF(AND(U19="Step",V19>0),MAX(Z19,0)-MAX(Y19,0),0) -> 0 | AI19: =IF(AND(U19="Step",V19>0),MIN(Y19,0)-MIN(Z19,0),0) -> 0 | AJ19: =IF(U19="Total",MAX(Z19,0)-MAX(Y19,0),0) -> 0 | AK19: =IF(U19="Total",MIN(Y19,0)-MIN(Z19,0),0) -> 0
U20: Total | V20: =INDEX(Historicals!$B$22:$K$22,MATCH(Actuals!$B$5,Historicals!$B$6:$K$6,0)) -> -80748 | W20: =IF(U20="Total",0,X19) -> 0 | X20: =IF(U20="Total",V20,W20+V20) -> -80748 | Y20: =MIN(W20,X20) -> -80748 | Z20: =MAX(W20,X20) -> 0 | AA20: ="Net loss"&CHAR(10)&TEXT(V20,"$#,##0;($#,##0);-") -> Net loss ($80,748) | AB20: =IF(U20="Rev",0,IF(Y20>0,Y20,0)) -> 0 | AC20: =IF(Z20<0,Z20,0) -> 0 | AD20: =IF(U20="Rev",INDEX(Historicals!$B$72:$K$72,MATCH(Actuals!$B$5,Historicals!$B$68:$K$68,0)),0) -> 0 | AE20: =IF(U20="Rev",INDEX(Historicals!$B$73:$K$73,MATCH(Actuals!$B$5,Historicals!$B$68:$K$68,0)),0) -> 0 | AF20: =IF(AND(U20="Step",V20<0),MAX(Z20,0)-MAX(Y20,0),0) -> 0 | AG20: =IF(AND(U20="Step",V20<0),MIN(Y20,0)-MIN(Z20,0),0) -> 0 | AH20: =IF(AND(U20="Step",V20>0),MAX(Z20,0)-MAX(Y20,0),0) -> 0 | AI20: =IF(AND(U20="Step",V20>0),MIN(Y20,0)-MIN(Z20,0),0) -> 0 | AJ20: =IF(U20="Total",MAX(Z20,0)-MAX(Y20,0),0) -> 0 | AK20: =IF(U20="Total",MIN(Y20,0)-MIN(Z20,0),0) -> -80748
U22: CHART DATA 2–3: QUARTERLY (Historicals rows 32–55)
U23: Quarter | V23: Revenue | W23: Adj. op. margin | X23: Compute % | Y23: Personnel % | Z23: S&M %
U24: =Historicals!B32 -> Q1 2025A | V24: =IF(Historicals!B33="",NA(),Historicals!B33) -> 376 | W24: =IF(Historicals!B33="",NA(),Historicals!B54/Historicals!B33) -> -2.2074468 | X24: =IF(Historicals!B33="",NA(),Historicals!B35/Historicals!B33) -> 2.5106383 | Y24: =IF(Historicals!B33="",NA(),Historicals!B36/Historicals!B33) -> 0.57978723 | Z24: =IF(Historicals!B33="",NA(),Historicals!B38/Historicals!B33) -> 0.063829787
U25: =Historicals!C32 -> Q2 2025A | V25: =IF(Historicals!C33="",NA(),Historicals!C33) -> 787 | W25: =IF(Historicals!C33="",NA(),Historicals!C54/Historicals!C33) -> -1.2947903 | X25: =IF(Historicals!C33="",NA(),Historicals!C35/Historicals!C33) -> 1.7662008 | Y25: =IF(Historicals!C33="",NA(),Historicals!C36/Historicals!C33) -> 0.40660737 | Z25: =IF(Historicals!C33="",NA(),Historicals!C38/Historicals!C33) -> 0.12198221
U26: =Historicals!D32 -> Q3 2025A | V26: =IF(Historicals!D33="",NA(),Historicals!D33) -> 1382 | W26: =IF(Historicals!D33="",NA(),Historicals!D54/Historicals!D33) -> -0.92908828 | X26: =IF(Historicals!D33="",NA(),Historicals!D35/Historicals!D33) -> 1.4811867 | Y26: =IF(Historicals!D33="",NA(),Historicals!D36/Historicals!D33) -> 0.35383502 | Z26: =IF(Historicals!D33="",NA(),Historicals!D38/Historicals!D33) -> 0.14616498
U27: =Historicals!E32 -> Q4 2025A | V27: =IF(Historicals!E33="",NA(),Historicals!E33) -> 2040 | W27: =IF(Historicals!E33="",NA(),Historicals!E54/Historicals!E33) -> -0.84362745 | X27: =IF(Historicals!E33="",NA(),Historicals!E35/Historicals!E33) -> 1.4436275 | Y27: =IF(Historicals!E33="",NA(),Historicals!E36/Historicals!E33) -> 0.39803922 | Z27: =IF(Historicals!E33="",NA(),Historicals!E38/Historicals!E33) -> 0.12058824
U28: =Historicals!F32 -> Q1 2026A | V28: =IF(Historicals!F33="",NA(),Historicals!F33) -> 4731 | W28: =IF(Historicals!F33="",NA(),Historicals!F54/Historicals!F33) -> -0.1304164 | X28: =IF(Historicals!F33="",NA(),Historicals!F35/Historicals!F33) -> 0.7159163 | Y28: =IF(Historicals!F33="",NA(),Historicals!F36/Historicals!F33) -> 0.27372648 | Z28: =IF(Historicals!F33="",NA(),Historicals!F38/Historicals!F33) -> 0.21834707
U29: =Historicals!G32 -> Q2 2026A | V29: =IF(Historicals!G33="",NA(),Historicals!G33) -> 11555 | W29: =IF(Historicals!G33="",NA(),Historicals!G54/Historicals!G33) -> 0.19342276 | X29: =IF(Historicals!G33="",NA(),Historicals!G35/Historicals!G33) -> 0.48100389 | Y29: =IF(Historicals!G33="",NA(),Historicals!G36/Historicals!G33) -> 0.16070965 | Z29: =IF(Historicals!G33="",NA(),Historicals!G38/Historicals!G33) -> 0.1847685
U30: =Historicals!H32 -> Q3 2026A | V30: =IF(Historicals!H33="",NA(),Historicals!H33) -> #N/A | W30: =IF(Historicals!H33="",NA(),Historicals!H54/Historicals!H33) -> #N/A | X30: =IF(Historicals!H33="",NA(),Historicals!H35/Historicals!H33) -> #N/A | Y30: =IF(Historicals!H33="",NA(),Historicals!H36/Historicals!H33) -> #N/A | Z30: =IF(Historicals!H33="",NA(),Historicals!H38/Historicals!H33) -> #N/A
U31: =Historicals!I32 -> Q4 2026A | V31: =IF(Historicals!I33="",NA(),Historicals!I33) -> #N/A | W31: =IF(Historicals!I33="",NA(),Historicals!I54/Historicals!I33) -> #N/A | X31: =IF(Historicals!I33="",NA(),Historicals!I35/Historicals!I33) -> #N/A | Y31: =IF(Historicals!I33="",NA(),Historicals!I36/Historicals!I33) -> #N/A | Z31: =IF(Historicals!I33="",NA(),Historicals!I38/Historicals!I33) -> #N/A
U32: =Historicals!J32 -> Q1 2027A | V32: =IF(Historicals!J33="",NA(),Historicals!J33) -> #N/A | W32: =IF(Historicals!J33="",NA(),Historicals!J54/Historicals!J33) -> #N/A | X32: =IF(Historicals!J33="",NA(),Historicals!J35/Historicals!J33) -> #N/A | Y32: =IF(Historicals!J33="",NA(),Historicals!J36/Historicals!J33) -> #N/A | Z32: =IF(Historicals!J33="",NA(),Historicals!J38/Historicals!J33) -> #N/A
U33: =Historicals!K32 -> Q2 2027A | V33: =IF(Historicals!K33="",NA(),Historicals!K33) -> #N/A | W33: =IF(Historicals!K33="",NA(),Historicals!K54/Historicals!K33) -> #N/A | X33: =IF(Historicals!K33="",NA(),Historicals!K35/Historicals!K33) -> #N/A | Y33: =IF(Historicals!K33="",NA(),Historicals!K36/Historicals!K33) -> #N/A | Z33: =IF(Historicals!K33="",NA(),Historicals!K38/Historicals!K33) -> #N/A
U34: =Historicals!L32 -> Q3 2027A | V34: =IF(Historicals!L33="",NA(),Historicals!L33) -> #N/A | W34: =IF(Historicals!L33="",NA(),Historicals!L54/Historicals!L33) -> #N/A | X34: =IF(Historicals!L33="",NA(),Historicals!L35/Historicals!L33) -> #N/A | Y34: =IF(Historicals!L33="",NA(),Historicals!L36/Historicals!L33) -> #N/A | Z34: =IF(Historicals!L33="",NA(),Historicals!L38/Historicals!L33) -> #N/A
U35: =Historicals!M32 -> Q4 2027A | V35: =IF(Historicals!M33="",NA(),Historicals!M33) -> #N/A | W35: =IF(Historicals!M33="",NA(),Historicals!M54/Historicals!M33) -> #N/A | X35: =IF(Historicals!M33="",NA(),Historicals!M35/Historicals!M33) -> #N/A | Y35: =IF(Historicals!M33="",NA(),Historicals!M36/Historicals!M33) -> #N/A | Z35: =IF(Historicals!M33="",NA(),Historicals!M38/Historicals!M33) -> #N/A
U36: #N/A = quarter not yet reported; keeps the charts gap-free and fills in automatically.
U37: CHART DATA 4: REVENUE BY SCENARIO (engine row 107)
U38: Year | V38: Bear | W38: Base | X38: Bull
U39: ='DCF Base'!B6 -> FY2023A | V39: ='DCF Bear'!B107 -> 41 | W39: ='DCF Base'!B107 -> 41 | X39: ='DCF Bull'!B107 -> 41
U40: ='DCF Base'!C6 -> FY2024A | V40: ='DCF Bear'!C107 -> 386 | W40: ='DCF Base'!C107 -> 386 | X40: ='DCF Bull'!C107 -> 386
U41: ='DCF Base'!D6 -> FY2025A | V41: ='DCF Bear'!D107 -> 4585 | W41: ='DCF Base'!D107 -> 4585 | X41: ='DCF Bull'!D107 -> 4585
U42: ='DCF Base'!E6 -> FY2026E | V42: ='DCF Bear'!E107 -> 51592.48 | W42: ='DCF Base'!E107 -> 54504.162 | X42: ='DCF Bull'!E107 -> 57560.46
U43: ='DCF Base'!F6 -> FY2027E | V43: ='DCF Bear'!F107 -> 86675.366 | W43: ='DCF Base'!F107 -> 113368.66 | X43: ='DCF Bull'!F107 -> 142749.94
U44: ='DCF Base'!G6 -> FY2028E | V44: ='DCF Bear'!G107 -> 116186.26 | W44: ='DCF Base'!G107 -> 180299.77 | X44: ='DCF Bull'!G107 -> 262705.94
U45: ='DCF Base'!H6 -> FY2029E | V45: ='DCF Bear'!H107 -> 141317.99 | W45: ='DCF Base'!H107 -> 251743.83 | X45: ='DCF Bull'!H107 -> 404707.59
U46: ='DCF Base'!I6 -> FY2030E | V46: ='DCF Bear'!I107 -> 163671.32 | W46: ='DCF Base'!I107 -> 326334.3 | X46: ='DCF Bull'!I107 -> 563606.7
U47: ='DCF Base'!J6 -> FY2031E | V47: ='DCF Bear'!J107 -> 183015.7 | W47: ='DCF Base'!J107 -> 403460.71 | X47: ='DCF Bull'!J107 -> 730659.63
U48: ='DCF Base'!K6 -> FY2032E | V48: ='DCF Bear'!K107 -> 200988.51 | W48: ='DCF Base'!K107 -> 478661.77 | X48: ='DCF Bull'!K107 -> 903420.73
U49: ='DCF Base'!L6 -> FY2033E | V49: ='DCF Bear'!L107 -> 216888.41 | W49: ='DCF Base'!L107 -> 548756.98 | X49: ='DCF Bull'!L107 -> 1071902.1
U50: ='DCF Base'!M6 -> FY2034E | V50: ='DCF Bear'!M107 -> 231877.99 | W50: ='DCF Base'!M107 -> 613645.02 | X50: ='DCF Bull'!M107 -> 1230833.7
U51: ='DCF Base'!N6 -> FY2035E | V51: ='DCF Bear'!N107 -> 245585.53 | W51: ='DCF Base'!N107 -> 673940.81 | X51: ='DCF Bull'!N107 -> 1376420.6
U52: ='DCF Base'!O6 -> FY2036E | V52: ='DCF Bear'!O107 -> 257648.4 | W52: ='DCF Base'!O107 -> 730060.89 | X52: ='DCF Bull'!O107 -> 1511717.1
U53: ='DCF Base'!P6 -> FY2037E | V53: ='DCF Bear'!P107 -> 269016.42 | W53: ='DCF Base'!P107 -> 780539.03 | X53: ='DCF Bull'!P107 -> 1638934.7
U54: ='DCF Base'!Q6 -> FY2038E | V54: ='DCF Bear'!Q107 -> 279541.87 | W54: ='DCF Base'!Q107 -> 826704.55 | X54: ='DCF Bull'!Q107 -> 1752279.5
U55: ='DCF Base'!R6 -> FY2039E | V55: ='DCF Bear'!R107 -> 289082.41 | W55: ='DCF Base'!R107 -> 867336.27 | X55: ='DCF Bull'!R107 -> 1855946
U56: ='DCF Base'!S6 -> FY2040E | V56: ='DCF Bear'!S107 -> 297754.88 | W56: ='DCF Base'!S107 -> 902029.72 | X56: ='DCF Bull'!S107 -> 1948743.3
U58: CHART DATA 5: COMPUTE BUILD-OUT – BASE (engine rows 80, 86)
U59: Year | V59: GW in service | W59: Owned share
U60: ='DCF Base'!D6 -> FY2025A | V60: =IF('DCF Base'!D80="",NA(),'DCF Base'!D80) -> 0.6105 | W60: =IF('DCF Base'!D86="",NA(),'DCF Base'!D86) -> #N/A
U61: ='DCF Base'!E6 -> FY2026E | V61: =IF('DCF Base'!E80="",NA(),'DCF Base'!E80) -> 2.4981074 | W61: =IF('DCF Base'!E86="",NA(),'DCF Base'!E86) -> 0.0755615
U62: ='DCF Base'!F6 -> FY2027E | V62: =IF('DCF Base'!F80="",NA(),'DCF Base'!F80) -> 4.868297 | W62: =IF('DCF Base'!F86="",NA(),'DCF Base'!F86) -> 0.1361459
U63: ='DCF Base'!G6 -> FY2028E | V63: =IF('DCF Base'!G80="",NA(),'DCF Base'!G80) -> 7.274694 | W63: =IF('DCF Base'!G86="",NA(),'DCF Base'!G86) -> 0.19034722
U64: ='DCF Base'!H6 -> FY2029E | V64: =IF('DCF Base'!H80="",NA(),'DCF Base'!H80) -> 9.584467 | W64: =IF('DCF Base'!H86="",NA(),'DCF Base'!H86) -> 0.22882215
U65: ='DCF Base'!I6 -> FY2030E | V65: =IF('DCF Base'!I80="",NA(),'DCF Base'!I80) -> 11.793368 | W65: =IF('DCF Base'!I86="",NA(),'DCF Base'!I86) -> 0.26088381
U66: ='DCF Base'!J6 -> FY2031E | V66: =IF('DCF Base'!J80="",NA(),'DCF Base'!J80) -> 14.134329 | W66: =IF('DCF Base'!J86="",NA(),'DCF Base'!J86) -> 0.28392456
U67: ='DCF Base'!K6 -> FY2032E | V67: =IF('DCF Base'!K80="",NA(),'DCF Base'!K80) -> 16.210406 | W67: =IF('DCF Base'!K86="",NA(),'DCF Base'!K86) -> 0.29879041
U68: ='DCF Base'!L6 -> FY2033E | V68: =IF('DCF Base'!L80="",NA(),'DCF Base'!L80) -> 18.173377 | W68: =IF('DCF Base'!L86="",NA(),'DCF Base'!L86) -> 0.30972242
U69: ='DCF Base'!M6 -> FY2034E | V69: =IF('DCF Base'!M80="",NA(),'DCF Base'!M80) -> 20.135866 | W69: =IF('DCF Base'!M86="",NA(),'DCF Base'!M86) -> 0.31852109
U70: ='DCF Base'!N6 -> FY2035E | V70: =IF('DCF Base'!N80="",NA(),'DCF Base'!N80) -> 21.89213 | W70: =IF('DCF Base'!N86="",NA(),'DCF Base'!N86) -> 0.32505761
U71: ='DCF Base'!O6 -> FY2036E | V71: =IF('DCF Base'!O80="",NA(),'DCF Base'!O80) -> 23.454516 | W71: =IF('DCF Base'!O86="",NA(),'DCF Base'!O86) -> 0.33004978
U72: ='DCF Base'!P6 -> FY2037E | V72: =IF('DCF Base'!P80="",NA(),'DCF Base'!P80) -> 25.181823 | W72: =IF('DCF Base'!P86="",NA(),'DCF Base'!P86) -> 0.33484791
U73: ='DCF Base'!Q6 -> FY2038E | V73: =IF('DCF Base'!Q80="",NA(),'DCF Base'!Q80) -> 27.215599 | W73: =IF('DCF Base'!Q86="",NA(),'DCF Base'!Q86) -> 0.33971661
U74: ='DCF Base'!R6 -> FY2039E | V74: =IF('DCF Base'!R80="",NA(),'DCF Base'!R80) -> 29.135837 | W74: =IF('DCF Base'!R86="",NA(),'DCF Base'!R86) -> 0.34368967
U75: ='DCF Base'!S6 -> FY2040E | V75: =IF('DCF Base'!S80="",NA(),'DCF Base'!S80) -> 30.91978 | W75: =IF('DCF Base'!S86="",NA(),'DCF Base'!S86) -> 0.34693855
U77: CHART DATA 6: VALUE PER SHARE vs ENTRY (Dashboard)
U78: Scenario | V78: Value / share | W78: Entry price
U79: =Dashboard!A9 -> Bear | V79: =Dashboard!D9 -> 30.494614 | W79: =Dashboard!$B$5 -> 58.9
U80: =Dashboard!A10 -> Base | V80: =Dashboard!D10 -> 111.87893 | W80: =Dashboard!$B$5 -> 58.9
U81: =Dashboard!A11 -> Bull | V81: =Dashboard!D11 -> 301.27484 | W81: =Dashboard!$B$5 -> 58.9
U82: Prob-weighted | V82: =Dashboard!D12 -> 138.88183 | W82: =Dashboard!$B$5 -> 58.9
U84: CHART DATA 7: UNLEVERED FCF BY SCENARIO (engine row 140)
U85: Year | V85: Bear | W85: Base | X85: Bull
U86: ='DCF Base'!E6 -> FY2026E | V86: ='DCF Bear'!E140 -> -8579.8288 | W86: ='DCF Base'!E140 -> -7691.967 | X86: ='DCF Bull'!E140 -> -5667.2398
U87: ='DCF Base'!F6 -> FY2027E | V87: ='DCF Bear'!F140 -> -5831.9997 | W87: ='DCF Base'!F140 -> -4801.4883 | X87: ='DCF Bull'!F140 -> -3764.3342
U88: ='DCF Base'!G6 -> FY2028E | V88: ='DCF Bear'!G140 -> 1686.0752 | W88: ='DCF Base'!G140 -> 3968.3714 | X88: ='DCF Bull'!G140 -> 11797.775
U89: ='DCF Base'!H6 -> FY2029E | V89: ='DCF Bear'!H140 -> 8232.3311 | W89: ='DCF Base'!H140 -> 25222.107 | X89: ='DCF Bull'!H140 -> 49598.122
U90: ='DCF Base'!I6 -> FY2030E | V90: ='DCF Bear'!I140 -> 16819.814 | W90: ='DCF Base'!I140 -> 52034.742 | X90: ='DCF Bull'!I140 -> 111790.21
U91: ='DCF Base'!J6 -> FY2031E | V91: ='DCF Bear'!J140 -> 25313.996 | W91: ='DCF Base'!J140 -> 82563.558 | X91: ='DCF Bull'!J140 -> 187317.88
U92: ='DCF Base'!K6 -> FY2032E | V92: ='DCF Bear'!K140 -> 33958.857 | W92: ='DCF Base'!K140 -> 119235.3 | X92: ='DCF Bull'!K140 -> 277574.16
U93: ='DCF Base'!L6 -> FY2033E | V93: ='DCF Bear'!L140 -> 40576.589 | W93: ='DCF Base'!L140 -> 151244.08 | X93: ='DCF Bull'!L140 -> 362979.63
U94: ='DCF Base'!M6 -> FY2034E | V94: ='DCF Bear'!M140 -> 46821.191 | W94: ='DCF Base'!M140 -> 182081.36 | X94: ='DCF Bull'!M140 -> 447992.54
U95: ='DCF Base'!N6 -> FY2035E | V95: ='DCF Bear'!N140 -> 51905.309 | W95: ='DCF Base'!N140 -> 209799.89 | X95: ='DCF Bull'!N140 -> 527791.19
U96: ='DCF Base'!O6 -> FY2036E | V96: ='DCF Bear'!O140 -> 56633.796 | W96: ='DCF Base'!O140 -> 236217.67 | X96: ='DCF Bull'!O140 -> 602989.93
U97: ='DCF Base'!P6 -> FY2037E | V97: ='DCF Bear'!P140 -> 59096.443 | W97: ='DCF Base'!P140 -> 254738.02 | X97: ='DCF Bull'!P140 -> 659173.96
U98: ='DCF Base'!Q6 -> FY2038E | V98: ='DCF Bear'!Q140 -> 60194.552 | W98: ='DCF Base'!Q140 -> 267580.94 | X98: ='DCF Bull'!Q140 -> 703261.15
U99: ='DCF Base'!R6 -> FY2039E | V99: ='DCF Bear'!R140 -> 61699.702 | W99: ='DCF Base'!R140 -> 281882.38 | X99: ='DCF Bull'!R140 -> 750322.45
A100: Created by: Rifat Tahmid | U100: ='DCF Base'!S6 -> FY2040E | V100: ='DCF Bear'!S140 -> 62798.404 | W100: ='DCF Base'!S140 -> 293683.2 | X100: ='DCF Bull'!S140 -> 792501.33

Sheet DCF Base
A1: Anthropic ($ANT) – DCF Valuation Engine (Scenario engine)
A2: Form S-1 filed 26-Oct-2026 | 15-Year Explicit Forecast FY2026E–FY2040E | $ in Millions except per share | Intrinsic value
A3: Identical engine on DCF Bear / DCF Base / DCF Bull – only B5 differs. Do not edit formulas on one engine without copying to the other two.
A5: SCENARIO INDEX | B5: 2 | C5: =CHOOSE(B5,"◀ BEAR","◀ BASE","◀ BULL") -> ◀ BASE | D5: (1 = Bear | 2 = Base | 3 = Bull)
A6: ($ in Millions) | B6: FY2023A | C6: FY2024A | D6: FY2025A | E6: FY2026E | F6: FY2027E | G6: FY2028E | H6: FY2029E | I6: FY2030E | J6: FY2031E | K6: FY2032E | L6: FY2033E | M6: FY2034E | N6: FY2035E | O6: FY2036E | P6: FY2037E | Q6: FY2038E | R6: FY2039E | S6: FY2040E
A8: SELECTED CASE ASSUMPTIONS (auto-pulled from Drivers by scenario index in B5)
A9: Q3 2026 revenue growth (QoQ) | E9: =CHOOSE($B$5,Drivers!E23,Drivers!E54,Drivers!E85) -> 0.47
A10: Q4 2026 revenue growth (QoQ) | E10: =CHOOSE($B$5,Drivers!E24,Drivers!E55,Drivers!E86) -> 0.25
A11: Subscription mix % of FY2026E revenue | E11: =CHOOSE($B$5,Drivers!E25,Drivers!E56,Drivers!E87) -> 0.2
A12: Consumption-based revenue growth (YoY) | F12: =CHOOSE($B$5,Drivers!F26,Drivers!F57,Drivers!F88) -> 1.1 | G12: =CHOOSE($B$5,Drivers!G26,Drivers!G57,Drivers!G88) -> 0.6 | H12: =CHOOSE($B$5,Drivers!H26,Drivers!H57,Drivers!H88) -> 0.4 | I12: =CHOOSE($B$5,Drivers!I26,Drivers!I57,Drivers!I88) -> 0.3 | J12: =CHOOSE($B$5,Drivers!J26,Drivers!J57,Drivers!J88) -> 0.24 | K12: =CHOOSE($B$5,Drivers!K26,Drivers!K57,Drivers!K88) -> 0.19 | L12: =CHOOSE($B$5,Drivers!L26,Drivers!L57,Drivers!L88) -> 0.15 | M12: =CHOOSE($B$5,Drivers!M26,Drivers!M57,Drivers!M88) -> 0.12 | ... S12: =CHOOSE($B$5,Drivers!S26,Drivers!S57,Drivers!S88) -> 0.04
A13: Subscription-based revenue growth (YoY) | F13: =CHOOSE($B$5,Drivers!F27,Drivers!F58,Drivers!F89) -> 1 | G13: =CHOOSE($B$5,Drivers!G27,Drivers!G58,Drivers!G89) -> 0.55 | H13: =CHOOSE($B$5,Drivers!H27,Drivers!H58,Drivers!H89) -> 0.38 | I13: =CHOOSE($B$5,Drivers!I27,Drivers!I58,Drivers!I89) -> 0.28 | J13: =CHOOSE($B$5,Drivers!J27,Drivers!J58,Drivers!J89) -> 0.22 | K13: =CHOOSE($B$5,Drivers!K27,Drivers!K58,Drivers!K89) -> 0.17 | L13: =CHOOSE($B$5,Drivers!L27,Drivers!L58,Drivers!L89) -> 0.13 | M13: =CHOOSE($B$5,Drivers!M27,Drivers!M58,Drivers!M89) -> 0.11 | ... S13: =CHOOSE($B$5,Drivers!S27,Drivers!S58,Drivers!S89) -> 0.04
A14: International % of revenue | E14: =CHOOSE($B$5,Drivers!E28,Drivers!E59,Drivers!E90) -> 0.28 | F14: =CHOOSE($B$5,Drivers!F28,Drivers!F59,Drivers!F90) -> 0.29 | G14: =CHOOSE($B$5,Drivers!G28,Drivers!G59,Drivers!G90) -> 0.3 | H14: =CHOOSE($B$5,Drivers!H28,Drivers!H59,Drivers!H90) -> 0.31 | I14: =CHOOSE($B$5,Drivers!I28,Drivers!I59,Drivers!I90) -> 0.32 | J14: =CHOOSE($B$5,Drivers!J28,Drivers!J59,Drivers!J90) -> 0.33 | K14: =CHOOSE($B$5,Drivers!K28,Drivers!K59,Drivers!K90) -> 0.34 | L14: =CHOOSE($B$5,Drivers!L28,Drivers!L59,Drivers!L90) -> 0.35 | ... S14: =CHOOSE($B$5,Drivers!S28,Drivers!S59,Drivers!S90) -> 0.4
A15: Enterprise customers (≥$100K) growth | E15: =CHOOSE($B$5,Drivers!E29,Drivers!E60,Drivers!E91) -> 9 | F15: =CHOOSE($B$5,Drivers!F29,Drivers!F60,Drivers!F91) -> 1 | G15: =CHOOSE($B$5,Drivers!G29,Drivers!G60,Drivers!G91) -> 0.6 | H15: =CHOOSE($B$5,Drivers!H29,Drivers!H60,Drivers!H91) -> 0.4 | I15: =CHOOSE($B$5,Drivers!I29,Drivers!I60,Drivers!I91) -> 0.3 | J15: =CHOOSE($B$5,Drivers!J29,Drivers!J60,Drivers!J91) -> 0.22 | K15: =CHOOSE($B$5,Drivers!K29,Drivers!K60,Drivers!K91) -> 0.17 | L15: =CHOOSE($B$5,Drivers!L29,Drivers!L60,Drivers!L91) -> 0.13 | ... S15: =CHOOSE($B$5,Drivers!S29,Drivers!S60,Drivers!S91) -> 0.03
A16: Enterprise (≥$100K) share of revenue | E16: =CHOOSE($B$5,Drivers!E30,Drivers!E61,Drivers!E92) -> 0.78 | F16: =CHOOSE($B$5,Drivers!F30,Drivers!F61,Drivers!F92) -> 0.79 | G16: =CHOOSE($B$5,Drivers!G30,Drivers!G61,Drivers!G92) -> 0.8 | H16: =CHOOSE($B$5,Drivers!H30,Drivers!H61,Drivers!H92) -> 0.81 | I16: =CHOOSE($B$5,Drivers!I30,Drivers!I61,Drivers!I92) -> 0.82 | J16: =CHOOSE($B$5,Drivers!J30,Drivers!J61,Drivers!J92) -> 0.83 | K16: =CHOOSE($B$5,Drivers!K30,Drivers!K61,Drivers!K92) -> 0.84 | L16: =CHOOSE($B$5,Drivers!L30,Drivers!L61,Drivers!L92) -> 0.85 | ... S16: =CHOOSE($B$5,Drivers!S30,Drivers!S61,Drivers!S92) -> 0.85
A17: Inference / serving compute % of revenue | E17: =CHOOSE($B$5,Drivers!E31,Drivers!E62,Drivers!E93) -> 0.3 | F17: =CHOOSE($B$5,Drivers!F31,Drivers!F62,Drivers!F93) -> 0.285 | G17: =CHOOSE($B$5,Drivers!G31,Drivers!G62,Drivers!G93) -> 0.27 | H17: =CHOOSE($B$5,Drivers!H31,Drivers!H62,Drivers!H93) -> 0.255 | I17: =CHOOSE($B$5,Drivers!I31,Drivers!I62,Drivers!I93) -> 0.24 | J17: =CHOOSE($B$5,Drivers!J31,Drivers!J62,Drivers!J93) -> 0.23 | K17: =CHOOSE($B$5,Drivers!K31,Drivers!K62,Drivers!K93) -> 0.22 | L17: =CHOOSE($B$5,Drivers!L31,Drivers!L62,Drivers!L93) -> 0.215 | ... S17: =CHOOSE($B$5,Drivers!S31,Drivers!S62,Drivers!S93) -> 0.2
A18: Training & research compute % of revenue | E18: =CHOOSE($B$5,Drivers!E32,Drivers!E63,Drivers!E94) -> 0.25 | F18: =CHOOSE($B$5,Drivers!F32,Drivers!F63,Drivers!F94) -> 0.22 | G18: =CHOOSE($B$5,Drivers!G32,Drivers!G63,Drivers!G94) -> 0.195 | H18: =CHOOSE($B$5,Drivers!H32,Drivers!H63,Drivers!H94) -> 0.175 | I18: =CHOOSE($B$5,Drivers!I32,Drivers!I63,Drivers!I94) -> 0.16 | J18: =CHOOSE($B$5,Drivers!J32,Drivers!J63,Drivers!J94) -> 0.15 | K18: =CHOOSE($B$5,Drivers!K32,Drivers!K63,Drivers!K94) -> 0.14 | L18: =CHOOSE($B$5,Drivers!L32,Drivers!L63,Drivers!L94) -> 0.13 | ... S18: =CHOOSE($B$5,Drivers!S32,Drivers!S63,Drivers!S94) -> 0.11
A19: Rental-equivalent compute cost per GW-year ($M) | E19: =CHOOSE($B$5,Drivers!E33,Drivers!E64,Drivers!E95) -> 12000 | F19: =CHOOSE($B$5,Drivers!F33,Drivers!F64,Drivers!F95) -> 11760 | G19: =CHOOSE($B$5,Drivers!G33,Drivers!G64,Drivers!G95) -> 11524.8 | H19: =CHOOSE($B$5,Drivers!H33,Drivers!H64,Drivers!H95) -> 11294.3 | I19: =CHOOSE($B$5,Drivers!I33,Drivers!I64,Drivers!I95) -> 11068.4 | J19: =CHOOSE($B$5,Drivers!J33,Drivers!J64,Drivers!J95) -> 10847 | K19: =CHOOSE($B$5,Drivers!K33,Drivers!K64,Drivers!K95) -> 10630.1 | L19: =CHOOSE($B$5,Drivers!L33,Drivers!L64,Drivers!L95) -> 10417.5 | ... S19: =CHOOSE($B$5,Drivers!S33,Drivers!S64,Drivers!S95) -> 9043.7
A20: Accelerators per GW (000s) | E20: =CHOOSE($B$5,Drivers!E34,Drivers!E65,Drivers!E96) -> 650 | F20: =CHOOSE($B$5,Drivers!F34,Drivers!F65,Drivers!F96) -> 630.5 | G20: =CHOOSE($B$5,Drivers!G34,Drivers!G65,Drivers!G96) -> 611.6 | H20: =CHOOSE($B$5,Drivers!H34,Drivers!H65,Drivers!H96) -> 593.2 | I20: =CHOOSE($B$5,Drivers!I34,Drivers!I65,Drivers!I96) -> 575.4 | J20: =CHOOSE($B$5,Drivers!J34,Drivers!J65,Drivers!J96) -> 558.2 | K20: =CHOOSE($B$5,Drivers!K34,Drivers!K65,Drivers!K96) -> 541.4 | L20: =CHOOSE($B$5,Drivers!L34,Drivers!L65,Drivers!L96) -> 525.2 | ... S20: =CHOOSE($B$5,Drivers!S34,Drivers!S65,Drivers!S96) -> 424.3
A21: Anthropic Direct share of new capacity | E21: =CHOOSE($B$5,Drivers!E35,Drivers!E66,Drivers!E97) -> 0.1 | F21: =CHOOSE($B$5,Drivers!F35,Drivers!F66,Drivers!F97) -> 0.2 | G21: =CHOOSE($B$5,Drivers!G35,Drivers!G66,Drivers!G97) -> 0.3 | H21: =CHOOSE($B$5,Drivers!H35,Drivers!H66,Drivers!H97) -> 0.35 | I21: =CHOOSE($B$5,Drivers!I35,Drivers!I66,Drivers!I97) -> 0.4 | J21: =CHOOSE($B$5,Drivers!J35,Drivers!J66,Drivers!J97) -> 0.4 | K21: =CHOOSE($B$5,Drivers!K35,Drivers!K66,Drivers!K97) -> 0.4 | L21: =CHOOSE($B$5,Drivers!L35,Drivers!L66,Drivers!L97) -> 0.4 | ... S21: =CHOOSE($B$5,Drivers!S35,Drivers!S66,Drivers!S97) -> 0.4
A22: Capex per owned GW ($M) | E22: =CHOOSE($B$5,Drivers!E36,Drivers!E67,Drivers!E98) -> 40000 | F22: =CHOOSE($B$5,Drivers!F36,Drivers!F67,Drivers!F98) -> 38400 | G22: =CHOOSE($B$5,Drivers!G36,Drivers!G67,Drivers!G98) -> 36864 | H22: =CHOOSE($B$5,Drivers!H36,Drivers!H67,Drivers!H98) -> 35389.4 | I22: =CHOOSE($B$5,Drivers!I36,Drivers!I67,Drivers!I98) -> 33973.9 | J22: =CHOOSE($B$5,Drivers!J36,Drivers!J67,Drivers!J98) -> 32614.9 | K22: =CHOOSE($B$5,Drivers!K36,Drivers!K67,Drivers!K98) -> 31310.3 | L22: =CHOOSE($B$5,Drivers!L36,Drivers!L67,Drivers!L98) -> 30057.9 | ... S22: =CHOOSE($B$5,Drivers!S36,Drivers!S67,Drivers!S98) -> 22586.9
A23: Power & ops cost per owned GW-year ($M) | E23: =CHOOSE($B$5,Drivers!E37,Drivers!E68,Drivers!E99) -> 2000 | F23: =CHOOSE($B$5,Drivers!F37,Drivers!F68,Drivers!F99) -> 2040 | G23: =CHOOSE($B$5,Drivers!G37,Drivers!G68,Drivers!G99) -> 2080.8 | H23: =CHOOSE($B$5,Drivers!H37,Drivers!H68,Drivers!H99) -> 2122.4 | I23: =CHOOSE($B$5,Drivers!I37,Drivers!I68,Drivers!I99) -> 2164.9 | J23: =CHOOSE($B$5,Drivers!J37,Drivers!J68,Drivers!J99) -> 2208.2 | K23: =CHOOSE($B$5,Drivers!K37,Drivers!K68,Drivers!K99) -> 2252.3 | L23: =CHOOSE($B$5,Drivers!L37,Drivers!L68,Drivers!L99) -> 2297.4 | ... S23: =CHOOSE($B$5,Drivers!S37,Drivers!S68,Drivers!S99) -> 2639
A24: Owned accelerator useful life (years) | E24: =CHOOSE($B$5,Drivers!E38,Drivers!E69,Drivers!E100) -> 5
A25: Headcount – FY2026E period end | E25: =CHOOSE($B$5,Drivers!E39,Drivers!E70,Drivers!E101) -> 6000
A26: Headcount growth (YoY) | F26: =CHOOSE($B$5,Drivers!F40,Drivers!F71,Drivers!F102) -> 0.35 | G26: =CHOOSE($B$5,Drivers!G40,Drivers!G71,Drivers!G102) -> 0.28 | H26: =CHOOSE($B$5,Drivers!H40,Drivers!H71,Drivers!H102) -> 0.22 | I26: =CHOOSE($B$5,Drivers!I40,Drivers!I71,Drivers!I102) -> 0.18 | J26: =CHOOSE($B$5,Drivers!J40,Drivers!J71,Drivers!J102) -> 0.15 | K26: =CHOOSE($B$5,Drivers!K40,Drivers!K71,Drivers!K102) -> 0.12 | L26: =CHOOSE($B$5,Drivers!L40,Drivers!L71,Drivers!L102) -> 0.1 | M26: =CHOOSE($B$5,Drivers!M40,Drivers!M71,Drivers!M102) -> 0.08 | ... S26: =CHOOSE($B$5,Drivers!S40,Drivers!S71,Drivers!S102) -> 0.035
A27: Personnel cost per head – FY2026E ($M) | E27: =CHOOSE($B$5,Drivers!E41,Drivers!E72,Drivers!E103) -> 1.5
A28: Personnel cost per head growth | F28: =CHOOSE($B$5,Drivers!F42,Drivers!F73,Drivers!F104) -> 0.05 | G28: =CHOOSE($B$5,Drivers!G42,Drivers!G73,Drivers!G104) -> 0.05 | H28: =CHOOSE($B$5,Drivers!H42,Drivers!H73,Drivers!H104) -> 0.05 | I28: =CHOOSE($B$5,Drivers!I42,Drivers!I73,Drivers!I104) -> 0.05 | J28: =CHOOSE($B$5,Drivers!J42,Drivers!J73,Drivers!J104) -> 0.04 | K28: =CHOOSE($B$5,Drivers!K42,Drivers!K73,Drivers!K104) -> 0.04 | L28: =CHOOSE($B$5,Drivers!L42,Drivers!L73,Drivers!L104) -> 0.04 | M28: =CHOOSE($B$5,Drivers!M42,Drivers!M73,Drivers!M104) -> 0.04 | ... S28: =CHOOSE($B$5,Drivers!S42,Drivers!S73,Drivers!S104) -> 0.04
A29: SBC % of personnel | E29: =CHOOSE($B$5,Drivers!E43,Drivers!E74,Drivers!E105) -> 0.65 | F29: =CHOOSE($B$5,Drivers!F43,Drivers!F74,Drivers!F105) -> 0.6 | G29: =CHOOSE($B$5,Drivers!G43,Drivers!G74,Drivers!G105) -> 0.55 | H29: =CHOOSE($B$5,Drivers!H43,Drivers!H74,Drivers!H105) -> 0.5 | I29: =CHOOSE($B$5,Drivers!I43,Drivers!I74,Drivers!I105) -> 0.46 | J29: =CHOOSE($B$5,Drivers!J43,Drivers!J74,Drivers!J105) -> 0.42 | K29: =CHOOSE($B$5,Drivers!K43,Drivers!K74,Drivers!K105) -> 0.4 | L29: =CHOOSE($B$5,Drivers!L43,Drivers!L74,Drivers!L105) -> 0.38 | ... S29: =CHOOSE($B$5,Drivers!S43,Drivers!S74,Drivers!S105) -> 0.3
A30: Sales, marketing & partnerships % of revenue | E30: =CHOOSE($B$5,Drivers!E44,Drivers!E75,Drivers!E106) -> 0.19 | F30: =CHOOSE($B$5,Drivers!F44,Drivers!F75,Drivers!F106) -> 0.17 | G30: =CHOOSE($B$5,Drivers!G44,Drivers!G75,Drivers!G106) -> 0.155 | H30: =CHOOSE($B$5,Drivers!H44,Drivers!H75,Drivers!H106) -> 0.145 | I30: =CHOOSE($B$5,Drivers!I44,Drivers!I75,Drivers!I106) -> 0.135 | J30: =CHOOSE($B$5,Drivers!J44,Drivers!J75,Drivers!J106) -> 0.125 | K30: =CHOOSE($B$5,Drivers!K44,Drivers!K75,Drivers!K106) -> 0.12 | L30: =CHOOSE($B$5,Drivers!L44,Drivers!L75,Drivers!L106) -> 0.115 | ... S30: =CHOOSE($B$5,Drivers!S44,Drivers!S75,Drivers!S106) -> 0.11
A31: Other operating & admin % of revenue | E31: =CHOOSE($B$5,Drivers!E45,Drivers!E76,Drivers!E107) -> 0.1 | F31: =CHOOSE($B$5,Drivers!F45,Drivers!F76,Drivers!F107) -> 0.09 | G31: =CHOOSE($B$5,Drivers!G45,Drivers!G76,Drivers!G107) -> 0.08 | H31: =CHOOSE($B$5,Drivers!H45,Drivers!H76,Drivers!H107) -> 0.075 | I31: =CHOOSE($B$5,Drivers!I45,Drivers!I76,Drivers!I107) -> 0.07 | J31: =CHOOSE($B$5,Drivers!J45,Drivers!J76,Drivers!J107) -> 0.065 | K31: =CHOOSE($B$5,Drivers!K45,Drivers!K76,Drivers!K107) -> 0.06 | L31: =CHOOSE($B$5,Drivers!L45,Drivers!L76,Drivers!L107) -> 0.06 | ... S31: =CHOOSE($B$5,Drivers!S45,Drivers!S76,Drivers!S107) -> 0.055
A32: Other (non-compute) capex % of revenue | E32: =CHOOSE($B$5,Drivers!E46,Drivers!E77,Drivers!E108) -> 0.01 | F32: =CHOOSE($B$5,Drivers!F46,Drivers!F77,Drivers!F108) -> 0.01 | G32: =CHOOSE($B$5,Drivers!G46,Drivers!G77,Drivers!G108) -> 0.01 | H32: =CHOOSE($B$5,Drivers!H46,Drivers!H77,Drivers!H108) -> 0.01 | I32: =CHOOSE($B$5,Drivers!I46,Drivers!I77,Drivers!I108) -> 0.01 | J32: =CHOOSE($B$5,Drivers!J46,Drivers!J77,Drivers!J108) -> 0.01 | K32: =CHOOSE($B$5,Drivers!K46,Drivers!K77,Drivers!K108) -> 0.01 | L32: =CHOOSE($B$5,Drivers!L46,Drivers!L77,Drivers!L108) -> 0.01 | ... S32: =CHOOSE($B$5,Drivers!S46,Drivers!S77,Drivers!S108) -> 0.01
A33: Other D&A % of revenue | E33: =CHOOSE($B$5,Drivers!E47,Drivers!E78,Drivers!E109) -> 0.005 | F33: =CHOOSE($B$5,Drivers!F47,Drivers!F78,Drivers!F109) -> 0.005 | G33: =CHOOSE($B$5,Drivers!G47,Drivers!G78,Drivers!G109) -> 0.005 | H33: =CHOOSE($B$5,Drivers!H47,Drivers!H78,Drivers!H109) -> 0.005 | I33: =CHOOSE($B$5,Drivers!I47,Drivers!I78,Drivers!I109) -> 0.005 | J33: =CHOOSE($B$5,Drivers!J47,Drivers!J78,Drivers!J109) -> 0.005 | K33: =CHOOSE($B$5,Drivers!K47,Drivers!K78,Drivers!K109) -> 0.005 | L33: =CHOOSE($B$5,Drivers!L47,Drivers!L78,Drivers!L109) -> 0.005 | ... S33: =CHOOSE($B$5,Drivers!S47,Drivers!S78,Drivers!S109) -> 0.005
A34: ΔNWC % of Δrevenue | E34: =CHOOSE($B$5,Drivers!E48,Drivers!E79,Drivers!E110) -> 0.03 | F34: =CHOOSE($B$5,Drivers!F48,Drivers!F79,Drivers!F110) -> 0.03 | G34: =CHOOSE($B$5,Drivers!G48,Drivers!G79,Drivers!G110) -> 0.03 | H34: =CHOOSE($B$5,Drivers!H48,Drivers!H79,Drivers!H110) -> 0.03 | I34: =CHOOSE($B$5,Drivers!I48,Drivers!I79,Drivers!I110) -> 0.03 | J34: =CHOOSE($B$5,Drivers!J48,Drivers!J79,Drivers!J110) -> 0.03 | K34: =CHOOSE($B$5,Drivers!K48,Drivers!K79,Drivers!K110) -> 0.03 | L34: =CHOOSE($B$5,Drivers!L48,Drivers!L79,Drivers!L110) -> 0.03 | ... S34: =CHOOSE($B$5,Drivers!S48,Drivers!S79,Drivers!S110) -> 0.03
A35: Terminal growth rate | E35: =CHOOSE($B$5,Drivers!E49,Drivers!E80,Drivers!E111) -> 0.035
A36: Exit EV / EBITDA multiple | E36: =CHOOSE($B$5,Drivers!E50,Drivers!E81,Drivers!E112) -> 14
A37: Scenario probability weight | E37: =CHOOSE($B$5,Drivers!E51,Drivers!E82,Drivers!E113) -> 0.5
A38: WACC (WACC tab) | E38: =CHOOSE($B$5,WACC!B27,WACC!B28,WACC!B29) -> 0.13367493
A39: Terminal-period WACC (mature stage, WACC tab) | E39: =CHOOSE($B$5,WACC!F27,WACC!F28,WACC!F29) -> 0.10015294
A40: Cash tax rate | E40: =WACC!B9 -> 0.23
A42: FY2026 YEAR-TO-DATE ACTUALS (Historicals column named in Actuals!B5 – re-points automatically)
A43: YTD revenue | E43: =INDEX(Historicals!$B$7:$K$7,MATCH(Actuals!$B$5,Historicals!$B$6:$K$6,0)) -> 16286
A44: YTD compute & infrastructure | E44: =INDEX(Historicals!$B$9:$K$9,MATCH(Actuals!$B$5,Historicals!$B$6:$K$6,0)) -> 8945
A45: YTD personnel | E45: =INDEX(Historicals!$B$10:$K$10,MATCH(Actuals!$B$5,Historicals!$B$6:$K$6,0)) -> 3152
A46: YTD sales, marketing & partnerships | E46: =INDEX(Historicals!$B$12:$K$12,MATCH(Actuals!$B$5,Historicals!$B$6:$K$6,0)) -> 3168
A47: YTD other operating & administrative | E47: =INDEX(Historicals!$B$13:$K$13,MATCH(Actuals!$B$5,Historicals!$B$6:$K$6,0)) -> 1714
A48: YTD stock-based compensation | E48: =INDEX(Historicals!$B$25:$K$25,MATCH(Actuals!$B$5,Historicals!$B$6:$K$6,0)) -> 2185
A49: YTD depreciation & amortization | E49: =INDEX(Historicals!$B$26:$K$26,MATCH(Actuals!$B$5,Historicals!$B$6:$K$6,0)) -> 97
A50: YTD fraction of fiscal year | E50: =Actuals!$B$6/12 -> 0.5
A51: Remaining FY2026E revenue (full year − YTD) | E51: =E65-E43 -> 38218.162
A52: YTD unlevered FCF proxy (CFO − capex − after-tax interest income) | E52: =INDEX(Historicals!$B$128:$K$128,MATCH(Actuals!$B$5,Historicals!$B$113:$K$113,0))+INDEX(Historicals!$B$130:$K$130,MATCH(Actuals!$B$5,Historicals!$B$113:$K$113,0))-INDEX(Historicals!$B$16:$K$16,MATCH(Actuals!$B$5,Historicals!$B$6:$K$6,0))*(1-$E$40) -> 2591.53
A54: FY2026E QUARTERLY REVENUE BUILD (reported quarters override estimates)
A55: Quarter | B55: Q1 2026 | C55: Q2 2026 | D55: Q3 2026 | E55: Q4 2026 | F55: FY2026E
A56: Reported revenue (Historicals) | B56: =IFERROR(IF(INDEX(Historicals!$B$33:$M$33,MATCH(B$55&"A",Historicals!$B$32:$M$32,0))="","",INDEX(Historicals!$B$33:$M$33,MATCH(B$55&"A",Historicals!$B$32:$M$32,0))),"") -> 4731 | C56: =IFERROR(IF(INDEX(Historicals!$B$33:$M$33,MATCH(C$55&"A",Historicals!$B$32:$M$32,0))="","",INDEX(Historicals!$B$33:$M$33,MATCH(C$55&"A",Historicals!$B$32:$M$32,0))),"") -> 11555 | D56: =IFERROR(IF(INDEX(Historicals!$B$33:$M$33,MATCH(D$55&"A",Historicals!$B$32:$M$32,0))="","",INDEX(Historicals!$B$33:$M$33,MATCH(D$55&"A",Historicals!$B$32:$M$32,0))),"") | E56: =IFERROR(IF(INDEX(Historicals!$B$33:$M$33,MATCH(E$55&"A",Historicals!$B$32:$M$32,0))="","",INDEX(Historicals!$B$33:$M$33,MATCH(E$55&"A",Historicals!$B$32:$M$32,0))),"")
A57: QoQ growth (actual if reported, else driver) | B57: =IF(B56<>"",B56/Historicals!$E$33-1,0) -> 1.3191176 | C57: =IF(C56<>"",C56/B58-1,0) -> 1.4424012 | D57: =IF(D56<>"",D56/C58-1,$E$9) -> 0.47 | E57: =IF(E56<>"",E56/D58-1,$E$10) -> 0.25
A58: Revenue – selected | B58: =IF(B56<>"",B56,Historicals!$E$33*(1+B57)) -> 4731 | C58: =IF(C56<>"",C56,B58*(1+C57)) -> 11555 | D58: =IF(D56<>"",D56,C58*(1+D57)) -> 16985.85 | E58: =IF(E56<>"",E56,D58*(1+E57)) -> 21232.312 | F58: =SUM(B58:E58) -> 54504.162
A59: Status | B59: =IF(B56<>"","Actual","Estimate") -> Actual | C59: =IF(C56<>"","Actual","Estimate") -> Actual | D59: =IF(D56<>"","Actual","Estimate") -> Estimate | E59: =IF(E56<>"","Actual","Estimate") -> Estimate
A60: Annualised revenue run-rate (quarter × 4) | B60: =B58*4 -> 18924 | C60: =C58*4 -> 46220 | D60: =D58*4 -> 67943.4 | E60: =E58*4 -> 84929.25
A62: REVENUE BUILD – by pricing model, geography and customer cohort ($M)
A63: Consumption-based revenue (API / platform / pay-for-intelligence) | B63: =Historicals!B72 -> 39 | C63: =Historicals!C72 -> 288 | D63: =Historicals!D72 -> 3796 | E63: =E65-E64 -> 43603.33 | F63: =E63*(1+F12) -> 91566.993 | G63: =F63*(1+G12) -> 146507.19 | H63: =G63*(1+H12) -> 205110.06 | I63: =H63*(1+I12) -> 266643.08 | J63: =I63*(1+J12) -> 330637.42 | K63: =J63*(1+K12) -> 393458.53 | L63: =K63*(1+L12) -> 452477.31 | M63: =L63*(1+M12) -> 506774.59 | ... S63: =R63*(1+S12) -> 749116.8
A64: Subscription-based revenue (Pro / Max / Team / Enterprise) | B64: =Historicals!B73 -> 2 | C64: =Historicals!C73 -> 98 | D64: =Historicals!D73 -> 789 | E64: =E65*E11 -> 10900.833 | F64: =E64*(1+F13) -> 21801.665 | G64: =F64*(1+G13) -> 33792.581 | H64: =G64*(1+H13) -> 46633.761 | I64: =H64*(1+I13) -> 59691.215 | J64: =I64*(1+J13) -> 72823.282 | K64: =J64*(1+K13) -> 85203.24 | L64: =K64*(1+L13) -> 96279.661 | M64: =L64*(1+M13) -> 106870.42 | ... S64: =R64*(1+S13) -> 152912.92
A65: Total Revenue | B65: =Historicals!B7 -> 41 | C65: =Historicals!C7 -> 386 | D65: =Historicals!D7 -> 4585 | E65: =F58 -> 54504.162 | F65: =F63+F64 -> 113368.66 | G65: =G63+G64 -> 180299.77 | H65: =H63+H64 -> 251743.83 | I65: =I63+I64 -> 326334.3 | J65: =J63+J64 -> 403460.71 | K65: =K63+K64 -> 478661.77 | L65: =L63+L64 -> 548756.98 | M65: =M63+M64 -> 613645.02 | ... S65: =S63+S64 -> 902029.72
A66: % YoY growth | C66: =C65/B65-1 -> 8.4146341 | D66: =D65/C65-1 -> 10.878238 | E66: =E65/D65-1 -> 10.887495 | F66: =F65/E65-1 -> 1.08 | G66: =G65/F65-1 -> 0.59038462 | H66: =H65/G65-1 -> 0.39625151 | I66: =I65/H65-1 -> 0.29629514 | J66: =J65/I65-1 -> 0.23634171 | ... S66: =S65/R65-1 -> 0.04
A67: Subscription mix % | B67: =B64/B65 -> 0.048780488 | C67: =C64/C65 -> 0.25388601 | D67: =D64/D65 -> 0.17208288 | E67: =E64/E65 -> 0.2 | F67: =F64/F65 -> 0.19230769 | G67: =G64/G65 -> 0.18742443 | H67: =H64/H65 -> 0.18524292 | I67: =I64/I65 -> 0.18291432 | ... S67: =S64/S65 -> 0.16952094
A68: United States revenue | B68: =Historicals!B69 -> 34 | C68: =Historicals!C69 -> 263 | D68: =Historicals!D69 -> 3362 | E68: =E65*(1-E14) -> 39242.997 | F68: =F65*(1-F14) -> 80491.747 | G68: =G65*(1-G14) -> 126209.84 | H68: =H65*(1-H14) -> 173703.24 | I68: =I65*(1-I14) -> 221907.32 | J68: =J65*(1-J14) -> 270318.67 | K68: =K65*(1-K14) -> 315916.77 | L68: =L65*(1-L14) -> 356692.03 | ... S68: =S65*(1-S14) -> 541217.83
A69: International revenue | B69: =Historicals!B70 -> 7 | C69: =Historicals!C70 -> 123 | D69: =Historicals!D70 -> 1223 | E69: =E65*E14 -> 15261.166 | F69: =F65*F14 -> 32876.911 | G69: =G65*G14 -> 54089.931 | H69: =H65*H14 -> 78040.586 | I69: =I65*I14 -> 104426.98 | J69: =J65*J14 -> 133142.03 | K69: =K65*K14 -> 162745 | L69: =L65*L14 -> 192064.94 | ... S69: =S65*S14 -> 360811.89
A70: Enterprise customers ≥$100K TTM (period end, #) | D70: =Historicals!E168 -> 1500 | E70: =D70*(1+E15) -> 15000 | F70: =E70*(1+F15) -> 30000 | G70: =F70*(1+G15) -> 48000 | H70: =G70*(1+H15) -> 67200 | I70: =H70*(1+I15) -> 87360 | J70: =I70*(1+J15) -> 106579.2 | K70: =J70*(1+K15) -> 124697.66 | L70: =K70*(1+L15) -> 140908.36 | ... S70: =R70*(1+S15) -> 206566.21
A71: Enterprise cohort revenue (≥$100K customers) | E71: =E65*E16 -> 42513.247 | F71: =F65*F16 -> 89561.24 | G71: =G65*G16 -> 144239.82 | H71: =H65*H16 -> 203912.5 | I71: =I65*I16 -> 267594.12 | J71: =J65*J16 -> 334872.39 | K71: =K65*K16 -> 402075.89 | L71: =L65*L16 -> 466443.43 | ... S71: =S65*S16 -> 766725.27
A72: Avg revenue per enterprise customer ($M) | E72: =E71/AVERAGE(D70,E70) -> 5.1531208 | F72: =F71/AVERAGE(E70,F70) -> 3.9804995 | G72: =G71/AVERAGE(F70,G70) -> 3.6984568 | H72: =H71/AVERAGE(G70,H70) -> 3.5401475 | I72: =I71/AVERAGE(H70,I70) -> 3.4626569 | J72: =J71/AVERAGE(I70,J70) -> 3.4533749 | K72: =K71/AVERAGE(J70,K70) -> 3.4770092 | L72: =L71/AVERAGE(K70,L70) -> 3.5122956 | ... S72: =S71/AVERAGE(R70,S70) -> 3.7666189
A73: Long-tail revenue (<$100K customers) | E73: =E65-E71 -> 11990.916 | F73: =F65-F71 -> 23807.418 | G73: =G65-G71 -> 36059.954 | H73: =H65-H71 -> 47831.327 | I73: =I65-I71 -> 58740.174 | J73: =J65-J71 -> 68588.32 | K73: =K65-K71 -> 76585.884 | L73: =L65-L71 -> 82313.546 | ... S73: =S65-S71 -> 135304.46
A75: COMPUTE & GPU CAPACITY BUILD – inference vs training, GW, accelerators, owned vs rented
A76: Inference / serving compute need ($M, rental-equivalent) | E76: =E65*E17 -> 16351.249 | F76: =F65*F17 -> 32310.068 | G76: =G65*G17 -> 48680.938 | H76: =H65*H17 -> 64194.676 | I76: =I65*I17 -> 78320.232 | J76: =J65*J17 -> 92795.962 | K76: =K65*K17 -> 105305.59 | L76: =L65*L17 -> 117982.75 | ... S76: =S65*S17 -> 180405.94
A77: Training & research compute need ($M, rental-equivalent) | E77: =E65*E18 -> 13626.041 | F77: =F65*F18 -> 24941.105 | G77: =G65*G18 -> 35158.455 | H77: =H65*H18 -> 44055.17 | I77: =I65*I18 -> 52213.488 | J77: =J65*J18 -> 60519.106 | K77: =K65*K18 -> 67012.648 | L77: =L65*L18 -> 71338.407 | ... S77: =S65*S18 -> 99223.27
A78: Total compute need ($M) [hist = reported compute & infra] | B78: =Historicals!B9 -> 433 | C78: =Historicals!C9 -> 2522 | D78: =Historicals!D9 -> 7326 | E78: =E76+E77 -> 29977.289 | F78: =F76+F77 -> 57251.172 | G78: =G76+G77 -> 83839.393 | H78: =H76+H77 -> 108249.85 | I78: =I76+I77 -> 130533.72 | J78: =J76+J77 -> 153315.07 | K78: =K76+K77 -> 172318.24 | L78: =L76+L77 -> 189321.16 | ... S78: =S76+S77 -> 279629.21
A79: Compute need % of revenue | B79: =B78/B65 -> 10.560976 | C79: =C78/C65 -> 6.5336788 | D79: =D78/D65 -> 1.597819 | E79: =E78/E65 -> 0.55 | F79: =F78/F65 -> 0.505 | G79: =G78/G65 -> 0.465 | H79: =H78/H65 -> 0.43 | I79: =I78/I65 -> 0.4 | ... S79: =S78/S65 -> 0.31
A80: Total compute capacity in service (GW) | D80: =D78/$E$19 -> 0.6105 | E80: =E78/E19 -> 2.4981074 | F80: =F78/F19 -> 4.868297 | G80: =G78/G19 -> 7.274694 | H80: =H78/H19 -> 9.584467 | I80: =I78/I19 -> 11.793368 | J80: =J78/J19 -> 14.134329 | K80: =K78/K19 -> 16.210406 | L80: =L78/L19 -> 18.173377 | ... S80: =S78/S19 -> 30.91978
A81: Accelerators in service (000s, GPU / TPU / Trainium equiv.) | D81: =D80*$E$20 -> 396.825 | E81: =E80*E20 -> 1623.7698 | F81: =F80*F20 -> 3069.4612 | G81: =G80*G20 -> 4449.2028 | H81: =H80*H20 -> 5685.5058 | I81: =I80*I20 -> 6785.9042 | J81: =J80*J20 -> 7889.7825 | K81: =K80*K20 -> 8776.3139 | L81: =L80*L20 -> 9544.6577 | ... S81: =S80*S20 -> 13119.263
A82: Owned (Anthropic Direct) capacity – opening (GW) | E82: =D85 -> 0 | F82: =E85 -> 0.18876074 | G82: =F85 -> 0.66279865 | H82: =G85 -> 1.3847177 | I82: =H85 -> 2.1931383 | J82: =I85 -> 3.0766989 | K82: =J85 -> 4.0130832 | L82: =K85 -> 4.843514 | ... S82: =R85 -> 10.013686
A83: Total capacity additions (GW) | E83: =MAX(0,E80-D80) -> 1.8876074 | F83: =MAX(0,F80-E80) -> 2.3701895 | G83: =MAX(0,G80-F80) -> 2.406397 | H83: =MAX(0,H80-G80) -> 2.309773 | I83: =MAX(0,I80-H80) -> 2.2089015 | J83: =MAX(0,J80-I80) -> 2.3409607 | K83: =MAX(0,K80-J80) -> 2.076077 | L83: =MAX(0,L80-K80) -> 1.962971 | ... S83: =MAX(0,S80-R80) -> 1.783943
A84: Owned capacity additions (GW) | E84: =E83*E21 -> 0.18876074 | F84: =F83*F21 -> 0.4740379 | G84: =G83*G21 -> 0.7219191 | H84: =H83*H21 -> 0.80842055 | I84: =I83*I21 -> 0.8835606 | J84: =J83*J21 -> 0.93638428 | K84: =K83*K21 -> 0.83043081 | L84: =L83*L21 -> 0.78518839 | ... S84: =S83*S21 -> 0.7135772
A85: Owned capacity – closing (GW) | D85: 0 | E85: =E82+E84 -> 0.18876074 | F85: =F82+F84 -> 0.66279865 | G85: =G82+G84 -> 1.3847177 | H85: =H82+H84 -> 2.1931383 | I85: =I82+I84 -> 3.0766989 | J85: =J82+J84 -> 4.0130832 | K85: =K82+K84 -> 4.843514 | L85: =L82+L84 -> 5.6287024 | ... S85: =S82+S84 -> 10.727264
A86: Owned share of total fleet | E86: =IF(E80>0,E85/E80,0) -> 0.0755615 | F86: =IF(F80>0,F85/F80,0) -> 0.1361459 | G86: =IF(G80>0,G85/G80,0) -> 0.19034722 | H86: =IF(H80>0,H85/H80,0) -> 0.22882215 | I86: =IF(I80>0,I85/I80,0) -> 0.26088381 | J86: =IF(J80>0,J85/J80,0) -> 0.28392456 | K86: =IF(K80>0,K85/K80,0) -> 0.29879041 | L86: =IF(L80>0,L85/L80,0) -> 0.30972242 | ... S86: =IF(S80>0,S85/S80,0) -> 0.34693855
A87: Rented capacity – CSP / leased (GW) | E87: =E80-E85 -> 2.3093467 | F87: =F80-F85 -> 4.2054983 | G87: =G80-G85 -> 5.8899762 | H87: =H80-H85 -> 7.3913287 | I87: =I80-I85 -> 8.7166696 | J87: =J80-J85 -> 10.121246 | K87: =K80-K85 -> 11.366892 | L87: =L80-L85 -> 12.544675 | ... S87: =S80-S85 -> 20.192516
A88: Owned accelerators (000s) | E88: =E85*E20 -> 122.69448 | F88: =F85*F20 -> 417.89455 | G88: =G85*G20 -> 846.89337 | H88: =H85*H20 -> 1300.9696 | I88: =I85*I20 -> 1770.3325 | J88: =J85*J20 -> 2240.103 | K88: =K85*K20 -> 2622.2785 | L88: =L85*L20 -> 2956.1945 | ... S88: =S85*S20 -> 4551.5779
A89: Rented compute expense ($M) | E89: =MAX(0,E78-AVERAGE(E82,E85)*E19) -> 28844.725 | F89: =MAX(0,F78-AVERAGE(F82,F85)*F19) -> 52244.003 | G89: =MAX(0,G78-AVERAGE(G82,G85)*G19) -> 72040.784 | H89: =MAX(0,H78-AVERAGE(H82,H85)*H19) -> 88045.155 | I89: =MAX(0,I78-AVERAGE(I82,I85)*I19) -> 101369.39 | J89: =MAX(0,J78-AVERAGE(J82,J85)*J19) -> 114863.64 | K89: =MAX(0,K78-AVERAGE(K82,K85)*K19) -> 125244.98 | L89: =MAX(0,L78-AVERAGE(L82,L85)*L19) -> 134774 | ... S89: =MAX(0,S78-AVERAGE(S82,S85)*S19) -> 185841.75
A90: Owned-fleet power & operations expense ($M) | E90: =AVERAGE(E82,E85)*E23 -> 188.76074 | F90: =AVERAGE(F82,F85)*F23 -> 868.59058 | G90: =AVERAGE(G82,G85)*G23 -> 2130.2361 | H90: =AVERAGE(H82,H85)*H23 -> 3796.8208 | I90: =AVERAGE(I82,I85)*I23 -> 5704.3353 | J90: =AVERAGE(J82,J85)*J23 -> 7827.8284 | K90: =AVERAGE(K82,K85)*K23 -> 9973.8569 | L90: =AVERAGE(L82,L85)*L23 -> 12029.435 | ... S90: =AVERAGE(S82,S85)*S23 -> 27367.683
A91: Owned-fleet depreciation ($M) | E91: =AVERAGE(E82,E85)*E22/$E$24 -> 755.04298 | F91: =AVERAGE(F82,F85)*F22/$E$24 -> 3269.9881 | G91: =AVERAGE(G82,G85)*G22/$E$24 -> 7547.9644 | H91: =AVERAGE(H82,H85)*H22/$E$24 -> 12661.818 | I91: =AVERAGE(I82,I85)*I22/$E$24 -> 17903.692 | J91: =AVERAGE(J82,J85)*J22/$E$24 -> 23123.253 | K91: =AVERAGE(K82,K85)*K22/$E$24 -> 27730.271 | L91: =AVERAGE(L82,L85)*L22/$E$24 -> 31477.283 | ... S91: =AVERAGE(S82,S85)*S22/$E$24 -> 46847.376
A92: Compute capex – growth + replacement ($M) | E92: =E84*E22+E82*E22/$E$24 -> 7550.4298 | F92: =F84*F22+F82*F22/$E$24 -> 19652.738 | G92: =G84*G22+G82*G22/$E$24 -> 31499.507 | H92: =H84*H22+H82*H22/$E$24 -> 38410.384 | I92: =I84*I22+I82*I22/$E$24 -> 44919.892 | J92: =J84*J22+J82*J22/$E$24 -> 50609.325 | K92: =K84*K22+K82*K22/$E$24 -> 51131.206 | L92: =L84*L22+L82*L22/$E$24 -> 52718.286 | ... S92: =S84*S22+S82*S22/$E$24 -> 61353.123
A93: Memo: owned-fleet saving vs renting ($M) | E93: =E78-E89-E90-E91 -> 188.76074 | F93: =F78-F89-F90-F91 -> 868.59058 | G93: =G78-G89-G90-G91 -> 2120.408 | H93: =H78-H89-H90-H91 -> 3746.0511 | I93: =I78-I89-I90-I91 -> 5556.3055 | J93: =J78-J89-J90-J91 -> 7500.3513 | K93: =K78-K89-K90-K91 -> 9369.1284 | L93: =L78-L89-L90-L91 -> 11040.439 | ... S93: =S78-S89-S90-S91 -> 19572.405
A95: PERSONNEL & OPERATING EXPENSE BUILD ($M)
A96: Headcount – period end (#) | E96: =E25 -> 6000 | F96: =E96*(1+F26) -> 8100 | G96: =F96*(1+G26) -> 10368 | H96: =G96*(1+H26) -> 12648.96 | I96: =H96*(1+I26) -> 14925.773 | J96: =I96*(1+J26) -> 17164.639 | K96: =J96*(1+K26) -> 19224.395 | L96: =K96*(1+L26) -> 21146.835 | M96: =L96*(1+M26) -> 22838.582 | ... S96: =R96*(1+S26) -> 30594.126
A97: Average headcount (#) | E97: =AVERAGE(Historicals!H172,E96) -> 5650 | F97: =AVERAGE(E96,F96) -> 7050 | G97: =AVERAGE(F96,G96) -> 9234 | H97: =AVERAGE(G96,H96) -> 11508.48 | I97: =AVERAGE(H96,I96) -> 13787.366 | J97: =AVERAGE(I96,J96) -> 16045.206 | K97: =AVERAGE(J96,K96) -> 18194.517 | L97: =AVERAGE(K96,L96) -> 20185.615 | M97: =AVERAGE(L96,M96) -> 21992.708 | ... S97: =AVERAGE(R96,S96) -> 30076.834
A98: Fully-loaded personnel cost per head ($M) | E98: =E27 -> 1.5 | F98: =E98*(1+F28) -> 1.575 | G98: =F98*(1+G28) -> 1.65375 | H98: =G98*(1+H28) -> 1.7364375 | I98: =H98*(1+I28) -> 1.8232594 | J98: =I98*(1+J28) -> 1.8961898 | K98: =J98*(1+K28) -> 1.9720373 | L98: =K98*(1+L28) -> 2.0509188 | M98: =L98*(1+M28) -> 2.1329556 | ... S98: =R98*(1+S28) -> 2.6988693
A99: Personnel expense (incl. SBC) | B99: =Historicals!B10 -> 95 | C99: =Historicals!C10 -> 454 | D99: =Historicals!D10 -> 1839 | E99: =E45+E97*E98*(1-E50) -> 7389.5 | F99: =F97*F98 -> 11103.75 | G99: =G97*G98 -> 15270.728 | H99: =H97*H98 -> 19983.756 | I99: =I97*I98 -> 25137.945 | J99: =J97*J98 -> 30424.755 | K99: =K97*K98 -> 35880.267 | L99: =L97*L98 -> 41399.058 | M99: =M97*M98 -> 46909.47 | ... S99: =S97*S98 -> 81173.443
A100: of which: stock-based compensation | B100: =Historicals!B25 -> 29 | C100: =Historicals!C25 -> 192 | D100: =Historicals!D25 -> 1158 | E100: =E48+(E99-E45)*E29 -> 4939.375 | F100: =F99*F29 -> 6662.25 | G100: =G99*G29 -> 8398.9001 | H100: =H99*H29 -> 9991.8781 | I100: =I99*I29 -> 11563.455 | J100: =J99*J29 -> 12778.397 | K100: =K99*K29 -> 14352.107 | L100: =L99*L29 -> 15731.642 | M100: =M99*M29 -> 16887.409 | ... S100: =S99*S29 -> 24352.033
A101: of which: cash personnel | B101: =B99-B100 -> 66 | C101: =C99-C100 -> 262 | D101: =D99-D100 -> 681 | E101: =E99-E100 -> 2450.125 | F101: =F99-F100 -> 4441.5 | G101: =G99-G100 -> 6871.8274 | H101: =H99-H100 -> 9991.8781 | I101: =I99-I100 -> 13574.49 | ... S101: =S99-S100 -> 56821.41
A102: Sales, marketing & partnerships | B102: =Historicals!B12 -> 2 | C102: =Historicals!C12 -> 43 | D102: =Historicals!D12 -> 568 | E102: =E46+E51*E30 -> 10429.451 | F102: =F65*F30 -> 19272.672 | G102: =G65*G30 -> 27946.464 | H102: =H65*H30 -> 36502.855 | I102: =I65*I30 -> 44055.13 | J102: =J65*J30 -> 50432.588 | K102: =K65*K30 -> 57439.413 | L102: =L65*L30 -> 63107.052 | M102: =M65*M30 -> 67500.952 | ... S102: =S65*S30 -> 99223.27
A103: Other operating & administrative | B103: =Historicals!B13 -> 62 | C103: =Historicals!C13 -> 347 | D103: =Historicals!D13 -> 1412 | E103: =E47+E51*E31 -> 5535.8162 | F103: =F65*F31 -> 10203.179 | G103: =G65*G31 -> 14423.982 | H103: =H65*H31 -> 18880.787 | I103: =I65*I31 -> 22843.401 | J103: =J65*J31 -> 26224.946 | K103: =K65*K31 -> 28719.706 | L103: =L65*L31 -> 32925.419 | M103: =M65*M31 -> 33750.476 | ... S103: =S65*S31 -> 49611.635
A104: Revenue per average employee ($M) | E104: =E65/E97 -> 9.6467544 | F104: =F65/F97 -> 16.080661 | G104: =G65/G97 -> 19.525641 | H104: =H65/H97 -> 21.874637 | I104: =I65/I97 -> 23.669081 | J104: =J65/J97 -> 25.14525 | K104: =K65/K97 -> 26.308023 | L104: =L65/L97 -> 27.185546 | ... S104: =S65/S97 -> 29.990847
A106: INCOME STATEMENT ($M) – opex shown ex-D&A in forecast; S-1 actuals embed immaterial D&A
A107: Revenue | B107: =B65 -> 41 | C107: =C65 -> 386 | D107: =D65 -> 4585 | E107: =E65 -> 54504.162 | F107: =F65 -> 113368.66 | G107: =G65 -> 180299.77 | H107: =H65 -> 251743.83 | I107: =I65 -> 326334.3 | ... S107: =S65 -> 902029.72
A108: Compute & infrastructure (rented + owned-fleet power) | B108: =Historicals!B9 -> 433 | C108: =Historicals!C9 -> 2522 | D108: =Historicals!D9 -> 7326 | E108: =E44+E51*(E89+E90)/E65 -> 29303.197 | F108: =F89+F90 -> 53112.594 | G108: =G89+G90 -> 74171.02 | H108: =H89+H90 -> 91841.976 | I108: =I89+I90 -> 107073.72 | J108: =J89+J90 -> 122691.46 | K108: =K89+K90 -> 135218.84 | L108: =L89+L90 -> 146803.43 | M108: =M89+M90 -> 158208.92 | ... S108: =S89+S90 -> 213209.43
...

Sheet DCF Bear
A1: Anthropic ($ANT) – DCF Valuation Engine (Scenario engine)
A2: Form S-1 filed 26-Oct-2026 | 15-Year Explicit Forecast FY2026E–FY2040E | $ in Millions except per share | Intrinsic value
A3: Identical engine on DCF Bear / DCF Base / DCF Bull – only B5 differs. Do not edit formulas on one engine without copying to the other two.
A5: SCENARIO INDEX | B5: 1 | C5: =CHOOSE(B5,"◀ BEAR","◀ BASE","◀ BULL") -> ◀ BEAR | D5: (1 = Bear | 2 = Base | 3 = Bull)
A6: ($ in Millions) | B6: FY2023A | C6: FY2024A | D6: FY2025A | E6: FY2026E | F6: FY2027E | G6: FY2028E | H6: FY2029E | I6: FY2030E | J6: FY2031E | K6: FY2032E | L6: FY2033E | M6: FY2034E | N6: FY2035E | O6: FY2036E | P6: FY2037E | Q6: FY2038E | R6: FY2039E | S6: FY2040E
A8: SELECTED CASE ASSUMPTIONS (auto-pulled from Drivers by scenario index in B5)
A9: Q3 2026 revenue growth (QoQ) | E9: =CHOOSE($B$5,Drivers!E23,Drivers!E54,Drivers!E85) -> 0.44128083
A10: Q4 2026 revenue growth (QoQ) | E10: =CHOOSE($B$5,Drivers!E24,Drivers!E55,Drivers!E86) -> 0.12
A11: Subscription mix % of FY2026E revenue | E11: =CHOOSE($B$5,Drivers!E25,Drivers!E56,Drivers!E87) -> 0.2
A12: Consumption-based revenue growth (YoY) | F12: =CHOOSE($B$5,Drivers!F26,Drivers!F57,Drivers!F88) -> 0.7 | G12: =CHOOSE($B$5,Drivers!G26,Drivers!G57,Drivers!G88) -> 0.35 | H12: =CHOOSE($B$5,Drivers!H26,Drivers!H57,Drivers!H88) -> 0.22 | I12: =CHOOSE($B$5,Drivers!I26,Drivers!I57,Drivers!I88) -> 0.16 | J12: =CHOOSE($B$5,Drivers!J26,Drivers!J57,Drivers!J88) -> 0.12 | K12: =CHOOSE($B$5,Drivers!K26,Drivers!K57,Drivers!K88) -> 0.1 | L12: =CHOOSE($B$5,Drivers!L26,Drivers!L57,Drivers!L88) -> 0.08 | M12: =CHOOSE($B$5,Drivers!M26,Drivers!M57,Drivers!M88) -> 0.07 | ... S12: =CHOOSE($B$5,Drivers!S26,Drivers!S57,Drivers!S88) -> 0.03
A13: Subscription-based revenue growth (YoY) | F13: =CHOOSE($B$5,Drivers!F27,Drivers!F58,Drivers!F89) -> 0.6 | G13: =CHOOSE($B$5,Drivers!G27,Drivers!G58,Drivers!G89) -> 0.3 | H13: =CHOOSE($B$5,Drivers!H27,Drivers!H58,Drivers!H89) -> 0.2 | I13: =CHOOSE($B$5,Drivers!I27,Drivers!I58,Drivers!I89) -> 0.15 | J13: =CHOOSE($B$5,Drivers!J27,Drivers!J58,Drivers!J89) -> 0.11 | K13: =CHOOSE($B$5,Drivers!K27,Drivers!K58,Drivers!K89) -> 0.09 | L13: =CHOOSE($B$5,Drivers!L27,Drivers!L58,Drivers!L89) -> 0.075 | M13: =CHOOSE($B$5,Drivers!M27,Drivers!M58,Drivers!M89) -> 0.065 | ... S13: =CHOOSE($B$5,Drivers!S27,Drivers!S58,Drivers!S89) -> 0.03
A14: International % of revenue | E14: =CHOOSE($B$5,Drivers!E28,Drivers!E59,Drivers!E90) -> 0.27 | F14: =CHOOSE($B$5,Drivers!F28,Drivers!F59,Drivers!F90) -> 0.275 | G14: =CHOOSE($B$5,Drivers!G28,Drivers!G59,Drivers!G90) -> 0.28 | H14: =CHOOSE($B$5,Drivers!H28,Drivers!H59,Drivers!H90) -> 0.285 | I14: =CHOOSE($B$5,Drivers!I28,Drivers!I59,Drivers!I90) -> 0.29 | J14: =CHOOSE($B$5,Drivers!J28,Drivers!J59,Drivers!J90) -> 0.295 | K14: =CHOOSE($B$5,Drivers!K28,Drivers!K59,Drivers!K90) -> 0.3 | L14: =CHOOSE($B$5,Drivers!L28,Drivers!L59,Drivers!L90) -> 0.305 | ... S14: =CHOOSE($B$5,Drivers!S28,Drivers!S59,Drivers!S90) -> 0.33
A15: Enterprise customers (≥$100K) growth | E15: =CHOOSE($B$5,Drivers!E29,Drivers!E60,Drivers!E91) -> 7 | F15: =CHOOSE($B$5,Drivers!F29,Drivers!F60,Drivers!F91) -> 0.6 | G15: =CHOOSE($B$5,Drivers!G29,Drivers!G60,Drivers!G91) -> 0.35 | H15: =CHOOSE($B$5,Drivers!H29,Drivers!H60,Drivers!H91) -> 0.22 | I15: =CHOOSE($B$5,Drivers!I29,Drivers!I60,Drivers!I91) -> 0.16 | J15: =CHOOSE($B$5,Drivers!J29,Drivers!J60,Drivers!J91) -> 0.12 | K15: =CHOOSE($B$5,Drivers!K29,Drivers!K60,Drivers!K91) -> 0.1 | L15: =CHOOSE($B$5,Drivers!L29,Drivers!L60,Drivers!L91) -> 0.08 | ... S15: =CHOOSE($B$5,Drivers!S29,Drivers!S60,Drivers!S91) -> 0.025
A16: Enterprise (≥$100K) share of revenue | E16: =CHOOSE($B$5,Drivers!E30,Drivers!E61,Drivers!E92) -> 0.76 | F16: =CHOOSE($B$5,Drivers!F30,Drivers!F61,Drivers!F92) -> 0.765 | G16: =CHOOSE($B$5,Drivers!G30,Drivers!G61,Drivers!G92) -> 0.77 | H16: =CHOOSE($B$5,Drivers!H30,Drivers!H61,Drivers!H92) -> 0.775 | I16: =CHOOSE($B$5,Drivers!I30,Drivers!I61,Drivers!I92) -> 0.78 | J16: =CHOOSE($B$5,Drivers!J30,Drivers!J61,Drivers!J92) -> 0.785 | K16: =CHOOSE($B$5,Drivers!K30,Drivers!K61,Drivers!K92) -> 0.79 | L16: =CHOOSE($B$5,Drivers!L30,Drivers!L61,Drivers!L92) -> 0.795 | ... S16: =CHOOSE($B$5,Drivers!S30,Drivers!S61,Drivers!S92) -> 0.8
A17: Inference / serving compute % of revenue | E17: =CHOOSE($B$5,Drivers!E31,Drivers!E62,Drivers!E93) -> 0.32 | F17: =CHOOSE($B$5,Drivers!F31,Drivers!F62,Drivers!F93) -> 0.315 | G17: =CHOOSE($B$5,Drivers!G31,Drivers!G62,Drivers!G93) -> 0.31 | H17: =CHOOSE($B$5,Drivers!H31,Drivers!H62,Drivers!H93) -> 0.295 | I17: =CHOOSE($B$5,Drivers!I31,Drivers!I62,Drivers!I93) -> 0.28 | J17: =CHOOSE($B$5,Drivers!J31,Drivers!J62,Drivers!J93) -> 0.27 | K17: =CHOOSE($B$5,Drivers!K31,Drivers!K62,Drivers!K93) -> 0.26 | L17: =CHOOSE($B$5,Drivers!L31,Drivers!L62,Drivers!L93) -> 0.255 | ... S17: =CHOOSE($B$5,Drivers!S31,Drivers!S62,Drivers!S93) -> 0.24
A18: Training & research compute % of revenue | E18: =CHOOSE($B$5,Drivers!E32,Drivers!E63,Drivers!E94) -> 0.28 | F18: =CHOOSE($B$5,Drivers!F32,Drivers!F63,Drivers!F94) -> 0.25 | G18: =CHOOSE($B$5,Drivers!G32,Drivers!G63,Drivers!G94) -> 0.225 | H18: =CHOOSE($B$5,Drivers!H32,Drivers!H63,Drivers!H94) -> 0.205 | I18: =CHOOSE($B$5,Drivers!I32,Drivers!I63,Drivers!I94) -> 0.19 | J18: =CHOOSE($B$5,Drivers!J32,Drivers!J63,Drivers!J94) -> 0.18 | K18: =CHOOSE($B$5,Drivers!K32,Drivers!K63,Drivers!K94) -> 0.17 | L18: =CHOOSE($B$5,Drivers!L32,Drivers!L63,Drivers!L94) -> 0.16 | ... S18: =CHOOSE($B$5,Drivers!S32,Drivers!S63,Drivers!S94) -> 0.14
A19: Rental-equivalent compute cost per GW-year ($M) | E19: =CHOOSE($B$5,Drivers!E33,Drivers!E64,Drivers!E95) -> 12000 | F19: =CHOOSE($B$5,Drivers!F33,Drivers!F64,Drivers!F95) -> 11760 | G19: =CHOOSE($B$5,Drivers!G33,Drivers!G64,Drivers!G95) -> 11524.8 | H19: =CHOOSE($B$5,Drivers!H33,Drivers!H64,Drivers!H95) -> 11294.3 | I19: =CHOOSE($B$5,Drivers!I33,Drivers!I64,Drivers!I95) -> 11068.4 | J19: =CHOOSE($B$5,Drivers!J33,Drivers!J64,Drivers!J95) -> 10847 | K19: =CHOOSE($B$5,Drivers!K33,Drivers!K64,Drivers!K95) -> 10630.1 | L19: =CHOOSE($B$5,Drivers!L33,Drivers!L64,Drivers!L95) -> 10417.5 | ... S19: =CHOOSE($B$5,Drivers!S33,Drivers!S64,Drivers!S95) -> 9043.7
A20: Accelerators per GW (000s) | E20: =CHOOSE($B$5,Drivers!E34,Drivers!E65,Drivers!E96) -> 650 | F20: =CHOOSE($B$5,Drivers!F34,Drivers!F65,Drivers!F96) -> 630.5 | G20: =CHOOSE($B$5,Drivers!G34,Drivers!G65,Drivers!G96) -> 611.6 | H20: =CHOOSE($B$5,Drivers!H34,Drivers!H65,Drivers!H96) -> 593.2 | I20: =CHOOSE($B$5,Drivers!I34,Drivers!I65,Drivers!I96) -> 575.4 | J20: =CHOOSE($B$5,Drivers!J34,Drivers!J65,Drivers!J96) -> 558.2 | K20: =CHOOSE($B$5,Drivers!K34,Drivers!K65,Drivers!K96) -> 541.4 | L20: =CHOOSE($B$5,Drivers!L34,Drivers!L65,Drivers!L96) -> 525.2 | ... S20: =CHOOSE($B$5,Drivers!S34,Drivers!S65,Drivers!S96) -> 424.3
A21: Anthropic Direct share of new capacity | E21: =CHOOSE($B$5,Drivers!E35,Drivers!E66,Drivers!E97) -> 0.05 | F21: =CHOOSE($B$5,Drivers!F35,Drivers!F66,Drivers!F97) -> 0.1 | G21: =CHOOSE($B$5,Drivers!G35,Drivers!G66,Drivers!G97) -> 0.15 | H21: =CHOOSE($B$5,Drivers!H35,Drivers!H66,Drivers!H97) -> 0.2 | I21: =CHOOSE($B$5,Drivers!I35,Drivers!I66,Drivers!I97) -> 0.25 | J21: =CHOOSE($B$5,Drivers!J35,Drivers!J66,Drivers!J97) -> 0.25 | K21: =CHOOSE($B$5,Drivers!K35,Drivers!K66,Drivers!K97) -> 0.25 | L21: =CHOOSE($B$5,Drivers!L35,Drivers!L66,Drivers!L97) -> 0.25 | ... S21: =CHOOSE($B$5,Drivers!S35,Drivers!S66,Drivers!S97) -> 0.25
A22: Capex per owned GW ($M) | E22: =CHOOSE($B$5,Drivers!E36,Drivers!E67,Drivers!E98) -> 40000 | F22: =CHOOSE($B$5,Drivers!F36,Drivers!F67,Drivers!F98) -> 38400 | G22: =CHOOSE($B$5,Drivers!G36,Drivers!G67,Drivers!G98) -> 36864 | H22: =CHOOSE($B$5,Drivers!H36,Drivers!H67,Drivers!H98) -> 35389.4 | I22: =CHOOSE($B$5,Drivers!I36,Drivers!I67,Drivers!I98) -> 33973.9 | J22: =CHOOSE($B$5,Drivers!J36,Drivers!J67,Drivers!J98) -> 32614.9 | K22: =CHOOSE($B$5,Drivers!K36,Drivers!K67,Drivers!K98) -> 31310.3 | L22: =CHOOSE($B$5,Drivers!L36,Drivers!L67,Drivers!L98) -> 30057.9 | ... S22: =CHOOSE($B$5,Drivers!S36,Drivers!S67,Drivers!S98) -> 22586.9
A23: Power & ops cost per owned GW-year ($M) | E23: =CHOOSE($B$5,Drivers!E37,Drivers!E68,Drivers!E99) -> 2000 | F23: =CHOOSE($B$5,Drivers!F37,Drivers!F68,Drivers!F99) -> 2040 | G23: =CHOOSE($B$5,Drivers!G37,Drivers!G68,Drivers!G99) -> 2080.8 | H23: =CHOOSE($B$5,Drivers!H37,Drivers!H68,Drivers!H99) -> 2122.4 | I23: =CHOOSE($B$5,Drivers!I37,Drivers!I68,Drivers!I99) -> 2164.9 | J23: =CHOOSE($B$5,Drivers!J37,Drivers!J68,Drivers!J99) -> 2208.2 | K23: =CHOOSE($B$5,Drivers!K37,Drivers!K68,Drivers!K99) -> 2252.3 | L23: =CHOOSE($B$5,Drivers!L37,Drivers!L68,Drivers!L99) -> 2297.4 | ... S23: =CHOOSE($B$5,Drivers!S37,Drivers!S68,Drivers!S99) -> 2639
A24: Owned accelerator useful life (years) | E24: =CHOOSE($B$5,Drivers!E38,Drivers!E69,Drivers!E100) -> 5
A25: Headcount – FY2026E period end | E25: =CHOOSE($B$5,Drivers!E39,Drivers!E70,Drivers!E101) -> 6000
A26: Headcount growth (YoY) | F26: =CHOOSE($B$5,Drivers!F40,Drivers!F71,Drivers!F102) -> 0.2 | G26: =CHOOSE($B$5,Drivers!G40,Drivers!G71,Drivers!G102) -> 0.15 | H26: =CHOOSE($B$5,Drivers!H40,Drivers!H71,Drivers!H102) -> 0.1 | I26: =CHOOSE($B$5,Drivers!I40,Drivers!I71,Drivers!I102) -> 0.08 | J26: =CHOOSE($B$5,Drivers!J40,Drivers!J71,Drivers!J102) -> 0.06 | K26: =CHOOSE($B$5,Drivers!K40,Drivers!K71,Drivers!K102) -> 0.05 | L26: =CHOOSE($B$5,Drivers!L40,Drivers!L71,Drivers!L102) -> 0.04 | M26: =CHOOSE($B$5,Drivers!M40,Drivers!M71,Drivers!M102) -> 0.035 | ... S26: =CHOOSE($B$5,Drivers!S40,Drivers!S71,Drivers!S102) -> 0.02
A27: Personnel cost per head – FY2026E ($M) | E27: =CHOOSE($B$5,Drivers!E41,Drivers!E72,Drivers!E103) -> 1.5
A28: Personnel cost per head growth | F28: =CHOOSE($B$5,Drivers!F42,Drivers!F73,Drivers!F104) -> 0.05 | G28: =CHOOSE($B$5,Drivers!G42,Drivers!G73,Drivers!G104) -> 0.05 | H28: =CHOOSE($B$5,Drivers!H42,Drivers!H73,Drivers!H104) -> 0.05 | I28: =CHOOSE($B$5,Drivers!I42,Drivers!I73,Drivers!I104) -> 0.05 | J28: =CHOOSE($B$5,Drivers!J42,Drivers!J73,Drivers!J104) -> 0.05 | K28: =CHOOSE($B$5,Drivers!K42,Drivers!K73,Drivers!K104) -> 0.05 | L28: =CHOOSE($B$5,Drivers!L42,Drivers!L73,Drivers!L104) -> 0.05 | M28: =CHOOSE($B$5,Drivers!M42,Drivers!M73,Drivers!M104) -> 0.05 | ... S28: =CHOOSE($B$5,Drivers!S42,Drivers!S73,Drivers!S104) -> 0.05
A29: SBC % of personnel | E29: =CHOOSE($B$5,Drivers!E43,Drivers!E74,Drivers!E105) -> 0.65 | F29: =CHOOSE($B$5,Drivers!F43,Drivers!F74,Drivers!F105) -> 0.6 | G29: =CHOOSE($B$5,Drivers!G43,Drivers!G74,Drivers!G105) -> 0.55 | H29: =CHOOSE($B$5,Drivers!H43,Drivers!H74,Drivers!H105) -> 0.5 | I29: =CHOOSE($B$5,Drivers!I43,Drivers!I74,Drivers!I105) -> 0.46 | J29: =CHOOSE($B$5,Drivers!J43,Drivers!J74,Drivers!J105) -> 0.42 | K29: =CHOOSE($B$5,Drivers!K43,Drivers!K74,Drivers!K105) -> 0.4 | L29: =CHOOSE($B$5,Drivers!L43,Drivers!L74,Drivers!L105) -> 0.38 | ... S29: =CHOOSE($B$5,Drivers!S43,Drivers!S74,Drivers!S105) -> 0.3
A30: Sales, marketing & partnerships % of revenue | E30: =CHOOSE($B$5,Drivers!E44,Drivers!E75,Drivers!E106) -> 0.21 | F30: =CHOOSE($B$5,Drivers!F44,Drivers!F75,Drivers!F106) -> 0.19 | G30: =CHOOSE($B$5,Drivers!G44,Drivers!G75,Drivers!G106) -> 0.175 | H30: =CHOOSE($B$5,Drivers!H44,Drivers!H75,Drivers!H106) -> 0.165 | I30: =CHOOSE($B$5,Drivers!I44,Drivers!I75,Drivers!I106) -> 0.155 | J30: =CHOOSE($B$5,Drivers!J44,Drivers!J75,Drivers!J106) -> 0.145 | K30: =CHOOSE($B$5,Drivers!K44,Drivers!K75,Drivers!K106) -> 0.14 | L30: =CHOOSE($B$5,Drivers!L44,Drivers!L75,Drivers!L106) -> 0.135 | ... S30: =CHOOSE($B$5,Drivers!S44,Drivers!S75,Drivers!S106) -> 0.13
A31: Other operating & admin % of revenue | E31: =CHOOSE($B$5,Drivers!E45,Drivers!E76,Drivers!E107) -> 0.11 | F31: =CHOOSE($B$5,Drivers!F45,Drivers!F76,Drivers!F107) -> 0.1 | G31: =CHOOSE($B$5,Drivers!G45,Drivers!G76,Drivers!G107) -> 0.09 | H31: =CHOOSE($B$5,Drivers!H45,Drivers!H76,Drivers!H107) -> 0.085 | I31: =CHOOSE($B$5,Drivers!I45,Drivers!I76,Drivers!I107) -> 0.08 | J31: =CHOOSE($B$5,Drivers!J45,Drivers!J76,Drivers!J107) -> 0.075 | K31: =CHOOSE($B$5,Drivers!K45,Drivers!K76,Drivers!K107) -> 0.07 | L31: =CHOOSE($B$5,Drivers!L45,Drivers!L76,Drivers!L107) -> 0.07 | ... S31: =CHOOSE($B$5,Drivers!S45,Drivers!S76,Drivers!S107) -> 0.065
A32: Other (non-compute) capex % of revenue | E32: =CHOOSE($B$5,Drivers!E46,Drivers!E77,Drivers!E108) -> 0.012 | F32: =CHOOSE($B$5,Drivers!F46,Drivers!F77,Drivers!F108) -> 0.012 | G32: =CHOOSE($B$5,Drivers!G46,Drivers!G77,Drivers!G108) -> 0.012 | H32: =CHOOSE($B$5,Drivers!H46,Drivers!H77,Drivers!H108) -> 0.012 | I32: =CHOOSE($B$5,Drivers!I46,Drivers!I77,Drivers!I108) -> 0.012 | J32: =CHOOSE($B$5,Drivers!J46,Drivers!J77,Drivers!J108) -> 0.012 | K32: =CHOOSE($B$5,Drivers!K46,Drivers!K77,Drivers!K108) -> 0.012 | L32: =CHOOSE($B$5,Drivers!L46,Drivers!L77,Drivers!L108) -> 0.012 | ... S32: =CHOOSE($B$5,Drivers!S46,Drivers!S77,Drivers!S108) -> 0.012
A33: Other D&A % of revenue | E33: =CHOOSE($B$5,Drivers!E47,Drivers!E78,Drivers!E109) -> 0.005 | F33: =CHOOSE($B$5,Drivers!F47,Drivers!F78,Drivers!F109) -> 0.005 | G33: =CHOOSE($B$5,Drivers!G47,Drivers!G78,Drivers!G109) -> 0.005 | H33: =CHOOSE($B$5,Drivers!H47,Drivers!H78,Drivers!H109) -> 0.005 | I33: =CHOOSE($B$5,Drivers!I47,Drivers!I78,Drivers!I109) -> 0.005 | J33: =CHOOSE($B$5,Drivers!J47,Drivers!J78,Drivers!J109) -> 0.005 | K33: =CHOOSE($B$5,Drivers!K47,Drivers!K78,Drivers!K109) -> 0.005 | L33: =CHOOSE($B$5,Drivers!L47,Drivers!L78,Drivers!L109) -> 0.005 | ... S33: =CHOOSE($B$5,Drivers!S47,Drivers!S78,Drivers!S109) -> 0.005
A34: ΔNWC % of Δrevenue | E34: =CHOOSE($B$5,Drivers!E48,Drivers!E79,Drivers!E110) -> 0.05 | F34: =CHOOSE($B$5,Drivers!F48,Drivers!F79,Drivers!F110) -> 0.05 | G34: =CHOOSE($B$5,Drivers!G48,Drivers!G79,Drivers!G110) -> 0.05 | H34: =CHOOSE($B$5,Drivers!H48,Drivers!H79,Drivers!H110) -> 0.05 | I34: =CHOOSE($B$5,Drivers!I48,Drivers!I79,Drivers!I110) -> 0.05 | J34: =CHOOSE($B$5,Drivers!J48,Drivers!J79,Drivers!J110) -> 0.05 | K34: =CHOOSE($B$5,Drivers!K48,Drivers!K79,Drivers!K110) -> 0.05 | L34: =CHOOSE($B$5,Drivers!L48,Drivers!L79,Drivers!L110) -> 0.05 | ... S34: =CHOOSE($B$5,Drivers!S48,Drivers!S79,Drivers!S110) -> 0.05
A35: Terminal growth rate | E35: =CHOOSE($B$5,Drivers!E49,Drivers!E80,Drivers!E111) -> 0.025
A36: Exit EV / EBITDA multiple | E36: =CHOOSE($B$5,Drivers!E50,Drivers!E81,Drivers!E112) -> 11
A37: Scenario probability weight | E37: =CHOOSE($B$5,Drivers!E51,Drivers!E82,Drivers!E113) -> 0.25
A38: WACC (WACC tab) | E38: =CHOOSE($B$5,WACC!B27,WACC!B28,WACC!B29) -> 0.13367493
A39: Terminal-period WACC (mature stage, WACC tab) | E39: =CHOOSE($B$5,WACC!F27,WACC!F28,WACC!F29) -> 0.10015294
A40: Cash tax rate | E40: =WACC!B9 -> 0.23
A42: FY2026 YEAR-TO-DATE ACTUALS (Historicals column named in Actuals!B5 – re-points automatically)
A43: YTD revenue | E43: =INDEX(Historicals!$B$7:$K$7,MATCH(Actuals!$B$5,Historicals!$B$6:$K$6,0)) -> 16286
A44: YTD compute & infrastructure | E44: =INDEX(Historicals!$B$9:$K$9,MATCH(Actuals!$B$5,Historicals!$B$6:$K$6,0)) -> 8945
A45: YTD personnel | E45: =INDEX(Historicals!$B$10:$K$10,MATCH(Actuals!$B$5,Historicals!$B$6:$K$6,0)) -> 3152
A46: YTD sales, marketing & partnerships | E46: =INDEX(Historicals!$B$12:$K$12,MATCH(Actuals!$B$5,Historicals!$B$6:$K$6,0)) -> 3168
A47: YTD other operating & administrative | E47: =INDEX(Historicals!$B$13:$K$13,MATCH(Actuals!$B$5,Historicals!$B$6:$K$6,0)) -> 1714
A48: YTD stock-based compensation | E48: =INDEX(Historicals!$B$25:$K$25,MATCH(Actuals!$B$5,Historicals!$B$6:$K$6,0)) -> 2185
A49: YTD depreciation & amortization | E49: =INDEX(Historicals!$B$26:$K$26,MATCH(Actuals!$B$5,Historicals!$B$6:$K$6,0)) -> 97
A50: YTD fraction of fiscal year | E50: =Actuals!$B$6/12 -> 0.5
A51: Remaining FY2026E revenue (full year − YTD) | E51: =E65-E43 -> 35306.48
A52: YTD unlevered FCF proxy (CFO − capex − after-tax interest income) | E52: =INDEX(Historicals!$B$128:$K$128,MATCH(Actuals!$B$5,Historicals!$B$113:$K$113,0))+INDEX(Historicals!$B$130:$K$130,MATCH(Actuals!$B$5,Historicals!$B$113:$K$113,0))-INDEX(Historicals!$B$16:$K$16,MATCH(Actuals!$B$5,Historicals!$B$6:$K$6,0))*(1-$E$40) -> 2591.53
A54: FY2026E QUARTERLY REVENUE BUILD (reported quarters override estimates)
A55: Quarter | B55: Q1 2026 | C55: Q2 2026 | D55: Q3 2026 | E55: Q4 2026 | F55: FY2026E
A56: Reported revenue (Historicals) | B56: =IFERROR(IF(INDEX(Historicals!$B$33:$M$33,MATCH(B$55&"A",Historicals!$B$32:$M$32,0))="","",INDEX(Historicals!$B$33:$M$33,MATCH(B$55&"A",Historicals!$B$32:$M$32,0))),"") -> 4731 | C56: =IFERROR(IF(INDEX(Historicals!$B$33:$M$33,MATCH(C$55&"A",Historicals!$B$32:$M$32,0))="","",INDEX(Historicals!$B$33:$M$33,MATCH(C$55&"A",Historicals!$B$32:$M$32,0))),"") -> 11555 | D56: =IFERROR(IF(INDEX(Historicals!$B$33:$M$33,MATCH(D$55&"A",Historicals!$B$32:$M$32,0))="","",INDEX(Historicals!$B$33:$M$33,MATCH(D$55&"A",Historicals!$B$32:$M$32,0))),"") | E56: =IFERROR(IF(INDEX(Historicals!$B$33:$M$33,MATCH(E$55&"A",Historicals!$B$32:$M$32,0))="","",INDEX(Historicals!$B$33:$M$33,MATCH(E$55&"A",Historicals!$B$32:$M$32,0))),"")
A57: QoQ growth (actual if reported, else driver) | B57: =IF(B56<>"",B56/Historicals!$E$33-1,0) -> 1.3191176 | C57: =IF(C56<>"",C56/B58-1,0) -> 1.4424012 | D57: =IF(D56<>"",D56/C58-1,$E$9) -> 0.44128083 | E57: =IF(E56<>"",E56/D58-1,$E$10) -> 0.12
A58: Revenue – selected | B58: =IF(B56<>"",B56,Historicals!$E$33*(1+B57)) -> 4731 | C58: =IF(C56<>"",C56,B58*(1+C57)) -> 11555 | D58: =IF(D56<>"",D56,C58*(1+D57)) -> 16654 | E58: =IF(E56<>"",E56,D58*(1+E57)) -> 18652.48 | F58: =SUM(B58:E58) -> 51592.48
A59: Status | B59: =IF(B56<>"","Actual","Estimate") -> Actual | C59: =IF(C56<>"","Actual","Estimate") -> Actual | D59: =IF(D56<>"","Actual","Estimate") -> Estimate | E59: =IF(E56<>"","Actual","Estimate") -> Estimate
A60: Annualised revenue run-rate (quarter × 4) | B60: =B58*4 -> 18924 | C60: =C58*4 -> 46220 | D60: =D58*4 -> 66616 | E60: =E58*4 -> 74609.92
A62: REVENUE BUILD – by pricing model, geography and customer cohort ($M)
A63: Consumption-based revenue (API / platform / pay-for-intelligence) | B63: =Historicals!B72 -> 39 | C63: =Historicals!C72 -> 288 | D63: =Historicals!D72 -> 3796 | E63: =E65-E64 -> 41273.984 | F63: =E63*(1+F12) -> 70165.773 | G63: =F63*(1+G12) -> 94723.793 | H63: =G63*(1+H12) -> 115563.03 | I63: =H63*(1+I12) -> 134053.11 | J63: =I63*(1+J12) -> 150139.49 | K63: =J63*(1+K12) -> 165153.43 | L63: =K63*(1+L12) -> 178365.71 | M63: =L63*(1+M12) -> 190851.31 | ... S63: =R63*(1+S12) -> 246103.34
A64: Subscription-based revenue (Pro / Max / Team / Enterprise) | B64: =Historicals!B73 -> 2 | C64: =Historicals!C73 -> 98 | D64: =Historicals!D73 -> 789 | E64: =E65*E11 -> 10318.496 | F64: =E64*(1+F13) -> 16509.594 | G64: =F64*(1+G13) -> 21462.472 | H64: =G64*(1+H13) -> 25754.966 | I64: =H64*(1+I13) -> 29618.211 | J64: =I64*(1+J13) -> 32876.214 | K64: =J64*(1+K13) -> 35835.073 | L64: =K64*(1+L13) -> 38522.704 | M64: =L64*(1+M13) -> 41026.68 | ... S64: =R64*(1+S13) -> 51651.538
A65: Total Revenue | B65: =Historicals!B7 -> 41 | C65: =Historicals!C7 -> 386 | D65: =Historicals!D7 -> 4585 | E65: =F58 -> 51592.48 | F65: =F63+F64 -> 86675.366 | G65: =G63+G64 -> 116186.26 | H65: =H63+H64 -> 141317.99 | I65: =I63+I64 -> 163671.32 | J65: =J63+J64 -> 183015.7 | K65: =K63+K64 -> 200988.51 | L65: =L63+L64 -> 216888.41 | M65: =M63+M64 -> 231877.99 | ... S65: =S63+S64 -> 297754.88
A66: % YoY growth | C66: =C65/B65-1 -> 8.4146341 | D66: =D65/C65-1 -> 10.878238 | E66: =E65/D65-1 -> 10.252449 | F66: =F65/E65-1 -> 0.68 | G66: =G65/F65-1 -> 0.34047619 | H66: =H65/G65-1 -> 0.21630551 | I66: =I65/H65-1 -> 0.15817752 | J66: =J65/I65-1 -> 0.11819038 | ... S66: =S65/R65-1 -> 0.03
A67: Subscription mix % | B67: =B64/B65 -> 0.048780488 | C67: =C64/C65 -> 0.25388601 | D67: =D64/D65 -> 0.17208288 | E67: =E64/E65 -> 0.2 | F67: =F64/F65 -> 0.19047619 | G67: =G64/G65 -> 0.18472469 | H67: =H64/H65 -> 0.18224831 | I67: =I64/I65 -> 0.18096152 | ... S67: =S64/S65 -> 0.17347
A68: United States revenue | B68: =Historicals!B69 -> 34 | C68: =Historicals!C69 -> 263 | D68: =Historicals!D69 -> 3362 | E68: =E65*(1-E14) -> 37662.51 | F68: =F65*(1-F14) -> 62839.641 | G68: =G65*(1-G14) -> 83654.111 | H68: =H65*(1-H14) -> 101042.37 | I68: =I65*(1-I14) -> 116206.64 | J68: =J65*(1-J14) -> 129026.07 | K68: =K65*(1-K14) -> 140691.96 | L68: =L65*(1-L14) -> 150737.45 | ... S68: =S65*(1-S14) -> 199495.77
A69: International revenue | B69: =Historicals!B70 -> 7 | C69: =Historicals!C70 -> 123 | D69: =Historicals!D70 -> 1223 | E69: =E65*E14 -> 13929.97 | F69: =F65*F14 -> 23835.726 | G69: =G65*G14 -> 32532.154 | H69: =H65*H14 -> 40275.628 | I69: =I65*I14 -> 47464.684 | J69: =J65*J14 -> 53989.631 | K69: =K65*K14 -> 60296.552 | L69: =L65*L14 -> 66150.966 | ... S69: =S65*S14 -> 98259.11
A70: Enterprise customers ≥$100K TTM (period end, #) | D70: =Historicals!E168 -> 1500 | E70: =D70*(1+E15) -> 12000 | F70: =E70*(1+F15) -> 19200 | G70: =F70*(1+G15) -> 25920 | H70: =G70*(1+H15) -> 31622.4 | I70: =H70*(1+I15) -> 36681.984 | J70: =I70*(1+J15) -> 41083.822 | K70: =J70*(1+K15) -> 45192.204 | L70: =K70*(1+L15) -> 48807.581 | ... S70: =R70*(1+S15) -> 63584.967
A71: Enterprise cohort revenue (≥$100K customers) | E71: =E65*E16 -> 39210.285 | F71: =F65*F16 -> 66306.655 | G71: =G65*G16 -> 89463.424 | H71: =H65*H16 -> 109521.45 | I71: =I65*I16 -> 127663.63 | J71: =J65*J16 -> 143667.32 | K71: =K65*K16 -> 158780.92 | L71: =L65*L16 -> 172426.29 | ... S71: =S65*S16 -> 238203.9
A72: Avg revenue per enterprise customer ($M) | E72: =E71/AVERAGE(D70,E70) -> 5.8089311 | F72: =F71/AVERAGE(E70,F70) -> 4.2504266 | G72: =G71/AVERAGE(F70,G70) -> 3.9655773 | H72: =H71/AVERAGE(G70,H70) -> 3.8066346 | I72: =I71/AVERAGE(H70,I70) -> 3.7380802 | J72: =J71/AVERAGE(I70,J70) -> 3.6948713 | K72: =K71/AVERAGE(J70,K70) -> 3.6807657 | L72: =L71/AVERAGE(K70,L70) -> 3.6686528 | ... S72: =S71/AVERAGE(R70,S70) -> 3.7924797
A73: Long-tail revenue (<$100K customers) | E73: =E65-E71 -> 12382.195 | F73: =F65-F71 -> 20368.711 | G73: =G65-G71 -> 26722.841 | H73: =H65-H71 -> 31796.549 | I73: =I65-I71 -> 36007.691 | J73: =J65-J71 -> 39348.375 | K73: =K65-K71 -> 42207.587 | L73: =L65-L71 -> 44462.125 | ... S73: =S65-S71 -> 59550.976
A75: COMPUTE & GPU CAPACITY BUILD – inference vs training, GW, accelerators, owned vs rented
A76: Inference / serving compute need ($M, rental-equivalent) | E76: =E65*E17 -> 16509.594 | F76: =F65*F17 -> 27302.74 | G76: =G65*G17 -> 36017.742 | H76: =H65*H17 -> 41688.808 | I76: =I65*I17 -> 45827.97 | J76: =J65*J17 -> 49414.239 | K76: =K65*K17 -> 52257.012 | L76: =L65*L17 -> 55306.545 | ... S76: =S65*S17 -> 71461.171
A77: Training & research compute need ($M, rental-equivalent) | E77: =E65*E18 -> 14445.894 | F77: =F65*F18 -> 21668.842 | G77: =G65*G18 -> 26141.91 | H77: =H65*H18 -> 28970.189 | I77: =I65*I18 -> 31097.551 | J77: =J65*J18 -> 32942.826 | K77: =K65*K18 -> 34168.046 | L77: =L65*L18 -> 34702.146 | ... S77: =S65*S18 -> 41685.683
A78: Total compute need ($M) [hist = reported compute & infra] | B78: =Historicals!B9 -> 433 | C78: =Historicals!C9 -> 2522 | D78: =Historicals!D9 -> 7326 | E78: =E76+E77 -> 30955.488 | F78: =F76+F77 -> 48971.582 | G78: =G76+G77 -> 62159.652 | H78: =H76+H77 -> 70658.997 | I78: =I76+I77 -> 76925.522 | J78: =J76+J77 -> 82357.065 | K78: =K76+K77 -> 86425.058 | L78: =L76+L77 -> 90008.691 | ... S78: =S76+S77 -> 113146.85
A79: Compute need % of revenue | B79: =B78/B65 -> 10.560976 | C79: =C78/C65 -> 6.5336788 | D79: =D78/D65 -> 1.597819 | E79: =E78/E65 -> 0.6 | F79: =F78/F65 -> 0.565 | G79: =G78/G65 -> 0.535 | H79: =H78/H65 -> 0.5 | I79: =I78/I65 -> 0.47 | ... S79: =S78/S65 -> 0.38
A80: Total compute capacity in service (GW) | D80: =D78/$E$19 -> 0.6105 | E80: =E78/E19 -> 2.579624 | F80: =F78/F19 -> 4.1642502 | G80: =G78/G19 -> 5.3935558 | H80: =H78/H19 -> 6.2561643 | I80: =I78/I19 -> 6.9500128 | J80: =J78/J19 -> 7.5926122 | K80: =K78/K19 -> 8.1302206 | L80: =L78/L19 -> 8.6401432 | ... S80: =S78/S19 -> 12.511124
A81: Accelerators in service (000s, GPU / TPU / Trainium equiv.) | D81: =D80*$E$20 -> 396.825 | E81: =E80*E20 -> 1676.7556 | F81: =F80*F20 -> 2625.5597 | G81: =G80*G20 -> 3298.6987 | H81: =H80*H20 -> 3711.1567 | I81: =I80*I20 -> 3999.0374 | J81: =J80*J20 -> 4238.1962 | K81: =K80*K20 -> 4401.7014 | L81: =L80*L20 -> 4537.8032 | ... S81: =S80*S20 -> 5308.47
A82: Owned (Anthropic Direct) capacity – opening (GW) | E82: =D85 -> 0 | F82: =E85 -> 0.0984562 | G82: =F85 -> 0.25691882 | H82: =G85 -> 0.44131466 | I82: =H85 -> 0.61383637 | J82: =I85 -> 0.78729849 | K82: =J85 -> 0.94794834 | L82: =K85 -> 1.0823504 | ... S82: =R85 -> 2.0257311
A83: Total capacity additions (GW) | E83: =MAX(0,E80-D80) -> 1.969124 | F83: =MAX(0,F80-E80) -> 1.5846262 | G83: =MAX(0,G80-F80) -> 1.2293056 | H83: =MAX(0,H80-G80) -> 0.86260855 | I83: =MAX(0,I80-H80) -> 0.69384848 | J83: =MAX(0,J80-I80) -> 0.64259942 | K83: =MAX(0,K80-J80) -> 0.53760839 | L83: =MAX(0,L80-K80) -> 0.50992253 | ... S83: =MAX(0,S80-R80) -> 0.60738088
A84: Owned capacity additions (GW) | E84: =E83*E21 -> 0.0984562 | F84: =F83*F21 -> 0.15846262 | G84: =G83*G21 -> 0.18439584 | H84: =H83*H21 -> 0.17252171 | I84: =I83*I21 -> 0.17346212 | J84: =J83*J21 -> 0.16064985 | K84: =K83*K21 -> 0.1344021 | L84: =L83*L21 -> 0.12748063 | ... S84: =S83*S21 -> 0.15184522
A85: Owned capacity – closing (GW) | D85: 0 | E85: =E82+E84 -> 0.0984562 | F85: =F82+F84 -> 0.25691882 | G85: =G82+G84 -> 0.44131466 | H85: =H82+H84 -> 0.61383637 | I85: =I82+I84 -> 0.78729849 | J85: =J82+J84 -> 0.94794834 | K85: =K82+K84 -> 1.0823504 | L85: =L82+L84 -> 1.2098311 | ... S85: =S82+S84 -> 2.1775763
A86: Owned share of total fleet | E86: =IF(E80>0,E85/E80,0) -> 0.03816688 | F86: =IF(F80>0,F85/F80,0) -> 0.061696297 | G86: =IF(G80>0,G85/G80,0) -> 0.081822582 | H86: =IF(H80>0,H85/H80,0) -> 0.098117047 | I86: =IF(I80>0,I85/I80,0) -> 0.11328015 | J86: =IF(J80>0,J85/J80,0) -> 0.12485141 | K86: =IF(K80>0,K85/K80,0) -> 0.13312682 | L86: =IF(L80>0,L85/L80,0) -> 0.14002442 | ... S86: =IF(S80>0,S85/S80,0) -> 0.17405121
A87: Rented capacity – CSP / leased (GW) | E87: =E80-E85 -> 2.4811678 | F87: =F80-F85 -> 3.9073314 | G87: =G80-G85 -> 4.9522411 | H87: =H80-H85 -> 5.642328 | I87: =I80-I85 -> 6.1627143 | J87: =J80-J85 -> 6.6446639 | K87: =K80-K85 -> 7.0478702 | L87: =L80-L85 -> 7.4303121 | ... S87: =S80-S85 -> 10.333548
A88: Owned accelerators (000s) | E88: =E85*E20 -> 63.99653 | F88: =F85*F20 -> 161.98731 | G88: =G85*G20 -> 269.90805 | H88: =H85*H20 -> 364.12773 | I88: =I85*I20 -> 453.01155 | J88: =J85*J20 -> 529.14477 | K88: =K85*K20 -> 585.98453 | L88: =L85*L20 -> 635.40328 | ... S88: =S85*S20 -> 923.94564
A89: Rented compute expense ($M) | E89: =MAX(0,E78-AVERAGE(E82,E85)*E19) -> 30364.751 | F89: =MAX(0,F78-AVERAGE(F82,F85)*F19) -> 46881.977 | G89: =MAX(0,G78-AVERAGE(G82,G85)*G19) -> 58136.151 | H89: =MAX(0,H78-AVERAGE(H82,H85)*H19) -> 64700.401 | I89: =MAX(0,I78-AVERAGE(I82,I85)*I19) -> 69171.361 | J89: =MAX(0,J78-AVERAGE(J82,J85)*J19) -> 72945.954 | K89: =MAX(0,K78-AVERAGE(K82,K85)*K19) -> 75633.919 | L89: =MAX(0,L78-AVERAGE(L82,L85)*L19) -> 78069.291 | ... S89: =MAX(0,S78-AVERAGE(S82,S85)*S19) -> 94140.128
A90: Owned-fleet power & operations expense ($M) | E90: =AVERAGE(E82,E85)*E23 -> 98.4562 | F90: =AVERAGE(F82,F85)*F23 -> 362.48252 | G90: =AVERAGE(G82,G85)*G23 -> 726.44211 | H90: =AVERAGE(H82,H85)*H23 -> 1119.7263 | I90: =AVERAGE(I82,I85)*I23 -> 1516.6584 | J90: =AVERAGE(J82,J85)*J23 -> 1915.886 | K90: =AVERAGE(K82,K85)*K23 -> 2286.421 | L90: =AVERAGE(L82,L85)*L23 -> 2633.0289 | ... S90: =AVERAGE(S82,S85)*S23 -> 5546.2642
A91: Owned-fleet depreciation ($M) | E91: =AVERAGE(E82,E85)*E22/$E$24 -> 393.8248 | F91: =AVERAGE(F82,F85)*F22/$E$24 -> 1364.6401 | G91: =AVERAGE(G82,G85)*G22/$E$24 -> 2573.9679 | H91: =AVERAGE(H82,H85)*H22/$E$24 -> 3734.1162 | I91: =AVERAGE(I82,I85)*I22/$E$24 -> 4760.2016 | J91: =AVERAGE(J82,J85)*J22/$E$24 -> 5659.4902 | K91: =AVERAGE(K82,K85)*K22/$E$24 -> 6356.9264 | L91: =AVERAGE(L82,L85)*L22/$E$24 -> 6889.8163 | ... S91: =AVERAGE(S82,S85)*S22/$E$24 -> 9493.9686
A92: Compute capex – growth + replacement ($M) | E92: =E84*E22+E82*E22/$E$24 -> 3938.248 | F92: =F84*F22+F82*F22/$E$24 -> 6841.1081 | G92: =G84*G22+G82*G22/$E$24 -> 8691.7794 | H92: =H84*H22+H82*H22/$E$24 -> 9229.012 | I92: =I84*I22+I82*I22/$E$24 -> 10064.068 | J92: =J84*J22+J82*J22/$E$24 -> 10375.111 | K92: =K84*K22+K82*K22/$E$24 -> 10144.279 | L92: =L84*L22+L82*L22/$E$24 -> 10338.436 | ... S92: =S84*S22+S82*S22/$E$24 -> 12580.71
A93: Memo: owned-fleet saving vs renting ($M) | E93: =E78-E89-E90-E91 -> 98.4562 | F93: =F78-F89-F90-F91 -> 362.48252 | G93: =G78-G89-G90-G91 -> 723.09059 | H93: =H78-H89-H90-H91 -> 1104.7537 | I93: =I78-I89-I90-I91 -> 1477.3006 | J93: =J78-J89-J90-J91 -> 1835.735 | K93: =K78-K89-K90-K91 -> 2147.7922 | L93: =L78-L89-L90-L91 -> 2416.5553 | ... S93: =S78-S89-S90-S91 -> 3966.4931
A95: PERSONNEL & OPERATING EXPENSE BUILD ($M)
A96: Headcount – period end (#) | E96: =E25 -> 6000 | F96: =E96*(1+F26) -> 7200 | G96: =F96*(1+G26) -> 8280 | H96: =G96*(1+H26) -> 9108 | I96: =H96*(1+I26) -> 9836.64 | J96: =I96*(1+J26) -> 10426.838 | K96: =J96*(1+K26) -> 10948.18 | L96: =K96*(1+L26) -> 11386.108 | M96: =L96*(1+M26) -> 11784.621 | ... S96: =R96*(1+S26) -> 13665.897
A97: Average headcount (#) | E97: =AVERAGE(Historicals!H172,E96) -> 5650 | F97: =AVERAGE(E96,F96) -> 6600 | G97: =AVERAGE(F96,G96) -> 7740 | H97: =AVERAGE(G96,H96) -> 8694 | I97: =AVERAGE(H96,I96) -> 9472.32 | J97: =AVERAGE(I96,J96) -> 10131.739 | K97: =AVERAGE(J96,K96) -> 10687.509 | L97: =AVERAGE(K96,L96) -> 11167.144 | M97: =AVERAGE(L96,M96) -> 11585.364 | ... S97: =AVERAGE(R96,S96) -> 13531.918
A98: Fully-loaded personnel cost per head ($M) | E98: =E27 -> 1.5 | F98: =E98*(1+F28) -> 1.575 | G98: =F98*(1+G28) -> 1.65375 | H98: =G98*(1+H28) -> 1.7364375 | I98: =H98*(1+I28) -> 1.8232594 | J98: =I98*(1+J28) -> 1.9144223 | K98: =J98*(1+K28) -> 2.0101435 | L98: =K98*(1+L28) -> 2.1106506 | M98: =L98*(1+M28) -> 2.2161832 | ... S98: =R98*(1+S28) -> 2.9698974
A99: Personnel expense (incl. SBC) | B99: =Historicals!B10 -> 95 | C99: =Historicals!C10 -> 454 | D99: =Historicals!D10 -> 1839 | E99: =E45+E97*E98*(1-E50) -> 7389.5 | F99: =F97*F98 -> 10395 | G99: =G97*G98 -> 12800.025 | H99: =H97*H98 -> 15096.588 | I99: =I97*I98 -> 17270.496 | J99: =J97*J98 -> 19396.428 | K99: =K97*K98 -> 21483.427 | L99: =L97*L98 -> 23569.939 | M99: =M97*M98 -> 25675.29 | ... S99: =S97*S98 -> 40188.408
A100: of which: stock-based compensation | B100: =Historicals!B25 -> 29 | C100: =Historicals!C25 -> 192 | D100: =Historicals!D25 -> 1158 | E100: =E48+(E99-E45)*E29 -> 4939.375 | F100: =F99*F29 -> 6237 | G100: =G99*G29 -> 7040.0138 | H100: =H99*H29 -> 7548.2938 | I100: =I99*I29 -> 7944.4283 | J100: =J99*J29 -> 8146.4997 | K100: =K99*K29 -> 8593.3708 | L100: =L99*L29 -> 8956.577 | M100: =M99*M29 -> 9243.1043 | ... S100: =S99*S29 -> 12056.522
A101: of which: cash personnel | B101: =B99-B100 -> 66 | C101: =C99-C100 -> 262 | D101: =D99-D100 -> 681 | E101: =E99-E100 -> 2450.125 | F101: =F99-F100 -> 4158 | G101: =G99-G100 -> 5760.0113 | H101: =H99-H100 -> 7548.2938 | I101: =I99-I100 -> 9326.068 | ... S101: =S99-S100 -> 28131.886
A102: Sales, marketing & partnerships | B102: =Historicals!B12 -> 2 | C102: =Historicals!C12 -> 43 | D102: =Historicals!D12 -> 568 | E102: =E46+E51*E30 -> 10582.361 | F102: =F65*F30 -> 16468.32 | G102: =G65*G30 -> 20332.596 | H102: =H65*H30 -> 23317.469 | I102: =I65*I30 -> 25369.055 | J102: =J65*J30 -> 26537.276 | K102: =K65*K30 -> 28138.391 | L102: =L65*L30 -> 29279.936 | M102: =M65*M30 -> 30144.138 | ... S102: =S65*S30 -> 38708.134
A103: Other operating & administrative | B103: =Historicals!B13 -> 62 | C103: =Historicals!C13 -> 347 | D103: =Historicals!D13 -> 1412 | E103: =E47+E51*E31 -> 5597.7128 | F103: =F65*F31 -> 8667.5366 | G103: =G65*G31 -> 10456.764 | H103: =H65*H31 -> 12012.029 | I103: =I65*I31 -> 13093.706 | J103: =J65*J31 -> 13726.177 | K103: =K65*K31 -> 14069.196 | L103: =L65*L31 -> 15182.189 | M103: =M65*M31 -> 15072.069 | ... S103: =S65*S31 -> 19354.067
A104: Revenue per average employee ($M) | E104: =E65/E97 -> 9.1314124 | F104: =F65/F97 -> 13.132631 | G104: =G65/G97 -> 15.011145 | H104: =H65/H97 -> 16.254658 | I104: =I65/I97 -> 17.278906 | J104: =J65/J97 -> 18.063602 | K104: =K65/K97 -> 18.805926 | L104: =L65/L97 -> 19.422013 | ... S104: =S65/S97 -> 22.003893
A106: INCOME STATEMENT ($M) – opex shown ex-D&A in forecast; S-1 actuals embed immaterial D&A
A107: Revenue | B107: =B65 -> 41 | C107: =C65 -> 386 | D107: =D65 -> 4585 | E107: =E65 -> 51592.48 | F107: =F65 -> 86675.366 | G107: =G65 -> 116186.26 | H107: =H65 -> 141317.99 | I107: =I65 -> 163671.32 | ... S107: =S65 -> 297754.88
A108: Compute & infrastructure (rented + owned-fleet power) | B108: =Historicals!B9 -> 433 | C108: =Historicals!C9 -> 2522 | D108: =Historicals!D9 -> 7326 | E108: =E44+E51*(E89+E90)/E65 -> 29792.003 | F108: =F89+F90 -> 47244.459 | G108: =G89+G90 -> 58862.593 | H108: =H89+H90 -> 65820.127 | I108: =I89+I90 -> 70688.02 | J108: =J89+J90 -> 74861.84 | K108: =K89+K90 -> 77920.34 | L108: =L89+L90 -> 80702.32 | M108: =M89+M90 -> 83845.056 | ... S108: =S89+S90 -> 99686.393
...

Sheet DCF Bull
A1: Anthropic ($ANT) – DCF Valuation Engine (Scenario engine)
A2: Form S-1 filed 26-Oct-2026 | 15-Year Explicit Forecast FY2026E–FY2040E | $ in Millions except per share | Intrinsic value
A3: Identical engine on DCF Bear / DCF Base / DCF Bull – only B5 differs. Do not edit formulas on one engine without copying to the other two.
A5: SCENARIO INDEX | B5: 3 | C5: =CHOOSE(B5,"◀ BEAR","◀ BASE","◀ BULL") -> ◀ BULL | D5: (1 = Bear | 2 = Base | 3 = Bull)
A6: ($ in Millions) | B6: FY2023A | C6: FY2024A | D6: FY2025A | E6: FY2026E | F6: FY2027E | G6: FY2028E | H6: FY2029E | I6: FY2030E | J6: FY2031E | K6: FY2032E | L6: FY2033E | M6: FY2034E | N6: FY2035E | O6: FY2036E | P6: FY2037E | Q6: FY2038E | R6: FY2039E | S6: FY2040E
A8: SELECTED CASE ASSUMPTIONS (auto-pulled from Drivers by scenario index in B5)
A9: Q3 2026 revenue growth (QoQ) | E9: =CHOOSE($B$5,Drivers!E23,Drivers!E54,Drivers!E85) -> 0.52
A10: Q4 2026 revenue growth (QoQ) | E10: =CHOOSE($B$5,Drivers!E24,Drivers!E55,Drivers!E86) -> 0.35
A11: Subscription mix % of FY2026E revenue | E11: =CHOOSE($B$5,Drivers!E25,Drivers!E56,Drivers!E87) -> 0.2
A12: Consumption-based revenue growth (YoY) | F12: =CHOOSE($B$5,Drivers!F26,Drivers!F57,Drivers!F88) -> 1.5 | G12: =CHOOSE($B$5,Drivers!G26,Drivers!G57,Drivers!G88) -> 0.85 | H12: =CHOOSE($B$5,Drivers!H26,Drivers!H57,Drivers!H88) -> 0.55 | I12: =CHOOSE($B$5,Drivers!I26,Drivers!I57,Drivers!I88) -> 0.4 | J12: =CHOOSE($B$5,Drivers!J26,Drivers!J57,Drivers!J88) -> 0.3 | K12: =CHOOSE($B$5,Drivers!K26,Drivers!K57,Drivers!K88) -> 0.24 | L12: =CHOOSE($B$5,Drivers!L26,Drivers!L57,Drivers!L88) -> 0.19 | M12: =CHOOSE($B$5,Drivers!M26,Drivers!M57,Drivers!M88) -> 0.15 | ... S12: =CHOOSE($B$5,Drivers!S26,Drivers!S57,Drivers!S88) -> 0.05
A13: Subscription-based revenue growth (YoY) | F13: =CHOOSE($B$5,Drivers!F27,Drivers!F58,Drivers!F89) -> 1.4 | G13: =CHOOSE($B$5,Drivers!G27,Drivers!G58,Drivers!G89) -> 0.8 | H13: =CHOOSE($B$5,Drivers!H27,Drivers!H58,Drivers!H89) -> 0.5 | I13: =CHOOSE($B$5,Drivers!I27,Drivers!I58,Drivers!I89) -> 0.36 | J13: =CHOOSE($B$5,Drivers!J27,Drivers!J58,Drivers!J89) -> 0.28 | K13: =CHOOSE($B$5,Drivers!K27,Drivers!K58,Drivers!K89) -> 0.22 | L13: =CHOOSE($B$5,Drivers!L27,Drivers!L58,Drivers!L89) -> 0.17 | M13: =CHOOSE($B$5,Drivers!M27,Drivers!M58,Drivers!M89) -> 0.14 | ... S13: =CHOOSE($B$5,Drivers!S27,Drivers!S58,Drivers!S89) -> 0.05
A14: International % of revenue | E14: =CHOOSE($B$5,Drivers!E28,Drivers!E59,Drivers!E90) -> 0.29 | F14: =CHOOSE($B$5,Drivers!F28,Drivers!F59,Drivers!F90) -> 0.3 | G14: =CHOOSE($B$5,Drivers!G28,Drivers!G59,Drivers!G90) -> 0.31 | H14: =CHOOSE($B$5,Drivers!H28,Drivers!H59,Drivers!H90) -> 0.32 | I14: =CHOOSE($B$5,Drivers!I28,Drivers!I59,Drivers!I90) -> 0.33 | J14: =CHOOSE($B$5,Drivers!J28,Drivers!J59,Drivers!J90) -> 0.34 | K14: =CHOOSE($B$5,Drivers!K28,Drivers!K59,Drivers!K90) -> 0.35 | L14: =CHOOSE($B$5,Drivers!L28,Drivers!L59,Drivers!L90) -> 0.36 | ... S14: =CHOOSE($B$5,Drivers!S28,Drivers!S59,Drivers!S90) -> 0.42
A15: Enterprise customers (≥$100K) growth | E15: =CHOOSE($B$5,Drivers!E29,Drivers!E60,Drivers!E91) -> 10 | F15: =CHOOSE($B$5,Drivers!F29,Drivers!F60,Drivers!F91) -> 1.3 | G15: =CHOOSE($B$5,Drivers!G29,Drivers!G60,Drivers!G91) -> 0.8 | H15: =CHOOSE($B$5,Drivers!H29,Drivers!H60,Drivers!H91) -> 0.5 | I15: =CHOOSE($B$5,Drivers!I29,Drivers!I60,Drivers!I91) -> 0.35 | J15: =CHOOSE($B$5,Drivers!J29,Drivers!J60,Drivers!J91) -> 0.26 | K15: =CHOOSE($B$5,Drivers!K29,Drivers!K60,Drivers!K91) -> 0.2 | L15: =CHOOSE($B$5,Drivers!L29,Drivers!L60,Drivers!L91) -> 0.15 | ... S15: =CHOOSE($B$5,Drivers!S29,Drivers!S60,Drivers!S91) -> 0.035
A16: Enterprise (≥$100K) share of revenue | E16: =CHOOSE($B$5,Drivers!E30,Drivers!E61,Drivers!E92) -> 0.79 | F16: =CHOOSE($B$5,Drivers!F30,Drivers!F61,Drivers!F92) -> 0.8 | G16: =CHOOSE($B$5,Drivers!G30,Drivers!G61,Drivers!G92) -> 0.81 | H16: =CHOOSE($B$5,Drivers!H30,Drivers!H61,Drivers!H92) -> 0.82 | I16: =CHOOSE($B$5,Drivers!I30,Drivers!I61,Drivers!I92) -> 0.83 | J16: =CHOOSE($B$5,Drivers!J30,Drivers!J61,Drivers!J92) -> 0.84 | K16: =CHOOSE($B$5,Drivers!K30,Drivers!K61,Drivers!K92) -> 0.85 | L16: =CHOOSE($B$5,Drivers!L30,Drivers!L61,Drivers!L92) -> 0.86 | ... S16: =CHOOSE($B$5,Drivers!S30,Drivers!S61,Drivers!S92) -> 0.88
A17: Inference / serving compute % of revenue | E17: =CHOOSE($B$5,Drivers!E31,Drivers!E62,Drivers!E93) -> 0.29 | F17: =CHOOSE($B$5,Drivers!F31,Drivers!F62,Drivers!F93) -> 0.265 | G17: =CHOOSE($B$5,Drivers!G31,Drivers!G62,Drivers!G93) -> 0.25 | H17: =CHOOSE($B$5,Drivers!H31,Drivers!H62,Drivers!H93) -> 0.235 | I17: =CHOOSE($B$5,Drivers!I31,Drivers!I62,Drivers!I93) -> 0.22 | J17: =CHOOSE($B$5,Drivers!J31,Drivers!J62,Drivers!J93) -> 0.21 | K17: =CHOOSE($B$5,Drivers!K31,Drivers!K62,Drivers!K93) -> 0.2 | L17: =CHOOSE($B$5,Drivers!L31,Drivers!L62,Drivers!L93) -> 0.195 | ... S17: =CHOOSE($B$5,Drivers!S31,Drivers!S62,Drivers!S93) -> 0.18
A18: Training & research compute % of revenue | E18: =CHOOSE($B$5,Drivers!E32,Drivers!E63,Drivers!E94) -> 0.24 | F18: =CHOOSE($B$5,Drivers!F32,Drivers!F63,Drivers!F94) -> 0.2 | G18: =CHOOSE($B$5,Drivers!G32,Drivers!G63,Drivers!G94) -> 0.175 | H18: =CHOOSE($B$5,Drivers!H32,Drivers!H63,Drivers!H94) -> 0.155 | I18: =CHOOSE($B$5,Drivers!I32,Drivers!I63,Drivers!I94) -> 0.14 | J18: =CHOOSE($B$5,Drivers!J32,Drivers!J63,Drivers!J94) -> 0.13 | K18: =CHOOSE($B$5,Drivers!K32,Drivers!K63,Drivers!K94) -> 0.12 | L18: =CHOOSE($B$5,Drivers!L32,Drivers!L63,Drivers!L94) -> 0.11 | ... S18: =CHOOSE($B$5,Drivers!S32,Drivers!S63,Drivers!S94) -> 0.09
A19: Rental-equivalent compute cost per GW-year ($M) | E19: =CHOOSE($B$5,Drivers!E33,Drivers!E64,Drivers!E95) -> 12000 | F19: =CHOOSE($B$5,Drivers!F33,Drivers!F64,Drivers!F95) -> 11760 | G19: =CHOOSE($B$5,Drivers!G33,Drivers!G64,Drivers!G95) -> 11524.8 | H19: =CHOOSE($B$5,Drivers!H33,Drivers!H64,Drivers!H95) -> 11294.3 | I19: =CHOOSE($B$5,Drivers!I33,Drivers!I64,Drivers!I95) -> 11068.4 | J19: =CHOOSE($B$5,Drivers!J33,Drivers!J64,Drivers!J95) -> 10847 | K19: =CHOOSE($B$5,Drivers!K33,Drivers!K64,Drivers!K95) -> 10630.1 | L19: =CHOOSE($B$5,Drivers!L33,Drivers!L64,Drivers!L95) -> 10417.5 | ... S19: =CHOOSE($B$5,Drivers!S33,Drivers!S64,Drivers!S95) -> 9043.7
A20: Accelerators per GW (000s) | E20: =CHOOSE($B$5,Drivers!E34,Drivers!E65,Drivers!E96) -> 650 | F20: =CHOOSE($B$5,Drivers!F34,Drivers!F65,Drivers!F96) -> 630.5 | G20: =CHOOSE($B$5,Drivers!G34,Drivers!G65,Drivers!G96) -> 611.6 | H20: =CHOOSE($B$5,Drivers!H34,Drivers!H65,Drivers!H96) -> 593.2 | I20: =CHOOSE($B$5,Drivers!I34,Drivers!I65,Drivers!I96) -> 575.4 | J20: =CHOOSE($B$5,Drivers!J34,Drivers!J65,Drivers!J96) -> 558.2 | K20: =CHOOSE($B$5,Drivers!K34,Drivers!K65,Drivers!K96) -> 541.4 | L20: =CHOOSE($B$5,Drivers!L34,Drivers!L65,Drivers!L96) -> 525.2 | ... S20: =CHOOSE($B$5,Drivers!S34,Drivers!S65,Drivers!S96) -> 424.3
A21: Anthropic Direct share of new capacity | E21: =CHOOSE($B$5,Drivers!E35,Drivers!E66,Drivers!E97) -> 0.1 | F21: =CHOOSE($B$5,Drivers!F35,Drivers!F66,Drivers!F97) -> 0.25 | G21: =CHOOSE($B$5,Drivers!G35,Drivers!G66,Drivers!G97) -> 0.35 | H21: =CHOOSE($B$5,Drivers!H35,Drivers!H66,Drivers!H97) -> 0.45 | I21: =CHOOSE($B$5,Drivers!I35,Drivers!I66,Drivers!I97) -> 0.5 | J21: =CHOOSE($B$5,Drivers!J35,Drivers!J66,Drivers!J97) -> 0.5 | K21: =CHOOSE($B$5,Drivers!K35,Drivers!K66,Drivers!K97) -> 0.5 | L21: =CHOOSE($B$5,Drivers!L35,Drivers!L66,Drivers!L97) -> 0.5 | ... S21: =CHOOSE($B$5,Drivers!S35,Drivers!S66,Drivers!S97) -> 0.5
A22: Capex per owned GW ($M) | E22: =CHOOSE($B$5,Drivers!E36,Drivers!E67,Drivers!E98) -> 40000 | F22: =CHOOSE($B$5,Drivers!F36,Drivers!F67,Drivers!F98) -> 38400 | G22: =CHOOSE($B$5,Drivers!G36,Drivers!G67,Drivers!G98) -> 36864 | H22: =CHOOSE($B$5,Drivers!H36,Drivers!H67,Drivers!H98) -> 35389.4 | I22: =CHOOSE($B$5,Drivers!I36,Drivers!I67,Drivers!I98) -> 33973.9 | J22: =CHOOSE($B$5,Drivers!J36,Drivers!J67,Drivers!J98) -> 32614.9 | K22: =CHOOSE($B$5,Drivers!K36,Drivers!K67,Drivers!K98) -> 31310.3 | L22: =CHOOSE($B$5,Drivers!L36,Drivers!L67,Drivers!L98) -> 30057.9 | ... S22: =CHOOSE($B$5,Drivers!S36,Drivers!S67,Drivers!S98) -> 22586.9
A23: Power & ops cost per owned GW-year ($M) | E23: =CHOOSE($B$5,Drivers!E37,Drivers!E68,Drivers!E99) -> 2000 | F23: =CHOOSE($B$5,Drivers!F37,Drivers!F68,Drivers!F99) -> 2040 | G23: =CHOOSE($B$5,Drivers!G37,Drivers!G68,Drivers!G99) -> 2080.8 | H23: =CHOOSE($B$5,Drivers!H37,Drivers!H68,Drivers!H99) -> 2122.4 | I23: =CHOOSE($B$5,Drivers!I37,Drivers!I68,Drivers!I99) -> 2164.9 | J23: =CHOOSE($B$5,Drivers!J37,Drivers!J68,Drivers!J99) -> 2208.2 | K23: =CHOOSE($B$5,Drivers!K37,Drivers!K68,Drivers!K99) -> 2252.3 | L23: =CHOOSE($B$5,Drivers!L37,Drivers!L68,Drivers!L99) -> 2297.4 | ... S23: =CHOOSE($B$5,Drivers!S37,Drivers!S68,Drivers!S99) -> 2639
A24: Owned accelerator useful life (years) | E24: =CHOOSE($B$5,Drivers!E38,Drivers!E69,Drivers!E100) -> 5
A25: Headcount – FY2026E period end | E25: =CHOOSE($B$5,Drivers!E39,Drivers!E70,Drivers!E101) -> 6000
A26: Headcount growth (YoY) | F26: =CHOOSE($B$5,Drivers!F40,Drivers!F71,Drivers!F102) -> 0.35 | G26: =CHOOSE($B$5,Drivers!G40,Drivers!G71,Drivers!G102) -> 0.28 | H26: =CHOOSE($B$5,Drivers!H40,Drivers!H71,Drivers!H102) -> 0.22 | I26: =CHOOSE($B$5,Drivers!I40,Drivers!I71,Drivers!I102) -> 0.18 | J26: =CHOOSE($B$5,Drivers!J40,Drivers!J71,Drivers!J102) -> 0.15 | K26: =CHOOSE($B$5,Drivers!K40,Drivers!K71,Drivers!K102) -> 0.12 | L26: =CHOOSE($B$5,Drivers!L40,Drivers!L71,Drivers!L102) -> 0.1 | M26: =CHOOSE($B$5,Drivers!M40,Drivers!M71,Drivers!M102) -> 0.08 | ... S26: =CHOOSE($B$5,Drivers!S40,Drivers!S71,Drivers!S102) -> 0.035
A27: Personnel cost per head – FY2026E ($M) | E27: =CHOOSE($B$5,Drivers!E41,Drivers!E72,Drivers!E103) -> 1.5
A28: Personnel cost per head growth | F28: =CHOOSE($B$5,Drivers!F42,Drivers!F73,Drivers!F104) -> 0.04 | G28: =CHOOSE($B$5,Drivers!G42,Drivers!G73,Drivers!G104) -> 0.04 | H28: =CHOOSE($B$5,Drivers!H42,Drivers!H73,Drivers!H104) -> 0.04 | I28: =CHOOSE($B$5,Drivers!I42,Drivers!I73,Drivers!I104) -> 0.04 | J28: =CHOOSE($B$5,Drivers!J42,Drivers!J73,Drivers!J104) -> 0.04 | K28: =CHOOSE($B$5,Drivers!K42,Drivers!K73,Drivers!K104) -> 0.04 | L28: =CHOOSE($B$5,Drivers!L42,Drivers!L73,Drivers!L104) -> 0.04 | M28: =CHOOSE($B$5,Drivers!M42,Drivers!M73,Drivers!M104) -> 0.04 | ... S28: =CHOOSE($B$5,Drivers!S42,Drivers!S73,Drivers!S104) -> 0.04
A29: SBC % of personnel | E29: =CHOOSE($B$5,Drivers!E43,Drivers!E74,Drivers!E105) -> 0.65 | F29: =CHOOSE($B$5,Drivers!F43,Drivers!F74,Drivers!F105) -> 0.6 | G29: =CHOOSE($B$5,Drivers!G43,Drivers!G74,Drivers!G105) -> 0.55 | H29: =CHOOSE($B$5,Drivers!H43,Drivers!H74,Drivers!H105) -> 0.5 | I29: =CHOOSE($B$5,Drivers!I43,Drivers!I74,Drivers!I105) -> 0.46 | J29: =CHOOSE($B$5,Drivers!J43,Drivers!J74,Drivers!J105) -> 0.42 | K29: =CHOOSE($B$5,Drivers!K43,Drivers!K74,Drivers!K105) -> 0.4 | L29: =CHOOSE($B$5,Drivers!L43,Drivers!L74,Drivers!L105) -> 0.38 | ... S29: =CHOOSE($B$5,Drivers!S43,Drivers!S74,Drivers!S105) -> 0.3
A30: Sales, marketing & partnerships % of revenue | E30: =CHOOSE($B$5,Drivers!E44,Drivers!E75,Drivers!E106) -> 0.185 | F30: =CHOOSE($B$5,Drivers!F44,Drivers!F75,Drivers!F106) -> 0.16 | G30: =CHOOSE($B$5,Drivers!G44,Drivers!G75,Drivers!G106) -> 0.145 | H30: =CHOOSE($B$5,Drivers!H44,Drivers!H75,Drivers!H106) -> 0.135 | I30: =CHOOSE($B$5,Drivers!I44,Drivers!I75,Drivers!I106) -> 0.125 | J30: =CHOOSE($B$5,Drivers!J44,Drivers!J75,Drivers!J106) -> 0.115 | K30: =CHOOSE($B$5,Drivers!K44,Drivers!K75,Drivers!K106) -> 0.11 | L30: =CHOOSE($B$5,Drivers!L44,Drivers!L75,Drivers!L106) -> 0.105 | ... S30: =CHOOSE($B$5,Drivers!S44,Drivers!S75,Drivers!S106) -> 0.1
A31: Other operating & admin % of revenue | E31: =CHOOSE($B$5,Drivers!E45,Drivers!E76,Drivers!E107) -> 0.095 | F31: =CHOOSE($B$5,Drivers!F45,Drivers!F76,Drivers!F107) -> 0.085 | G31: =CHOOSE($B$5,Drivers!G45,Drivers!G76,Drivers!G107) -> 0.075 | H31: =CHOOSE($B$5,Drivers!H45,Drivers!H76,Drivers!H107) -> 0.07 | I31: =CHOOSE($B$5,Drivers!I45,Drivers!I76,Drivers!I107) -> 0.065 | J31: =CHOOSE($B$5,Drivers!J45,Drivers!J76,Drivers!J107) -> 0.06 | K31: =CHOOSE($B$5,Drivers!K45,Drivers!K76,Drivers!K107) -> 0.055 | L31: =CHOOSE($B$5,Drivers!L45,Drivers!L76,Drivers!L107) -> 0.055 | ... S31: =CHOOSE($B$5,Drivers!S45,Drivers!S76,Drivers!S107) -> 0.05
A32: Other (non-compute) capex % of revenue | E32: =CHOOSE($B$5,Drivers!E46,Drivers!E77,Drivers!E108) -> 0.008 | F32: =CHOOSE($B$5,Drivers!F46,Drivers!F77,Drivers!F108) -> 0.008 | G32: =CHOOSE($B$5,Drivers!G46,Drivers!G77,Drivers!G108) -> 0.008 | H32: =CHOOSE($B$5,Drivers!H46,Drivers!H77,Drivers!H108) -> 0.008 | I32: =CHOOSE($B$5,Drivers!I46,Drivers!I77,Drivers!I108) -> 0.008 | J32: =CHOOSE($B$5,Drivers!J46,Drivers!J77,Drivers!J108) -> 0.008 | K32: =CHOOSE($B$5,Drivers!K46,Drivers!K77,Drivers!K108) -> 0.008 | L32: =CHOOSE($B$5,Drivers!L46,Drivers!L77,Drivers!L108) -> 0.008 | ... S32: =CHOOSE($B$5,Drivers!S46,Drivers!S77,Drivers!S108) -> 0.008
A33: Other D&A % of revenue | E33: =CHOOSE($B$5,Drivers!E47,Drivers!E78,Drivers!E109) -> 0.005 | F33: =CHOOSE($B$5,Drivers!F47,Drivers!F78,Drivers!F109) -> 0.005 | G33: =CHOOSE($B$5,Drivers!G47,Drivers!G78,Drivers!G109) -> 0.005 | H33: =CHOOSE($B$5,Drivers!H47,Drivers!H78,Drivers!H109) -> 0.005 | I33: =CHOOSE($B$5,Drivers!I47,Drivers!I78,Drivers!I109) -> 0.005 | J33: =CHOOSE($B$5,Drivers!J47,Drivers!J78,Drivers!J109) -> 0.005 | K33: =CHOOSE($B$5,Drivers!K47,Drivers!K78,Drivers!K109) -> 0.005 | L33: =CHOOSE($B$5,Drivers!L47,Drivers!L78,Drivers!L109) -> 0.005 | ... S33: =CHOOSE($B$5,Drivers!S47,Drivers!S78,Drivers!S109) -> 0.005
A34: ΔNWC % of Δrevenue | E34: =CHOOSE($B$5,Drivers!E48,Drivers!E79,Drivers!E110) -> 0.02 | F34: =CHOOSE($B$5,Drivers!F48,Drivers!F79,Drivers!F110) -> 0.02 | G34: =CHOOSE($B$5,Drivers!G48,Drivers!G79,Drivers!G110) -> 0.02 | H34: =CHOOSE($B$5,Drivers!H48,Drivers!H79,Drivers!H110) -> 0.02 | I34: =CHOOSE($B$5,Drivers!I48,Drivers!I79,Drivers!I110) -> 0.02 | J34: =CHOOSE($B$5,Drivers!J48,Drivers!J79,Drivers!J110) -> 0.02 | K34: =CHOOSE($B$5,Drivers!K48,Drivers!K79,Drivers!K110) -> 0.02 | L34: =CHOOSE($B$5,Drivers!L48,Drivers!L79,Drivers!L110) -> 0.02 | ... S34: =CHOOSE($B$5,Drivers!S48,Drivers!S79,Drivers!S110) -> 0.02
A35: Terminal growth rate | E35: =CHOOSE($B$5,Drivers!E49,Drivers!E80,Drivers!E111) -> 0.04
A36: Exit EV / EBITDA multiple | E36: =CHOOSE($B$5,Drivers!E50,Drivers!E81,Drivers!E112) -> 17
A37: Scenario probability weight | E37: =CHOOSE($B$5,Drivers!E51,Drivers!E82,Drivers!E113) -> 0.25
A38: WACC (WACC tab) | E38: =CHOOSE($B$5,WACC!B27,WACC!B28,WACC!B29) -> 0.13367493
A39: Terminal-period WACC (mature stage, WACC tab) | E39: =CHOOSE($B$5,WACC!F27,WACC!F28,WACC!F29) -> 0.10015294
A40: Cash tax rate | E40: =WACC!B9 -> 0.23
A42: FY2026 YEAR-TO-DATE ACTUALS (Historicals column named in Actuals!B5 – re-points automatically)
A43: YTD revenue | E43: =INDEX(Historicals!$B$7:$K$7,MATCH(Actuals!$B$5,Historicals!$B$6:$K$6,0)) -> 16286
A44: YTD compute & infrastructure | E44: =INDEX(Historicals!$B$9:$K$9,MATCH(Actuals!$B$5,Historicals!$B$6:$K$6,0)) -> 8945
A45: YTD personnel | E45: =INDEX(Historicals!$B$10:$K$10,MATCH(Actuals!$B$5,Historicals!$B$6:$K$6,0)) -> 3152
A46: YTD sales, marketing & partnerships | E46: =INDEX(Historicals!$B$12:$K$12,MATCH(Actuals!$B$5,Historicals!$B$6:$K$6,0)) -> 3168
A47: YTD other operating & administrative | E47: =INDEX(Historicals!$B$13:$K$13,MATCH(Actuals!$B$5,Historicals!$B$6:$K$6,0)) -> 1714
A48: YTD stock-based compensation | E48: =INDEX(Historicals!$B$25:$K$25,MATCH(Actuals!$B$5,Historicals!$B$6:$K$6,0)) -> 2185
A49: YTD depreciation & amortization | E49: =INDEX(Historicals!$B$26:$K$26,MATCH(Actuals!$B$5,Historicals!$B$6:$K$6,0)) -> 97
A50: YTD fraction of fiscal year | E50: =Actuals!$B$6/12 -> 0.5
A51: Remaining FY2026E revenue (full year − YTD) | E51: =E65-E43 -> 41274.46
A52: YTD unlevered FCF proxy (CFO − capex − after-tax interest income) | E52: =INDEX(Historicals!$B$128:$K$128,MATCH(Actuals!$B$5,Historicals!$B$113:$K$113,0))+INDEX(Historicals!$B$130:$K$130,MATCH(Actuals!$B$5,Historicals!$B$113:$K$113,0))-INDEX(Historicals!$B$16:$K$16,MATCH(Actuals!$B$5,Historicals!$B$6:$K$6,0))*(1-$E$40) -> 2591.53
A54: FY2026E QUARTERLY REVENUE BUILD (reported quarters override estimates)
A55: Quarter | B55: Q1 2026 | C55: Q2 2026 | D55: Q3 2026 | E55: Q4 2026 | F55: FY2026E
A56: Reported revenue (Historicals) | B56: =IFERROR(IF(INDEX(Historicals!$B$33:$M$33,MATCH(B$55&"A",Historicals!$B$32:$M$32,0))="","",INDEX(Historicals!$B$33:$M$33,MATCH(B$55&"A",Historicals!$B$32:$M$32,0))),"") -> 4731 | C56: =IFERROR(IF(INDEX(Historicals!$B$33:$M$33,MATCH(C$55&"A",Historicals!$B$32:$M$32,0))="","",INDEX(Historicals!$B$33:$M$33,MATCH(C$55&"A",Historicals!$B$32:$M$32,0))),"") -> 11555 | D56: =IFERROR(IF(INDEX(Historicals!$B$33:$M$33,MATCH(D$55&"A",Historicals!$B$32:$M$32,0))="","",INDEX(Historicals!$B$33:$M$33,MATCH(D$55&"A",Historicals!$B$32:$M$32,0))),"") | E56: =IFERROR(IF(INDEX(Historicals!$B$33:$M$33,MATCH(E$55&"A",Historicals!$B$32:$M$32,0))="","",INDEX(Historicals!$B$33:$M$33,MATCH(E$55&"A",Historicals!$B$32:$M$32,0))),"")
A57: QoQ growth (actual if reported, else driver) | B57: =IF(B56<>"",B56/Historicals!$E$33-1,0) -> 1.3191176 | C57: =IF(C56<>"",C56/B58-1,0) -> 1.4424012 | D57: =IF(D56<>"",D56/C58-1,$E$9) -> 0.52 | E57: =IF(E56<>"",E56/D58-1,$E$10) -> 0.35
A58: Revenue – selected | B58: =IF(B56<>"",B56,Historicals!$E$33*(1+B57)) -> 4731 | C58: =IF(C56<>"",C56,B58*(1+C57)) -> 11555 | D58: =IF(D56<>"",D56,C58*(1+D57)) -> 17563.6 | E58: =IF(E56<>"",E56,D58*(1+E57)) -> 23710.86 | F58: =SUM(B58:E58) -> 57560.46
A59: Status | B59: =IF(B56<>"","Actual","Estimate") -> Actual | C59: =IF(C56<>"","Actual","Estimate") -> Actual | D59: =IF(D56<>"","Actual","Estimate") -> Estimate | E59: =IF(E56<>"","Actual","Estimate") -> Estimate
A60: Annualised revenue run-rate (quarter × 4) | B60: =B58*4 -> 18924 | C60: =C58*4 -> 46220 | D60: =D58*4 -> 70254.4 | E60: =E58*4 -> 94843.44
A62: REVENUE BUILD – by pricing model, geography and customer cohort ($M)
A63: Consumption-based revenue (API / platform / pay-for-intelligence) | B63: =Historicals!B72 -> 39 | C63: =Historicals!C72 -> 288 | D63: =Historicals!D72 -> 3796 | E63: =E65-E64 -> 46048.368 | F63: =E63*(1+F12) -> 115120.92 | G63: =F63*(1+G12) -> 212973.7 | H63: =G63*(1+H12) -> 330109.24 | I63: =H63*(1+I12) -> 462152.93 | J63: =I63*(1+J12) -> 600798.81 | K63: =J63*(1+K12) -> 744990.53 | L63: =K63*(1+L12) -> 886538.73 | M63: =L63*(1+M12) -> 1019519.5 | ... S63: =R63*(1+S12) -> 1622986.6
A64: Subscription-based revenue (Pro / Max / Team / Enterprise) | B64: =Historicals!B73 -> 2 | C64: =Historicals!C73 -> 98 | D64: =Historicals!D73 -> 789 | E64: =E65*E11 -> 11512.092 | F64: =E64*(1+F13) -> 27629.021 | G64: =F64*(1+G13) -> 49732.237 | H64: =G64*(1+H13) -> 74598.356 | I64: =H64*(1+I13) -> 101453.76 | J64: =I64*(1+J13) -> 129860.82 | K64: =J64*(1+K13) -> 158430.2 | L64: =K64*(1+L13) -> 185363.33 | M64: =L64*(1+M13) -> 211314.2 | ... S64: =R64*(1+S13) -> 325756.64
A65: Total Revenue | B65: =Historicals!B7 -> 41 | C65: =Historicals!C7 -> 386 | D65: =Historicals!D7 -> 4585 | E65: =F58 -> 57560.46 | F65: =F63+F64 -> 142749.94 | G65: =G63+G64 -> 262705.94 | H65: =H63+H64 -> 404707.59 | I65: =I63+I64 -> 563606.7 | J65: =J63+J64 -> 730659.63 | K65: =K63+K64 -> 903420.73 | L65: =L63+L64 -> 1071902.1 | M65: =M63+M64 -> 1230833.7 | ... S65: =S63+S64 -> 1948743.3
A66: % YoY growth | C66: =C65/B65-1 -> 8.4146341 | D66: =D65/C65-1 -> 10.878238 | E66: =E65/D65-1 -> 11.554081 | F66: =F65/E65-1 -> 1.48 | G66: =G65/F65-1 -> 0.84032258 | H66: =H65/G65-1 -> 0.54053462 | I66: =I65/H65-1 -> 0.39262694 | J66: =J65/I65-1 -> 0.29639984 | ... S66: =S65/R65-1 -> 0.05
A67: Subscription mix % | B67: =B64/B65 -> 0.048780488 | C67: =C64/C65 -> 0.25388601 | D67: =D64/D65 -> 0.17208288 | E67: =E64/E65 -> 0.2 | F67: =F64/F65 -> 0.19354839 | G67: =G64/G65 -> 0.18930762 | H67: =H64/H65 -> 0.18432655 | I67: =I64/I65 -> 0.18000809 | ... S67: =S64/S65 -> 0.16716242
A68: United States revenue | B68: =Historicals!B69 -> 34 | C68: =Historicals!C69 -> 263 | D68: =Historicals!D69 -> 3362 | E68: =E65*(1-E14) -> 40867.927 | F68: =F65*(1-F14) -> 99924.959 | G68: =G65*(1-G14) -> 181267.1 | H68: =H65*(1-H14) -> 275201.16 | I68: =I65*(1-I14) -> 377616.49 | J68: =J65*(1-J14) -> 482235.36 | K68: =K65*(1-K14) -> 587223.47 | L68: =L65*(1-L14) -> 686017.32 | ... S68: =S65*(1-S14) -> 1130271.1
A69: International revenue | B69: =Historicals!B70 -> 7 | C69: =Historicals!C70 -> 123 | D69: =Historicals!D70 -> 1223 | E69: =E65*E14 -> 16692.533 | F69: =F65*F14 -> 42824.982 | G69: =G65*G14 -> 81438.841 | H69: =H65*H14 -> 129506.43 | I69: =I65*I14 -> 185990.21 | J69: =J65*J14 -> 248424.27 | K69: =K65*K14 -> 316197.25 | L69: =L65*L14 -> 385884.74 | ... S69: =S65*S14 -> 818472.17
A70: Enterprise customers ≥$100K TTM (period end, #) | D70: =Historicals!E168 -> 1500 | E70: =D70*(1+E15) -> 16500 | F70: =E70*(1+F15) -> 37950 | G70: =F70*(1+G15) -> 68310 | H70: =G70*(1+H15) -> 102465 | I70: =H70*(1+I15) -> 138327.75 | J70: =I70*(1+J15) -> 174292.96 | K70: =J70*(1+K15) -> 209151.56 | L70: =K70*(1+L15) -> 240524.29 | ... S70: =R70*(1+S15) -> 376405.62
A71: Enterprise cohort revenue (≥$100K customers) | E71: =E65*E16 -> 45472.763 | F71: =F65*F16 -> 114199.95 | G71: =G65*G16 -> 212791.81 | H71: =H65*H16 -> 331860.23 | I71: =I65*I16 -> 467793.56 | J71: =J65*J16 -> 613754.09 | K71: =K65*K16 -> 767907.62 | L71: =L65*L16 -> 921835.77 | ... S71: =S65*S16 -> 1714894.1
A72: Avg revenue per enterprise customer ($M) | E72: =E71/AVERAGE(D70,E70) -> 5.0525293 | F72: =F71/AVERAGE(E70,F70) -> 4.1946723 | G72: =G71/AVERAGE(F70,G70) -> 4.005116 | H72: =H71/AVERAGE(G70,H70) -> 3.88652 | I72: =I71/AVERAGE(H70,I70) -> 3.8854455 | J72: =J71/AVERAGE(I70,J70) -> 3.9265094 | K72: =K71/AVERAGE(J70,K70) -> 4.0053127 | L72: =L71/AVERAGE(K70,L70) -> 4.1000012 | ... S72: =S71/AVERAGE(R70,S70) -> 4.6343319
A73: Long-tail revenue (<$100K customers) | E73: =E65-E71 -> 12087.697 | F73: =F65-F71 -> 28549.988 | G73: =G65-G71 -> 49914.128 | H73: =H65-H71 -> 72847.367 | I73: =I65-I71 -> 95813.139 | J73: =J65-J71 -> 116905.54 | K73: =K65-K71 -> 135513.11 | L73: =L65-L71 -> 150066.29 | ... S73: =S65-S71 -> 233849.19
A75: COMPUTE & GPU CAPACITY BUILD – inference vs training, GW, accelerators, owned vs rented
A76: Inference / serving compute need ($M, rental-equivalent) | E76: =E65*E17 -> 16692.533 | F76: =F65*F17 -> 37828.734 | G76: =G65*G17 -> 65676.485 | H76: =H65*H17 -> 95106.285 | I76: =I65*I17 -> 123993.47 | J76: =J65*J17 -> 153438.52 | K76: =K65*K17 -> 180684.15 | L76: =L65*L17 -> 209020.9 | ... S76: =S65*S17 -> 350773.79
A77: Training & research compute need ($M, rental-equivalent) | E77: =E65*E18 -> 13814.51 | F77: =F65*F18 -> 28549.988 | G77: =G65*G18 -> 45973.539 | H77: =H65*H18 -> 62729.677 | I77: =I65*I18 -> 78904.938 | J77: =J65*J18 -> 94985.752 | K77: =K65*K18 -> 108410.49 | L77: =L65*L18 -> 117909.23 | ... S77: =S65*S18 -> 175386.89
A78: Total compute need ($M) [hist = reported compute & infra] | B78: =Historicals!B9 -> 433 | C78: =Historicals!C9 -> 2522 | D78: =Historicals!D9 -> 7326 | E78: =E76+E77 -> 30507.044 | F78: =F76+F77 -> 66378.722 | G78: =G76+G77 -> 111650.02 | H78: =H76+H77 -> 157835.96 | I78: =I76+I77 -> 202898.41 | J78: =J76+J77 -> 248424.27 | K78: =K76+K77 -> 289094.63 | L78: =L76+L77 -> 326930.13 | ... S78: =S76+S77 -> 526160.68
A79: Compute need % of revenue | B79: =B78/B65 -> 10.560976 | C79: =C78/C65 -> 6.5336788 | D79: =D78/D65 -> 1.597819 | E79: =E78/E65 -> 0.53 | F79: =F78/F65 -> 0.465 | G79: =G78/G65 -> 0.425 | H79: =H78/H65 -> 0.39 | I79: =I78/I65 -> 0.36 | ... S79: =S78/S65 -> 0.27
A80: Total compute capacity in service (GW) | D80: =D78/$E$19 -> 0.6105 | E80: =E78/E19 -> 2.5422537 | F80: =F78/F19 -> 5.6444492 | G80: =G78/G19 -> 9.6878058 | H80: =H78/H19 -> 13.974833 | I80: =I78/I19 -> 18.331323 | J80: =J78/J19 -> 22.902579 | K80: =K78/K19 -> 27.195853 | L80: =L78/L19 -> 31.382782 | ... S80: =S78/S19 -> 58.179803
A81: Accelerators in service (000s, GPU / TPU / Trainium equiv.) | D81: =D80*$E$20 -> 396.825 | E81: =E80*E20 -> 1652.4649 | F81: =F80*F20 -> 3558.8252 | G81: =G80*G20 -> 5925.062 | H81: =H80*H20 -> 8289.8712 | I81: =I80*I20 -> 10547.843 | J81: =J80*J20 -> 12784.22 | K81: =K80*K20 -> 14723.835 | L81: =L80*L20 -> 16482.237 | ... S81: =S80*S20 -> 24685.69
A82: Owned (Anthropic Direct) capacity – opening (GW) | E82: =D85 -> 0 | F82: =E85 -> 0.19317537 | G82: =F85 -> 0.96872425 | H82: =G85 -> 2.3838991 | I82: =H85 -> 4.3130615 | J82: =I85 -> 6.4913061 | K82: =J85 -> 8.7769343 | L82: =K85 -> 10.923571 | ... S82: =R85 -> 24.476117
A83: Total capacity additions (GW) | E83: =MAX(0,E80-D80) -> 1.9317537 | F83: =MAX(0,F80-E80) -> 3.1021955 | G83: =MAX(0,G80-F80) -> 4.0433566 | H83: =MAX(0,H80-G80) -> 4.2870277 | I83: =MAX(0,I80-H80) -> 4.3564891 | J83: =MAX(0,J80-I80) -> 4.5712564 | K83: =MAX(0,K80-J80) -> 4.2932736 | L83: =MAX(0,L80-K80) -> 4.1869291 | ... S83: =MAX(0,S80-R80) -> 3.8788577
A84: Owned capacity additions (GW) | E84: =E83*E21 -> 0.19317537 | F84: =F83*F21 -> 0.77554888 | G84: =G83*G21 -> 1.4151748 | H84: =H83*H21 -> 1.9291625 | I84: =I83*I21 -> 2.1782446 | J84: =J83*J21 -> 2.2856282 | K84: =K83*K21 -> 2.1466368 | L84: =L83*L21 -> 2.0934646 | ... S84: =S83*S21 -> 1.9394288
A85: Owned capacity – closing (GW) | D85: 0 | E85: =E82+E84 -> 0.19317537 | F85: =F82+F84 -> 0.96872425 | G85: =G82+G84 -> 2.3838991 | H85: =H82+H84 -> 4.3130615 | I85: =I82+I84 -> 6.4913061 | J85: =J82+J84 -> 8.7769343 | K85: =K82+K84 -> 10.923571 | L85: =L82+L84 -> 13.017036 | ... S85: =S82+S84 -> 26.415546
A86: Owned share of total fleet | E86: =IF(E80>0,E85/E80,0) -> 0.075985874 | F86: =IF(F80>0,F85/F80,0) -> 0.17162423 | G86: =IF(G80>0,G85/G80,0) -> 0.24607214 | H86: =IF(H80>0,H85/H80,0) -> 0.30863062 | I86: =IF(I80>0,I85/I80,0) -> 0.35411008 | J86: =IF(J80>0,J85/J80,0) -> 0.38322908 | K86: =IF(K80>0,K85/K80,0) -> 0.40166312 | L86: =IF(L80>0,L85/L80,0) -> 0.41478272 | ... S86: =IF(S80>0,S85/S80,0) -> 0.45403293
A87: Rented capacity – CSP / leased (GW) | E87: =E80-E85 -> 2.3490783 | F87: =F80-F85 -> 4.6757249 | G87: =G80-G85 -> 7.3039067 | H87: =H80-H85 -> 9.661772 | I87: =I80-I85 -> 11.840017 | J87: =J80-J85 -> 14.125645 | K87: =K80-K85 -> 16.272282 | L87: =L80-L85 -> 18.365746 | ... S87: =S80-S85 -> 31.764257
A88: Owned accelerators (000s) | E88: =E85*E20 -> 125.56399 | F88: =F85*F20 -> 610.78064 | G88: =G85*G20 -> 1457.9927 | H88: =H85*H20 -> 2558.5081 | I88: =I85*I20 -> 3735.0975 | J88: =J85*J20 -> 4899.2847 | K88: =K85*K20 -> 5914.0214 | L88: =L85*L20 -> 6836.5471 | ... S88: =S85*S20 -> 11208.116
A89: Rented compute expense ($M) | E89: =MAX(0,E78-AVERAGE(E82,E85)*E19) -> 29347.992 | F89: =MAX(0,F78-AVERAGE(F82,F85)*F19) -> 59546.753 | G89: =MAX(0,G78-AVERAGE(G82,G85)*G19) -> 92330.868 | H89: =MAX(0,H78-AVERAGE(H82,H85)*H19) -> 120017.22 | I89: =MAX(0,I78-AVERAGE(I82,I85)*I19) -> 143104.88 | J89: =MAX(0,J78-AVERAGE(J82,J85)*J19) -> 165616.97 | K89: =MAX(0,K78-AVERAGE(K82,K85)*K19) -> 184385.46 | L89: =MAX(0,L78-AVERAGE(L82,L85)*L19) -> 202229.49 | ... S89: =MAX(0,S78-AVERAGE(S82,S85)*S19) -> 296036.21
A90: Owned-fleet power & operations expense ($M) | E90: =AVERAGE(E82,E85)*E23 -> 193.17537 | F90: =AVERAGE(F82,F85)*F23 -> 1185.1376 | G90: =AVERAGE(G82,G85)*G23 -> 3488.0693 | H90: =AVERAGE(H82,H85)*H23 -> 7106.8146 | I90: =AVERAGE(I82,I85)*I23 -> 11695.188 | J90: =AVERAGE(J82,J85)*J23 -> 16857.664 | K90: =AVERAGE(K82,K85)*K23 -> 22185.724 | L90: =AVERAGE(L82,L85)*L23 -> 27500.575 | ... S90: =AVERAGE(S82,S85)*S23 -> 67151.55
A91: Owned-fleet depreciation ($M) | E91: =AVERAGE(E82,E85)*E22/$E$24 -> 772.70146 | F91: =AVERAGE(F82,F85)*F22/$E$24 -> 4461.6945 | G91: =AVERAGE(G82,G85)*G22/$E$24 -> 12359.111 | H91: =AVERAGE(H82,H85)*H22/$E$24 -> 23700.142 | I91: =AVERAGE(I82,I85)*I22/$E$24 -> 36706.65 | J91: =AVERAGE(J82,J85)*J22/$E$24 -> 49797.213 | K91: =AVERAGE(K82,K85)*K22/$E$24 -> 61682.873 | L91: =AVERAGE(L82,L85)*L22/$E$24 -> 71960.436 | ... S91: =AVERAGE(S82,S85)*S22/$E$24 -> 114948.49
A92: Compute capex – growth + replacement ($M) | E92: =E84*E22+E82*E22/$E$24 -> 7727.0146 | F92: =F84*F22+F82*F22/$E$24 -> 31264.664 | G92: =G84*G22+G82*G22/$E$24 -> 59311.214 | H92: =H84*H22+H82*H22/$E$24 -> 85144.853 | I92: =I84*I22+I82*I22/$E$24 -> 103309.77 | J92: =J84*J22+J82*J22/$E$24 -> 116888.2 | K92: =K84*K22+K82*K22/$E$24 -> 122173.53 | L92: =L84*L22+L82*L22/$E$24 -> 128593.07 | ... S92: =S84*S22+S82*S22/$E$24 -> 154373.61
A93: Memo: owned-fleet saving vs renting ($M) | E93: =E78-E89-E90-E91 -> 193.17536 | F93: =F78-F89-F90-F91 -> 1185.1376 | G93: =G78-G89-G90-G91 -> 3471.9767 | H93: =H78-H89-H90-H91 -> 7011.7847 | I93: =I78-I89-I90-I91 -> 11391.693 | J93: =J78-J89-J90-J91 -> 16152.424 | K93: =K78-K89-K90-K91 -> 20840.574 | L93: =L78-L89-L90-L91 -> 25239.624 | ... S93: =S78-S89-S90-S91 -> 48024.427
A95: PERSONNEL & OPERATING EXPENSE BUILD ($M)
A96: Headcount – period end (#) | E96: =E25 -> 6000 | F96: =E96*(1+F26) -> 8100 | G96: =F96*(1+G26) -> 10368 | H96: =G96*(1+H26) -> 12648.96 | I96: =H96*(1+I26) -> 14925.773 | J96: =I96*(1+J26) -> 17164.639 | K96: =J96*(1+K26) -> 19224.395 | L96: =K96*(1+L26) -> 21146.835 | M96: =L96*(1+M26) -> 22838.582 | ... S96: =R96*(1+S26) -> 30594.126
A97: Average headcount (#) | E97: =AVERAGE(Historicals!H172,E96) -> 5650 | F97: =AVERAGE(E96,F96) -> 7050 | G97: =AVERAGE(F96,G96) -> 9234 | H97: =AVERAGE(G96,H96) -> 11508.48 | I97: =AVERAGE(H96,I96) -> 13787.366 | J97: =AVERAGE(I96,J96) -> 16045.206 | K97: =AVERAGE(J96,K96) -> 18194.517 | L97: =AVERAGE(K96,L96) -> 20185.615 | M97: =AVERAGE(L96,M96) -> 21992.708 | ... S97: =AVERAGE(R96,S96) -> 30076.834
A98: Fully-loaded personnel cost per head ($M) | E98: =E27 -> 1.5 | F98: =E98*(1+F28) -> 1.56 | G98: =F98*(1+G28) -> 1.6224 | H98: =G98*(1+H28) -> 1.687296 | I98: =H98*(1+I28) -> 1.7547878 | J98: =I98*(1+J28) -> 1.8249794 | K98: =J98*(1+K28) -> 1.8979785 | L98: =K98*(1+L28) -> 1.9738977 | M98: =L98*(1+M28) -> 2.0528536 | ... S98: =R98*(1+S28) -> 2.5975147
A99: Personnel expense (incl. SBC) | B99: =Historicals!B10 -> 95 | C99: =Historicals!C10 -> 454 | D99: =Historicals!D10 -> 1839 | E99: =E45+E97*E98*(1-E50) -> 7389.5 | F99: =F97*F98 -> 10998 | G99: =G97*G98 -> 14981.242 | H99: =H97*H98 -> 19418.212 | I99: =I97*I98 -> 24193.903 | J99: =J97*J98 -> 29282.169 | K99: =K97*K98 -> 34532.803 | L99: =L97*L98 -> 39844.339 | M99: =M97*M98 -> 45147.81 | ... S99: =S97*S98 -> 78125.018
A100: of which: stock-based compensation | B100: =Historicals!B25 -> 29 | C100: =Historicals!C25 -> 192 | D100: =Historicals!D25 -> 1158 | E100: =E48+(E99-E45)*E29 -> 4939.375 | F100: =F99*F29 -> 6598.8 | G100: =G99*G29 -> 8239.6829 | H100: =H99*H29 -> 9709.1061 | I100: =I99*I29 -> 11129.195 | J100: =J99*J29 -> 12298.511 | K100: =K99*K29 -> 13813.121 | L100: =L99*L29 -> 15140.849 | M100: =M99*M29 -> 16253.212 | ... S100: =S99*S29 -> 23437.505
A101: of which: cash personnel | B101: =B99-B100 -> 66 | C101: =C99-C100 -> 262 | D101: =D99-D100 -> 681 | E101: =E99-E100 -> 2450.125 | F101: =F99-F100 -> 4399.2 | G101: =G99-G100 -> 6741.5587 | H101: =H99-H100 -> 9709.1061 | I101: =I99-I100 -> 13064.708 | ... S101: =S99-S100 -> 54687.512
A102: Sales, marketing & partnerships | B102: =Historicals!B12 -> 2 | C102: =Historicals!C12 -> 43 | D102: =Historicals!D12 -> 568 | E102: =E46+E51*E30 -> 10803.775 | F102: =F65*F30 -> 22839.991 | G102: =G65*G30 -> 38092.361 | H102: =H65*H30 -> 54635.525 | I102: =I65*I30 -> 70450.837 | J102: =J65*J30 -> 84025.858 | K102: =K65*K30 -> 99376.28 | L102: =L65*L30 -> 112549.72 | M102: =M65*M30 -> 123083.37 | ... S102: =S65*S30 -> 194874.33
A103: Other operating & administrative | B103: =Historicals!B13 -> 62 | C103: =Historicals!C13 -> 347 | D103: =Historicals!D13 -> 1412 | E103: =E47+E51*E31 -> 5635.0737 | F103: =F65*F31 -> 12133.745 | G103: =G65*G31 -> 19702.945 | H103: =H65*H31 -> 28329.532 | I103: =I65*I31 -> 36634.435 | J103: =J65*J31 -> 43839.578 | K103: =K65*K31 -> 49688.14 | L103: =L65*L31 -> 58954.613 | M103: =M65*M31 -> 61541.687 | ... S103: =S65*S31 -> 97437.163
A104: Revenue per average employee ($M) | E104: =E65/E97 -> 10.187692 | F104: =F65/F97 -> 20.248219 | G104: =G65/G97 -> 28.449853 | H104: =H65/H97 -> 35.166034 | I104: =I65/I97 -> 40.878488 | J104: =J65/J97 -> 45.537567 | K104: =K65/K97 -> 49.65346 | L104: =L65/L97 -> 53.102274 | ... S104: =S65/S97 -> 64.792167
A106: INCOME STATEMENT ($M) – opex shown ex-D&A in forecast; S-1 actuals embed immaterial D&A
A107: Revenue | B107: =B65 -> 41 | C107: =C65 -> 386 | D107: =D65 -> 4585 | E107: =E65 -> 57560.46 | F107: =F65 -> 142749.94 | G107: =G65 -> 262705.94 | H107: =H65 -> 404707.59 | I107: =I65 -> 563606.7 | ... S107: =S65 -> 1948743.3
A108: Compute & infrastructure (rented + owned-fleet power) | B108: =Historicals!B9 -> 433 | C108: =Historicals!C9 -> 2522 | D108: =Historicals!D9 -> 7326 | E108: =E44+E51*(E89+E90)/E65 -> 30127.87 | F108: =F89+F90 -> 60731.89 | G108: =G89+G90 -> 95818.937 | H108: =H89+H90 -> 127124.04 | I108: =I89+I90 -> 154800.07 | J108: =J89+J90 -> 182474.64 | K108: =K89+K90 -> 206571.19 | L108: =L89+L90 -> 229730.07 | M108: =M89+M90 -> 252479.92 | ... S108: =S89+S90 -> 363187.76
...

Sheet Drivers
A1: Anthropic ($ANT) – Forecast Drivers (Bear / Base / Bull)
A2: Operating drivers feeding DCF Bear / DCF Base / DCF Bull | FY2026E–FY2040E (15-year explicit forecast) | $ in Millions unless stated
A3: All blue cells are analyst estimates (not company guidance) – revisit each quarter against the Actuals tab. Historical reference block below links live to Historicals.
A5: HISTORICAL REFERENCE (live links to Historicals – S-1 actuals)
A6: Metric | B6: FY2023A | C6: FY2024A | D6: FY2025A | E6: 6M 2026A | F6: Q2 2026A
A7: Revenue growth % (YoY) | C7: =Historicals!C7/Historicals!B7-1 -> 8.4146341 | D7: =Historicals!D7/Historicals!C7-1 -> 10.878238 | E7: =Historicals!F7/Historicals!E7-1 -> 13.003439 | F7: =Historicals!G33/Historicals!C33-1 -> 13.682338
A8: Subscription-based mix % of revenue | B8: =Historicals!B73/Historicals!B7 -> 0.048780488 | C8: =Historicals!C73/Historicals!C7 -> 0.25388601 | D8: =Historicals!D73/Historicals!D7 -> 0.17208288 | E8: =Historicals!F73/Historicals!F7 -> 0.19783863
A9: International % of revenue | B9: =Historicals!B70/Historicals!B7 -> 0.17073171 | C9: =Historicals!C70/Historicals!C7 -> 0.31865285 | D9: =Historicals!D70/Historicals!D7 -> 0.26673937 | E9: =Historicals!F70/Historicals!F7 -> 0.2777232
A10: Compute & infrastructure % of revenue | B10: =Historicals!B9/Historicals!B7 -> 10.560976 | C10: =Historicals!C9/Historicals!C7 -> 6.5336788 | D10: =Historicals!D9/Historicals!D7 -> 1.597819 | E10: =Historicals!F9/Historicals!F7 -> 0.54924475 | F10: =Historicals!G35/Historicals!G33 -> 0.48100389
A11: Personnel % of revenue | B11: =Historicals!B10/Historicals!B7 -> 2.3170732 | C11: =Historicals!C10/Historicals!C7 -> 1.1761658 | D11: =Historicals!D10/Historicals!D7 -> 0.40109051 | E11: =Historicals!F10/Historicals!F7 -> 0.19354046 | F11: =Historicals!G36/Historicals!G33 -> 0.16070965
A12: Sales, marketing & partnerships % of revenue | B12: =Historicals!B12/Historicals!B7 -> 0.048780488 | C12: =Historicals!C12/Historicals!C7 -> 0.11139896 | D12: =Historicals!D12/Historicals!D7 -> 0.12388222 | E12: =Historicals!F12/Historicals!F7 -> 0.1945229 | F12: =Historicals!G38/Historicals!G33 -> 0.1847685
A13: Other operating & admin % of revenue | B13: =Historicals!B13/Historicals!B7 -> 1.5121951 | C13: =Historicals!C13/Historicals!C7 -> 0.89896373 | D13: =Historicals!D13/Historicals!D7 -> 0.30796074 | E13: =Historicals!F13/Historicals!F7 -> 0.10524377 | F13: =Historicals!G39/Historicals!G33 -> 0.089225444
A14: GAAP operating margin | B14: =Historicals!B15/Historicals!B7 -> -13.439024 | C14: =Historicals!C15/Historicals!C7 -> -7.7202073 | D14: =Historicals!D15/Historicals!D7 -> -1.7579062 | E14: =Historicals!F15/Historicals!F7 -> -0.042551885 | F14: =Historicals!G41/Historicals!G33 -> 0.084292514
A15: Adjusted operating margin (non-GAAP) | B15: =Historicals!B27/Historicals!B7 -> -12.731707 | C15: =Historicals!C27/Historicals!C7 -> -7.2227979 | D15: =Historicals!D27/Historicals!D7 -> -1.0586696 | E15: =Historicals!F27/Historicals!F7 -> 0.099349134 | F15: =Historicals!G54/Historicals!G33 -> 0.19342276
A16: SBC % of personnel expense | B16: =Historicals!B25/Historicals!B10 -> 0.30526316 | C16: =Historicals!C25/Historicals!C10 -> 0.42290749 | D16: =Historicals!D25/Historicals!D10 -> 0.62969005 | E16: =Historicals!F25/Historicals!F10 -> 0.69321066 | F16: =Historicals!G51/Historicals!G36 -> 0.67905223
A17: Capex % of revenue | B17: =-Historicals!B130/Historicals!B7 -> 0.048780488 | C17: =-Historicals!C130/Historicals!C7 -> 0.038860104 | D17: =-Historicals!D130/Historicals!D7 -> 0.028571429 | E17: =-Historicals!F130/Historicals!F7 -> 0.029595972
A18: D&A % of revenue | B18: =Historicals!B26/Historicals!B7 -> 0.073170732 | C18: =Historicals!C26/Historicals!C7 -> 0.054404145 | D18: =Historicals!D26/Historicals!D7 -> 0.0087241003 | E18: =Historicals!F26/Historicals!F7 -> 0.0059560359
A20: Driver | B20: Unit | E20: FY2026E | F20: FY2027E | G20: FY2028E | H20: FY2029E | I20: FY2030E | J20: FY2031E | K20: FY2032E | L20: FY2033E | M20: FY2034E | N20: FY2035E | O20: FY2036E | P20: FY2037E | Q20: FY2038E | R20: FY2039E | S20: FY2040E
A22: BEAR CASE ASSUMPTIONS (compute-cost overhang, slower diffusion, price competition)
A23: Q3 2026 revenue growth (QoQ, vs Q2 2026A) | B23: % QoQ | E23: =Actuals!$B$13/Historicals!$G$33-1 -> 0.44128083
A24: Q4 2026 revenue growth (QoQ) | B24: % QoQ | E24: 0.12
A25: Subscription-based mix % of FY2026E revenue | B25: % rev | E25: 0.2
A26: Consumption-based revenue growth (YoY) – API / platform / pay-for-intelligence | B26: % YoY | F26: 0.7 | G26: 0.35 | H26: 0.22 | I26: 0.16 | J26: 0.12 | K26: 0.1 | L26: 0.08 | M26: 0.07 | N26: 0.06 | O26: 0.05 | P26: 0.045 | Q26: 0.04 | R26: 0.035 | S26: 0.03
A27: Subscription-based revenue growth (YoY) – Pro / Max / Team / Enterprise | B27: % YoY | F27: 0.6 | G27: 0.3 | H27: 0.2 | I27: 0.15 | J27: 0.11 | K27: 0.09 | L27: 0.075 | M27: 0.065 | N27: 0.055 | O27: 0.045 | P27: 0.04 | Q27: 0.035 | R27: 0.03 | S27: 0.03
A28: International % of revenue | B28: % rev | E28: 0.27 | F28: 0.275 | G28: 0.28 | H28: 0.285 | I28: 0.29 | J28: 0.295 | K28: 0.3 | L28: 0.305 | M28: 0.31 | N28: 0.315 | O28: 0.32 | P28: 0.325 | Q28: 0.33 | R28: 0.33 | S28: 0.33
A29: Enterprise customers (≥$100K TTM) growth | B29: % YoY | E29: 7 | F29: 0.6 | G29: 0.35 | H29: 0.22 | I29: 0.16 | J29: 0.12 | K29: 0.1 | L29: 0.08 | M29: 0.06 | N29: 0.05 | O29: 0.04 | P29: 0.035 | Q29: 0.03 | R29: 0.03 | S29: 0.025
A30: Enterprise customers (≥$100K TTM) share of revenue | B30: % rev | E30: 0.76 | F30: 0.765 | G30: 0.77 | H30: 0.775 | I30: 0.78 | J30: 0.785 | K30: 0.79 | L30: 0.795 | M30: 0.8 | N30: 0.8 | O30: 0.8 | P30: 0.8 | Q30: 0.8 | R30: 0.8 | S30: 0.8
A31: Inference / serving compute % of revenue | B31: % rev | E31: 0.32 | F31: 0.315 | G31: 0.31 | H31: 0.295 | I31: 0.28 | J31: 0.27 | K31: 0.26 | L31: 0.255 | M31: 0.25 | N31: 0.245 | O31: 0.24 | P31: 0.24 | Q31: 0.24 | R31: 0.24 | S31: 0.24
A32: Training & research compute % of revenue | B32: % rev | E32: 0.28 | F32: 0.25 | G32: 0.225 | H32: 0.205 | I32: 0.19 | J32: 0.18 | K32: 0.17 | L32: 0.16 | M32: 0.155 | N32: 0.15 | O32: 0.145 | P32: 0.14 | Q32: 0.14 | R32: 0.14 | S32: 0.14
A33: Rental-equivalent compute cost per GW-year (CSP / lease) | B33: $M / GW-yr | E33: 12000 | F33: 11760 | G33: 11524.8 | H33: 11294.3 | I33: 11068.4 | J33: 10847 | K33: 10630.1 | L33: 10417.5 | M33: 10209.2 | N33: 10005 | O33: 9804.9 | P33: 9608.8 | Q33: 9416.6 | R33: 9228.3 | S33: 9043.7
A34: Accelerators per GW (GPU / TPU / Trainium equivalents) | B34: 000s / GW | E34: 650 | F34: 630.5 | G34: 611.6 | H34: 593.2 | I34: 575.4 | J34: 558.2 | K34: 541.4 | L34: 525.2 | M34: 509.4 | N34: 494.2 | O34: 479.3 | P34: 464.9 | Q34: 451 | R34: 437.5 | S34: 424.3
A35: Anthropic Direct (owned) share of new capacity | B35: % of ΔGW | E35: 0.05 | F35: 0.1 | G35: 0.15 | H35: 0.2 | I35: 0.25 | J35: 0.25 | K35: 0.25 | L35: 0.25 | M35: 0.25 | N35: 0.25 | O35: 0.25 | P35: 0.25 | Q35: 0.25 | R35: 0.25 | S35: 0.25
A36: Capex per owned GW (accelerators + networking + fit-out) | B36: $M / GW | E36: 40000 | F36: 38400 | G36: 36864 | H36: 35389.4 | I36: 33973.9 | J36: 32614.9 | K36: 31310.3 | L36: 30057.9 | M36: 28855.6 | N36: 27701.4 | O36: 26593.3 | P36: 25529.6 | Q36: 24508.4 | R36: 23528.1 | S36: 22586.9
A37: Power & operations cost per owned GW-year | B37: $M / GW-yr | E37: 2000 | F37: 2040 | G37: 2080.8 | H37: 2122.4 | I37: 2164.9 | J37: 2208.2 | K37: 2252.3 | L37: 2297.4 | M37: 2343.3 | N37: 2390.2 | O37: 2438 | P37: 2486.7 | Q37: 2536.5 | R37: 2587.2 | S37: 2639
A38: Owned accelerator useful life | B38: years | E38: 5
A39: Headcount – FY2026E period end | B39: # | E39: 6000
A40: Headcount growth (YoY, period end) | B40: % YoY | F40: 0.2 | G40: 0.15 | H40: 0.1 | I40: 0.08 | J40: 0.06 | K40: 0.05 | L40: 0.04 | M40: 0.035 | N40: 0.03 | O40: 0.03 | P40: 0.025 | Q40: 0.025 | R40: 0.02 | S40: 0.02
A41: Fully-loaded personnel cost per average head – FY2026E (incl. SBC) | B41: $M / head | E41: 1.5
A42: Personnel cost per head growth | B42: % YoY | F42: 0.05 | G42: 0.05 | H42: 0.05 | I42: 0.05 | J42: 0.05 | K42: 0.05 | L42: 0.05 | M42: 0.05 | N42: 0.05 | O42: 0.05 | P42: 0.05 | Q42: 0.05 | R42: 0.05 | S42: 0.05
A43: SBC % of personnel expense | B43: % pers. | E43: 0.65 | F43: 0.6 | G43: 0.55 | H43: 0.5 | I43: 0.46 | J43: 0.42 | K43: 0.4 | L43: 0.38 | M43: 0.36 | N43: 0.35 | O43: 0.34 | P43: 0.33 | Q43: 0.32 | R43: 0.31 | S43: 0.3
A44: Sales, marketing & partnerships % of revenue | B44: % rev | E44: 0.21 | F44: 0.19 | G44: 0.175 | H44: 0.165 | I44: 0.155 | J44: 0.145 | K44: 0.14 | L44: 0.135 | M44: 0.13 | N44: 0.13 | O44: 0.13 | P44: 0.13 | Q44: 0.13 | R44: 0.13 | S44: 0.13
A45: Other operating & administrative % of revenue | B45: % rev | E45: 0.11 | F45: 0.1 | G45: 0.09 | H45: 0.085 | I45: 0.08 | J45: 0.075 | K45: 0.07 | L45: 0.07 | M45: 0.065 | N45: 0.065 | O45: 0.065 | P45: 0.065 | Q45: 0.065 | R45: 0.065 | S45: 0.065
A46: Other (non-compute) capex % of revenue – offices, DC shells, software | B46: % rev | E46: 0.012 | F46: 0.012 | G46: 0.012 | H46: 0.012 | I46: 0.012 | J46: 0.012 | K46: 0.012 | L46: 0.012 | M46: 0.012 | N46: 0.012 | O46: 0.012 | P46: 0.012 | Q46: 0.012 | R46: 0.012 | S46: 0.012
A47: Other D&A % of revenue | B47: % rev | E47: 0.005 | F47: 0.005 | G47: 0.005 | H47: 0.005 | I47: 0.005 | J47: 0.005 | K47: 0.005 | L47: 0.005 | M47: 0.005 | N47: 0.005 | O47: 0.005 | P47: 0.005 | Q47: 0.005 | R47: 0.005 | S47: 0.005
A48: Δ Net working capital % of Δ revenue | B48: % Δrev | E48: 0.05 | F48: 0.05 | G48: 0.05 | H48: 0.05 | I48: 0.05 | J48: 0.05 | K48: 0.05 | L48: 0.05 | M48: 0.05 | N48: 0.05 | O48: 0.05 | P48: 0.05 | Q48: 0.05 | R48: 0.05 | S48: 0.05
A49: Terminal growth rate (Gordon Growth) | B49: % | E49: 0.025
A50: Exit EV / EBITDA multiple (applied to FY2040E) | B50: x | E50: 11
A51: Scenario probability weight | B51: % | E51: 0.25
A53: BASE CASE ASSUMPTIONS (decelerating hyper-growth, steady compute-efficiency gains)
A54: Q3 2026 revenue growth (QoQ, vs Q2 2026A) | B54: % QoQ | E54: 0.47
A55: Q4 2026 revenue growth (QoQ) | B55: % QoQ | E55: 0.25
A56: Subscription-based mix % of FY2026E revenue | B56: % rev | E56: 0.2
A57: Consumption-based revenue growth (YoY) – API / platform / pay-for-intelligence | B57: % YoY | F57: 1.1 | G57: 0.6 | H57: 0.4 | I57: 0.3 | J57: 0.24 | K57: 0.19 | L57: 0.15 | M57: 0.12 | N57: 0.1 | O57: 0.085 | P57: 0.07 | Q57: 0.06 | R57: 0.05 | S57: 0.04
A58: Subscription-based revenue growth (YoY) – Pro / Max / Team / Enterprise | B58: % YoY | F58: 1 | G58: 0.55 | H58: 0.38 | I58: 0.28 | J58: 0.22 | K58: 0.17 | L58: 0.13 | M58: 0.11 | N58: 0.09 | O58: 0.075 | P58: 0.065 | Q58: 0.055 | R58: 0.045 | S58: 0.04
A59: International % of revenue | B59: % rev | E59: 0.28 | F59: 0.29 | G59: 0.3 | H59: 0.31 | I59: 0.32 | J59: 0.33 | K59: 0.34 | L59: 0.35 | M59: 0.36 | N59: 0.37 | O59: 0.38 | P59: 0.39 | Q59: 0.4 | R59: 0.4 | S59: 0.4
A60: Enterprise customers (≥$100K TTM) growth | B60: % YoY | E60: 9 | F60: 1 | G60: 0.6 | H60: 0.4 | I60: 0.3 | J60: 0.22 | K60: 0.17 | L60: 0.13 | M60: 0.1 | N60: 0.08 | O60: 0.06 | P60: 0.05 | Q60: 0.04 | R60: 0.035 | S60: 0.03
A61: Enterprise customers (≥$100K TTM) share of revenue | B61: % rev | E61: 0.78 | F61: 0.79 | G61: 0.8 | H61: 0.81 | I61: 0.82 | J61: 0.83 | K61: 0.84 | L61: 0.85 | M61: 0.85 | N61: 0.85 | O61: 0.85 | P61: 0.85 | Q61: 0.85 | R61: 0.85 | S61: 0.85
A62: Inference / serving compute % of revenue | B62: % rev | E62: 0.3 | F62: 0.285 | G62: 0.27 | H62: 0.255 | I62: 0.24 | J62: 0.23 | K62: 0.22 | L62: 0.215 | M62: 0.21 | N62: 0.205 | O62: 0.2 | P62: 0.2 | Q62: 0.2 | R62: 0.2 | S62: 0.2
A63: Training & research compute % of revenue | B63: % rev | E63: 0.25 | F63: 0.22 | G63: 0.195 | H63: 0.175 | I63: 0.16 | J63: 0.15 | K63: 0.14 | L63: 0.13 | M63: 0.125 | N63: 0.12 | O63: 0.115 | P63: 0.11 | Q63: 0.11 | R63: 0.11 | S63: 0.11
A64: Rental-equivalent compute cost per GW-year (CSP / lease) | B64: $M / GW-yr | E64: 12000 | F64: 11760 | G64: 11524.8 | H64: 11294.3 | I64: 11068.4 | J64: 10847 | K64: 10630.1 | L64: 10417.5 | M64: 10209.2 | N64: 10005 | O64: 9804.9 | P64: 9608.8 | Q64: 9416.6 | R64: 9228.3 | S64: 9043.7
A65: Accelerators per GW (GPU / TPU / Trainium equivalents) | B65: 000s / GW | E65: 650 | F65: 630.5 | G65: 611.6 | H65: 593.2 | I65: 575.4 | J65: 558.2 | K65: 541.4 | L65: 525.2 | M65: 509.4 | N65: 494.2 | O65: 479.3 | P65: 464.9 | Q65: 451 | R65: 437.5 | S65: 424.3
A66: Anthropic Direct (owned) share of new capacity | B66: % of ΔGW | E66: 0.1 | F66: 0.2 | G66: 0.3 | H66: 0.35 | I66: 0.4 | J66: 0.4 | K66: 0.4 | L66: 0.4 | M66: 0.4 | N66: 0.4 | O66: 0.4 | P66: 0.4 | Q66: 0.4 | R66: 0.4 | S66: 0.4
A67: Capex per owned GW (accelerators + networking + fit-out) | B67: $M / GW | E67: 40000 | F67: 38400 | G67: 36864 | H67: 35389.4 | I67: 33973.9 | J67: 32614.9 | K67: 31310.3 | L67: 30057.9 | M67: 28855.6 | N67: 27701.4 | O67: 26593.3 | P67: 25529.6 | Q67: 24508.4 | R67: 23528.1 | S67: 22586.9
A68: Power & operations cost per owned GW-year | B68: $M / GW-yr | E68: 2000 | F68: 2040 | G68: 2080.8 | H68: 2122.4 | I68: 2164.9 | J68: 2208.2 | K68: 2252.3 | L68: 2297.4 | M68: 2343.3 | N68: 2390.2 | O68: 2438 | P68: 2486.7 | Q68: 2536.5 | R68: 2587.2 | S68: 2639
A69: Owned accelerator useful life | B69: years | E69: 5
A70: Headcount – FY2026E period end | B70: # | E70: 6000
A71: Headcount growth (YoY, period end) | B71: % YoY | F71: 0.35 | G71: 0.28 | H71: 0.22 | I71: 0.18 | J71: 0.15 | K71: 0.12 | L71: 0.1 | M71: 0.08 | N71: 0.07 | O71: 0.06 | P71: 0.05 | Q71: 0.045 | R71: 0.04 | S71: 0.035
A72: Fully-loaded personnel cost per average head – FY2026E (incl. SBC) | B72: $M / head | E72: 1.5
A73: Personnel cost per head growth | B73: % YoY | F73: 0.05 | G73: 0.05 | H73: 0.05 | I73: 0.05 | J73: 0.04 | K73: 0.04 | L73: 0.04 | M73: 0.04 | N73: 0.04 | O73: 0.04 | P73: 0.04 | Q73: 0.04 | R73: 0.04 | S73: 0.04
A74: SBC % of personnel expense | B74: % pers. | E74: 0.65 | F74: 0.6 | G74: 0.55 | H74: 0.5 | I74: 0.46 | J74: 0.42 | K74: 0.4 | L74: 0.38 | M74: 0.36 | N74: 0.35 | O74: 0.34 | P74: 0.33 | Q74: 0.32 | R74: 0.31 | S74: 0.3
A75: Sales, marketing & partnerships % of revenue | B75: % rev | E75: 0.19 | F75: 0.17 | G75: 0.155 | H75: 0.145 | I75: 0.135 | J75: 0.125 | K75: 0.12 | L75: 0.115 | M75: 0.11 | N75: 0.11 | O75: 0.11 | P75: 0.11 | Q75: 0.11 | R75: 0.11 | S75: 0.11
A76: Other operating & administrative % of revenue | B76: % rev | E76: 0.1 | F76: 0.09 | G76: 0.08 | H76: 0.075 | I76: 0.07 | J76: 0.065 | K76: 0.06 | L76: 0.06 | M76: 0.055 | N76: 0.055 | O76: 0.055 | P76: 0.055 | Q76: 0.055 | R76: 0.055 | S76: 0.055
A77: Other (non-compute) capex % of revenue – offices, DC shells, software | B77: % rev | E77: 0.01 | F77: 0.01 | G77: 0.01 | H77: 0.01 | I77: 0.01 | J77: 0.01 | K77: 0.01 | L77: 0.01 | M77: 0.01 | N77: 0.01 | O77: 0.01 | P77: 0.01 | Q77: 0.01 | R77: 0.01 | S77: 0.01
A78: Other D&A % of revenue | B78: % rev | E78: 0.005 | F78: 0.005 | G78: 0.005 | H78: 0.005 | I78: 0.005 | J78: 0.005 | K78: 0.005 | L78: 0.005 | M78: 0.005 | N78: 0.005 | O78: 0.005 | P78: 0.005 | Q78: 0.005 | R78: 0.005 | S78: 0.005
A79: Δ Net working capital % of Δ revenue | B79: % Δrev | E79: 0.03 | F79: 0.03 | G79: 0.03 | H79: 0.03 | I79: 0.03 | J79: 0.03 | K79: 0.03 | L79: 0.03 | M79: 0.03 | N79: 0.03 | O79: 0.03 | P79: 0.03 | Q79: 0.03 | R79: 0.03 | S79: 0.03
A80: Terminal growth rate (Gordon Growth) | B80: % | E80: 0.035
A81: Exit EV / EBITDA multiple (applied to FY2040E) | B81: x | E81: 14
A82: Scenario probability weight | B82: % | E82: 0.5
A84: BULL CASE ASSUMPTIONS (agentic diffusion, Anthropic Direct cost advantage)
A85: Q3 2026 revenue growth (QoQ, vs Q2 2026A) | B85: % QoQ | E85: 0.52
A86: Q4 2026 revenue growth (QoQ) | B86: % QoQ | E86: 0.35
A87: Subscription-based mix % of FY2026E revenue | B87: % rev | E87: 0.2
A88: Consumption-based revenue growth (YoY) – API / platform / pay-for-intelligence | B88: % YoY | F88: 1.5 | G88: 0.85 | H88: 0.55 | I88: 0.4 | J88: 0.3 | K88: 0.24 | L88: 0.19 | M88: 0.15 | N88: 0.12 | O88: 0.1 | P88: 0.085 | Q88: 0.07 | R88: 0.06 | S88: 0.05
A89: Subscription-based revenue growth (YoY) – Pro / Max / Team / Enterprise | B89: % YoY | F89: 1.4 | G89: 0.8 | H89: 0.5 | I89: 0.36 | J89: 0.28 | K89: 0.22 | L89: 0.17 | M89: 0.14 | N89: 0.11 | O89: 0.09 | P89: 0.08 | Q89: 0.065 | R89: 0.055 | S89: 0.05
A90: International % of revenue | B90: % rev | E90: 0.29 | F90: 0.3 | G90: 0.31 | H90: 0.32 | I90: 0.33 | J90: 0.34 | K90: 0.35 | L90: 0.36 | M90: 0.37 | N90: 0.38 | O90: 0.39 | P90: 0.4 | Q90: 0.41 | R90: 0.42 | S90: 0.42
A91: Enterprise customers (≥$100K TTM) growth | B91: % YoY | E91: 10 | F91: 1.3 | G91: 0.8 | H91: 0.5 | I91: 0.35 | J91: 0.26 | K91: 0.2 | L91: 0.15 | M91: 0.12 | N91: 0.09 | O91: 0.07 | P91: 0.06 | Q91: 0.05 | R91: 0.04 | S91: 0.035
A92: Enterprise customers (≥$100K TTM) share of revenue | B92: % rev | E92: 0.79 | F92: 0.8 | G92: 0.81 | H92: 0.82 | I92: 0.83 | J92: 0.84 | K92: 0.85 | L92: 0.86 | M92: 0.87 | N92: 0.88 | O92: 0.88 | P92: 0.88 | Q92: 0.88 | R92: 0.88 | S92: 0.88
A93: Inference / serving compute % of revenue | B93: % rev | E93: 0.29 | F93: 0.265 | G93: 0.25 | H93: 0.235 | I93: 0.22 | J93: 0.21 | K93: 0.2 | L93: 0.195 | M93: 0.19 | N93: 0.185 | O93: 0.18 | P93: 0.18 | Q93: 0.18 | R93: 0.18 | S93: 0.18
A94: Training & research compute % of revenue | B94: % rev | E94: 0.24 | F94: 0.2 | G94: 0.175 | H94: 0.155 | I94: 0.14 | J94: 0.13 | K94: 0.12 | L94: 0.11 | M94: 0.105 | N94: 0.1 | O94: 0.095 | P94: 0.09 | Q94: 0.09 | R94: 0.09 | S94: 0.09
A95: Rental-equivalent compute cost per GW-year (CSP / lease) | B95: $M / GW-yr | E95: 12000 | F95: 11760 | G95: 11524.8 | H95: 11294.3 | I95: 11068.4 | J95: 10847 | K95: 10630.1 | L95: 10417.5 | M95: 10209.2 | N95: 10005 | O95: 9804.9 | P95: 9608.8 | Q95: 9416.6 | R95: 9228.3 | S95: 9043.7
A96: Accelerators per GW (GPU / TPU / Trainium equivalents) | B96: 000s / GW | E96: 650 | F96: 630.5 | G96: 611.6 | H96: 593.2 | I96: 575.4 | J96: 558.2 | K96: 541.4 | L96: 525.2 | M96: 509.4 | N96: 494.2 | O96: 479.3 | P96: 464.9 | Q96: 451 | R96: 437.5 | S96: 424.3
A97: Anthropic Direct (owned) share of new capacity | B97: % of ΔGW | E97: 0.1 | F97: 0.25 | G97: 0.35 | H97: 0.45 | I97: 0.5 | J97: 0.5 | K97: 0.5 | L97: 0.5 | M97: 0.5 | N97: 0.5 | O97: 0.5 | P97: 0.5 | Q97: 0.5 | R97: 0.5 | S97: 0.5
A98: Capex per owned GW (accelerators + networking + fit-out) | B98: $M / GW | E98: 40000 | F98: 38400 | G98: 36864 | H98: 35389.4 | I98: 33973.9 | J98: 32614.9 | K98: 31310.3 | L98: 30057.9 | M98: 28855.6 | N98: 27701.4 | O98: 26593.3 | P98: 25529.6 | Q98: 24508.4 | R98: 23528.1 | S98: 22586.9
A99: Power & operations cost per owned GW-year | B99: $M / GW-yr | E99: 2000 | F99: 2040 | G99: 2080.8 | H99: 2122.4 | I99: 2164.9 | J99: 2208.2 | K99: 2252.3 | L99: 2297.4 | M99: 2343.3 | N99: 2390.2 | O99: 2438 | P99: 2486.7 | Q99: 2536.5 | R99: 2587.2 | S99: 2639
A100: Owned accelerator useful life | B100: years | E100: 5
A101: Headcount – FY2026E period end | B101: # | E101: 6000
A102: Headcount growth (YoY, period end) | B102: % YoY | F102: 0.35 | G102: 0.28 | H102: 0.22 | I102: 0.18 | J102: 0.15 | K102: 0.12 | L102: 0.1 | M102: 0.08 | N102: 0.07 | O102: 0.06 | P102: 0.05 | Q102: 0.045 | R102: 0.04 | S102: 0.035
A103: Fully-loaded personnel cost per average head – FY2026E (incl. SBC) | B103: $M / head | E103: 1.5
A104: Personnel cost per head growth | B104: % YoY | F104: 0.04 | G104: 0.04 | H104: 0.04 | I104: 0.04 | J104: 0.04 | K104: 0.04 | L104: 0.04 | M104: 0.04 | N104: 0.04 | O104: 0.04 | P104: 0.04 | Q104: 0.04 | R104: 0.04 | S104: 0.04
A105: SBC % of personnel expense | B105: % pers. | E105: 0.65 | F105: 0.6 | G105: 0.55 | H105: 0.5 | I105: 0.46 | J105: 0.42 | K105: 0.4 | L105: 0.38 | M105: 0.36 | N105: 0.35 | O105: 0.34 | P105: 0.33 | Q105: 0.32 | R105: 0.31 | S105: 0.3
...

Sheet WACC
A1: Anthropic ($ANT) – Cost of Capital & Capitalization
A2: CAPM / WACC (single-segment) | Fully diluted share bridge | Net cash bridge | $ in Millions, shares in millions
A3: Yellow = estimate pending IPO pricing / final prospectus (S-1 leaves price range, share count and offering size blank).
A5: MACRO INPUTS
A6: Item | B6: Value | G6: Note
A7: Risk-free rate (10Y US Treasury) | B7: 0.05 | G7: US Treasury daily par yield curve, 23-Oct-2026
A8: Equity risk premium | B8: 0.05 | G8: Analyst assumption (US implied ERP range 4.5–5.5%) – refresh quarterly
A9: Cash tax rate (21% federal + state, net) | B9: 0.23 | G9: Analyst assumption; NOL shield modelled separately in DCF
A10: Company-specific risk premium | B10: 0.015 | G10: New issue, PBC / Long-Term Benefit Trust governance, compute-commitment operating leverage
A12: BETA, COST OF EQUITY & WACC
A13: Item | B13: Value | G13: Note
A14: Comps median unlevered beta (Comps tab) | B14: =IF(Comps!K38="","n/a",Comps!K38) -> 1.378027 | G14: Comps!K35 – populates once market data is entered
A15: Selected unlevered beta (= peer median) | B15: =B14 -> 1.378027 | G15: Linked to Comps all-comps median unlevered beta (13 peers, CRWV excluded – no 5Y beta)
A16: Target debt / equity | B16: 0.02 | G16: Net-cash balance sheet; minimal funded debt post note conversion
A17: Relevered beta | B17: =B15*(1+(1-B9)*B16) -> 1.3992486 | G17: βL = βU × (1 + (1 − t) × D/E)
A18: Cost of equity (CAPM) | B18: =B7+B17*B8+B10 -> 0.13496243 | G18: Ke = Rf + βL × ERP + specific premium
A19: Pre-tax cost of debt | B19: 0.09 | G19: Reference: Infrastructure Partner 2026 NPA notes at 9.00% PIK (S-1, Liquidity)
A20: After-tax cost of debt | B20: =B19*(1-B9) -> 0.0693 | G20: Kd × (1 − t)
A21: Equity weight | B21: =1/(1+B16) -> 0.98039216 | G21: E / (D + E)
A22: Debt weight | B22: =B16/(1+B16) -> 0.019607843 | G22: D / (D + E)
A23: WACC | B23: =B18*B21+B20*B22 -> 0.13367493 | G23: Applied to all three scenario engines
A25: WACC SUMMARY BY SCENARIO (referenced by DCF engines)
A26: Scenario | B26: WACC | C26: Terminal g | D26: Exit EV/EBITDA | E26: Probability | F26: Terminal WACC | G26: Note
A27: Bear | B27: =$B$23 -> 0.13367493 | C27: =Drivers!E49 -> 0.025 | D27: =Drivers!E50 -> 11 | E27: =Drivers!E51 -> 0.25 | F27: =$B$70 -> 0.10015294
A28: Base | B28: =$B$23 -> 0.13367493 | C28: =Drivers!E80 -> 0.035 | D28: =Drivers!E81 -> 14 | E28: =Drivers!E82 -> 0.5 | F28: =$B$70 -> 0.10015294
A29: Bull | B29: =$B$23 -> 0.13367493 | C29: =Drivers!E111 -> 0.04 | D29: =Drivers!E112 -> 17 | E29: =Drivers!E113 -> 0.25 | F29: =$B$70 -> 0.10015294
A30: Check: probabilities sum to 100% | E30: =SUM(E27:E29) -> 1
A32: CAPITALIZATION – FULLY DILUTED SHARES POST-IPO (millions)
A33: Item | B33: Value | G33: Note
A34: Class A common outstanding (latest BS) | B34: =INDEX(Historicals!$B$108:$J$108,MATCH(Actuals!$B$7,Historicals!$B$80:$J$80,0))/1000 -> 2157.398 | G34: Historicals BS, shares in thousands ÷ 1,000
A35: Class N common outstanding (latest BS) | B35: =INDEX(Historicals!$B$109:$J$109,MATCH(Actuals!$B$7,Historicals!$B$80:$J$80,0))/1000 -> 30.643 | G35: Donation Matching Plan shares
A36: Redeemable convertible preferred outstanding | B36: =INDEX(Historicals!$B$107:$J$107,MATCH(Actuals!$B$7,Historicals!$B$80:$J$80,0))/1000 -> 853.394 | G36: Preferred Stock Conversion at IPO
A37: Preferred → common conversion ratio (post 10-for-1 split) | B37: 10 | G37: S-1 Note 1 'Stock Split': 10-for-1 split of Class A & N on 17-Sep-2026; preferred conversion rate proportionately adjusted
A38: Shares from Preferred Stock Conversion | B38: =B36*B37 -> 8533.94
A39: Convertible notes at fair value ($M) | B39: =INDEX(Historicals!$B$98:$J$98,MATCH(Actuals!$B$7,Historicals!$B$80:$J$80,0)) -> 108566 | G39: Amazon notes – Convertible Notes Conversion at IPO
A40: % of convertible notes converting at IPO (Convertible Notes Conversion) | B40: 1
A41: Reference price for note conversion ($/common share, split-adjusted) | B41: =Historicals!B178/B37 -> 58.90095 | G41: Series H-1 $589.0095 per preferred ÷ conversion ratio; FV ÷ price approximates conversion shares
A42: Shares from Convertible Notes Conversion (est.) | B42: =B39*B40/B41 -> 1843.1961 | G42: Estimate – S-1 share count blank
A43: Stock options outstanding (latest S-1 / 10-Q, millions) | B43: 1797.066 | G43: S-1 Note 11 – stock option activity, balance 30-Jun-2026 (1,797,066k)
A44: Weighted-average exercise price ($/share) | B44: 2.89 | G44: S-1 Note 11 – WAEP of options outstanding 30-Jun-2026
A45: RSUs outstanding – IPO performance condition (millions) | B45: 1049.631 | G45: S-1 Note 11 – RSU activity, balance 30-Jun-2026 (1,049,631k); vest on IPO performance condition
A46: Net dilution: options (treasury stock method at IPO price) + RSUs | B46: =B43-B43*B44/B47+B45 -> 2758.5218 | G46: Excludes Initial Public Benefit Issuance & post-30-Sep Class N / acquisition shares (blank in S-1) – add when disclosed
A47: IPO price ($/share) | B47: =Dashboard!B5 -> 58.9 | G47: Entered on Dashboard
A48: IPO primary gross proceeds ($M) | B48: 20000 | G48: Analyst placeholder – S-1 offering size blank
A49: Underwriting discount & expenses (%) | B49: 0.02
A50: IPO net proceeds ($M) | B50: =B48*(1-B49) -> 19600
A51: IPO primary shares issued | B51: =IF(B47>0,B48/B47,0) -> 339.55857
A52: Fully diluted shares post-IPO | B52: =B34+B35+B38+B42+B46+B51 -> 15663.257 | G52: Denominator for implied value per share
A54: NET CASH BRIDGE ($M, latest balance sheet per Actuals!B7)
A55: Item | B55: Value | G55: Note
A56: Cash and cash equivalents | B56: =INDEX(Historicals!$B$82:$J$82,MATCH(Actuals!$B$7,Historicals!$B$80:$J$80,0)) -> 112389
A57: Short-term investments | B57: =INDEX(Historicals!$B$83:$J$83,MATCH(Actuals!$B$7,Historicals!$B$80:$J$80,0)) -> 19262
A58: (−) Funded debt not converting at IPO | B58: 0 | G58: Amazon notes convert; no other funded debt disclosed
A59: (−) Convertible notes NOT converting at IPO (fair value, debt-like) | B59: =B39*(1-B40) -> 0
A60: (−) Finance leases / other debt-like items | B60: 0 | G60: Add drawn Broadcom NPA / finance leases when disclosed
A61: (+) IPO net primary proceeds | B61: =B50 -> 19600
A62: Net cash used in EV → equity bridge | B62: =B56+B57-B58-B59-B60+B61 -> 151251 | G62: Restricted cash excluded
A64: TERMINAL-PERIOD WACC (mature-stage cost of capital applied to Gordon Growth terminal value)
A65: Item | B65: Value | G65: Note
A66: Mature-stage unlevered beta | B66: 1 | G66: FY2040E Anthropic ≈ mega-cap software / hyperscaler risk profile
A67: Mature-stage specific risk premium | B67: 0 | G67: IPO / governance premium assumed to fade by terminal year
A68: Terminal relevered beta | B68: =B66*(1+(1-B9)*B16) -> 1.0154 | G68: Hamada
A69: Terminal cost of equity | B69: =B7+B68*B8+B67 -> 0.10077 | G69: CAPM
A70: Terminal-period WACC | B70: =B69*B21+B20*B22 -> 0.10015294 | G70: Used only to capitalise FY2040E UFCF; explicit years discounted at B23
A100: Created by: Rifat Tahmid

Sheet Commitments
A1: Anthropic ($ANT) – Compute Commitments & Coverage Test
A2: Source: Form S-1 filed 26-Oct-2026 (MD&A – Contractual Obligations; Convertible Notes; Note 13) | $ in Millions | model spend from DCF Base / DCF Bear
A3: The MD&A contractual-obligations table is blank in this S-1, but Notes 7 & 13 disclose the data – loaded below. Expect an S-1/A (price range, share count, likely 30-Sep-2026 figures) before the roadshow.
A5: A. CONTRACTUAL OBLIGATIONS (payments due by year – leases as of 30-Jun-2026, Note 7; purchase commitments as of 31-Dec-2025, Note 13)
A6: Obligation ($M) | B6: Total | C6: 2026 | D6: 2027 | E6: 2028 | F6: 2029 | G6: 2030 | H6: Thereafter | I6: Source / note
A7: Operating leases | B7: =SUM(C7:H7) -> 1601 | C7: 52 | D7: 109 | E7: 194 | F7: 162 | G7: 173 | H7: 911 | I7: Offices and compute & infrastructure (S-1 footnote 1)
A8: Finance leases | B8: =SUM(C8:H8) -> 523 | C8: 62 | D8: 106 | E8: 106 | F8: 106 | G8: 106 | H8: 37 | I8: Compute & infrastructure (S-1 footnote 2)
A9: Purchase commitments | B9: =SUM(C9:H9) -> 54559 | C9: 7059 | D9: 11128 | E9: 10832 | F9: 8304 | G9: 5428 | H9: 11808 | I9: CSP hosting and third-party infrastructure service agreements, non-cancelable >1 year (S-1 footnote 3)
A10: Total contractual obligations | B10: =SUM(B7:B9) -> 56683 | C10: =SUM(C7:C9) -> 7173 | D10: =SUM(D7:D9) -> 11343 | E10: =SUM(E7:E9) -> 11132 | F10: =SUM(F7:F9) -> 8572 | G10: =SUM(G7:G9) -> 5707 | H10: =SUM(H7:H9) -> 12756 | I10: Excludes convertible notes expected to settle in shares (S-1 footnote 4)
A12: Other commitments disclosed outside the table
A13: Data-centre developer guaranty – maximum potential payments (30-Jun-2026) | B13: 800 | I13: Minimum payments (S-1 MD&A paragraph after the table)
A14: Leases executed but not yet commenced (undiscounted) | B14: 321400 | I14: Expected to commence over the period stated in the S-1
A15: Memo: total fixed / minimum purchase commitments at 30-Jun-2026 (not summed – feeds row 16) | B15: 265600
A16: Purchase commitments added 31-Dec-2025 → 30-Jun-2026 (total $265.6B less dated schedule; timing not disclosed) | B16: =B15-B9 -> 211041 | I16: Aggregate future minimum payments (S-1 MD&A)
A17: Variable-capacity compute agreements – low estimate (TPU 2028-31 low + AMD initial tranche) | B17: 145000 | I17: S-1 footnote 5 range (payable as capacity is delivered)
A18: Variable-capacity compute agreements – high estimate (TPU high + AMD initial + optional AMD expansion) | B18: 190000 | I18: S-1 footnote 5 range
A19: Aggregate commitments – low (table + other + variable low) | B19: =B10+B13+B14+B16+B17 -> 734924 | I19: S-1 headline: “substantially all of which is related to compute and infrastructure”
A20: Aggregate commitments – high (table + other + variable high) | B20: =B10+B13+B14+B16+B18 -> 779924
A22: B. COMPUTE-LINKED FINANCING FACILITIES (S-1 – Convertible Notes section, as of 30-Jun-2026)
A23: Facility | B23: Capacity | C23: Outstanding | D23: Rate | I23: Terms (summary)
A24: Infrastructure Partner 2026 NPA (Broadcom) | B24: 42000 | C24: 0 | D24: 0.09 | I24: Draws only to fund quarterly rent under the 2026 Lease Arrangement; interest PIK (13% if revenue conditions not met); converts post-IPO at 90% of 30-day VWAP into Class N
A25: Google 2026 NPA | B25: 20000 | C25: 0 | I25: Draws linked to compute agreements and TTM revenue targets through Dec-2030; post-IPO settled in notes or Class N shares at 30-day VWAP; 14.99% ownership cap
A26: Amazon Notes (2023 & 2024 NPAs) – principal | B26: 6200 | C26: 6200 | I26: Total indebtedness at 30-Jun-2026; converts into Class N at the IPO up to Amazon's ownership cap (Convertible Notes Conversion)
A27: Total facility capacity | B27: =SUM(B24:B26) -> 68200 | C27: =SUM(C24:C26) -> 6200
A28: Potential post-IPO dilution if Broadcom + Google facilities are fully drawn and settled in shares (M shares at entry price) | B28: =(B24+B25)/Dashboard!$B$5 -> 1052.6316 | I28: Memo only – not in the fully diluted share count (WACC!B49). Shown to size the dilution risk.
A30: C. COVERAGE TEST – does the forecast compute spend cover what is already committed?
A31: Test ($M) | B31: Total | C31: 2026 | D31: 2027 | E31: 2028 | F31: 2029 | G31: 2030 | H31: Thereafter | I31: Note
A32: Base: forecast compute spend (rented + owned power & ops + compute capex) | B32: =SUM(C32:H32) -> 2743050 | C32: =('DCF Base'!E89+'DCF Base'!E90+'DCF Base'!E92)*(1-'DCF Base'!E50) -> 18291.958 | D32: ='DCF Base'!F89+'DCF Base'!F90+'DCF Base'!F92 -> 72765.332 | E32: ='DCF Base'!G89+'DCF Base'!G90+'DCF Base'!G92 -> 105670.53 | F32: ='DCF Base'!H89+'DCF Base'!H90+'DCF Base'!H92 -> 130252.36 | G32: ='DCF Base'!I89+'DCF Base'!I90+'DCF Base'!I92 -> 151993.61 | H32: =SUM('DCF Base'!J89:'DCF Base'!S90)+SUM('DCF Base'!J92:'DCF Base'!S92) -> 2264076.2 | I32: 2026 = remaining fiscal year (full-year model × (1 − YTD fraction)); Thereafter = FY2031E–FY2040E
A33: Bear: forecast compute spend | B33: =SUM(C33:H33) -> 1279385.2 | C33: =('DCF Bear'!E89+'DCF Bear'!E90+'DCF Bear'!E92)*(1-'DCF Bear'!E50) -> 17200.728 | D33: ='DCF Bear'!F89+'DCF Bear'!F90+'DCF Bear'!F92 -> 54085.568 | E33: ='DCF Bear'!G89+'DCF Bear'!G90+'DCF Bear'!G92 -> 67554.373 | F33: ='DCF Bear'!H89+'DCF Bear'!H90+'DCF Bear'!H92 -> 75049.139 | G33: ='DCF Bear'!I89+'DCF Bear'!I90+'DCF Bear'!I92 -> 80752.088 | H33: =SUM('DCF Bear'!J89:'DCF Bear'!S90)+SUM('DCF Bear'!J92:'DCF Bear'!S92) -> 984743.31
A34: Committed: dated schedule by year (row 10); Total column = all commitments incl. undated (row 19) | B34: =B19 -> 734924 | C34: =C10 -> 7173 | D34: =D10 -> 11343 | E34: =E10 -> 11132 | F34: =F10 -> 8572 | G34: =G10 -> 5707 | H34: =H10 -> 12756
A35: Base coverage (forecast spend ÷ committed) | B35: =IF(B$34=0,"(awaiting)",B32/B$34) -> 3.7324267 | C35: =IF(C$34=0,"(awaiting)",C32/C$34) -> 2.5501126 | D35: =IF(D$34=0,"(awaiting)",D32/D$34) -> 6.4149988 | E35: =IF(E$34=0,"(awaiting)",E32/E$34) -> 9.4925016 | F35: =IF(F$34=0,"(awaiting)",F32/F$34) -> 15.195096 | G35: =IF(G$34=0,"(awaiting)",G32/G$34) -> 26.632839 | H35: =IF(H$34=0,"(awaiting)",H32/H$34) -> 177.49108
A36: Bear coverage (forecast spend ÷ committed) | B36: =IF(B$34=0,"(awaiting)",B33/B$34) -> 1.7408402 | C36: =IF(C$34=0,"(awaiting)",C33/C$34) -> 2.3979824 | D36: =IF(D$34=0,"(awaiting)",D33/D$34) -> 4.768189 | E36: =IF(E$34=0,"(awaiting)",E33/E$34) -> 6.0684848 | F36: =IF(F$34=0,"(awaiting)",F33/F$34) -> 8.7551492 | G36: =IF(G$34=0,"(awaiting)",G33/G$34) -> 14.149656 | H36: =IF(H$34=0,"(awaiting)",H33/H$34) -> 77.198441
A37: Bear shortfall: committed spend above Bear forecast (potentially stranded) | B37: =SUM(C37:H37) -> 0 | C37: =MAX(0,C34-C33) -> 0 | D37: =MAX(0,D34-D33) -> 0 | E37: =MAX(0,E34-E33) -> 0 | F37: =MAX(0,F34-F33) -> 0 | G37: =MAX(0,G34-G33) -> 0 | H37: =MAX(0,H34-H33) -> 0 | I37: Memo – not deducted in the DCF engines; the Bear engine already models lower compute need
A38: Discount period (years from balance-sheet date; Thereafter = assumed weighted timing) | C38: =(Actuals!$B$10-Actuals!$B$8)/365/2 -> 0.25205479 | D38: =C38*2+0.5 -> 1.0041096 | E38: =D38+1 -> 2.0041096 | F38: =E38+1 -> 3.0041096 | G38: =F38+1 -> 4.0041096 | H38: 5.5 | I38: Thereafter timing (5.5 yrs, i.e. front-loaded into the early 2030s) is an input – adjust once the S-1 profile is known
A39: PV of Bear shortfall at Bear WACC | B39: =SUM(C39:H39) -> 0 | C39: =C37/(1+'DCF Bear'!$E$38)^C38 -> 0 | D39: =D37/(1+'DCF Bear'!$E$38)^D38 -> 0 | E39: =E37/(1+'DCF Bear'!$E$38)^E38 -> 0 | F39: =F37/(1+'DCF Bear'!$E$38)^F38 -> 0 | G39: =G37/(1+'DCF Bear'!$E$38)^G38 -> 0 | H39: =H37/(1+'DCF Bear'!$E$38)^H38 -> 0
A40: PV of Bear shortfall per fully diluted share ($) | B40: =B39/WACC!$B$52 -> 0
A41: Status | B41: =IF(B34=0,"Awaiting S-1 / 10-Q commitments table",IF(B39=0,"OK – Bear forecast spend covers committed obligations","FLAG – commitments exceed Bear spend; consider deducting B38 from Bear equity")) -> OK – Bear forecast spend covers committed obligations
A100: Created by: Rifat Tahmid

Sheet Ratios
A1: Anthropic ($ANT) – Ratios & Unit Economics
A2: Source: Historicals tab (Form S-1 filed 26-Oct-2026) and DCF Base engine | $ in Millions unless stated | fills automatically as new quarters are added to Historicals
A3: Cells stay blank until the matching Historicals column is populated. Ratios use S-1 line items exactly as reported.
A5: A. QUARTERLY OPERATING RATIOS (Historicals quarterly block, rows 32–55 & KPIs rows 167–174)
A6: Metric | B6: =Historicals!B32 -> Q1 2025A | C6: =Historicals!C32 -> Q2 2025A | D6: =Historicals!D32 -> Q3 2025A | E6: =Historicals!E32 -> Q4 2025A | F6: =Historicals!F32 -> Q1 2026A | G6: =Historicals!G32 -> Q2 2026A | H6: =Historicals!H32 -> Q3 2026A | I6: =Historicals!I32 -> Q4 2026A | ... M6: =Historicals!M32 -> Q4 2027A
A7: Revenue | B7: =IF(Historicals!B33="","",Historicals!B33) -> 376 | C7: =IF(Historicals!C33="","",Historicals!C33) -> 787 | D7: =IF(Historicals!D33="","",Historicals!D33) -> 1382 | E7: =IF(Historicals!E33="","",Historicals!E33) -> 2040 | F7: =IF(Historicals!F33="","",Historicals!F33) -> 4731 | G7: =IF(Historicals!G33="","",Historicals!G33) -> 11555 | H7: =IF(Historicals!H33="","",Historicals!H33) | I7: =IF(Historicals!I33="","",Historicals!I33) | ... M7: =IF(Historicals!M33="","",Historicals!M33)
A8: % QoQ growth | B8: ="–" -> – | C8: =IF(OR(Historicals!C33="",Historicals!B33=""),"",Historicals!C33/Historicals!B33-1) -> 1.0930851 | D8: =IF(OR(Historicals!D33="",Historicals!C33=""),"",Historicals!D33/Historicals!C33-1) -> 0.75603558 | E8: =IF(OR(Historicals!E33="",Historicals!D33=""),"",Historicals!E33/Historicals!D33-1) -> 0.47612156 | F8: =IF(OR(Historicals!F33="",Historicals!E33=""),"",Historicals!F33/Historicals!E33-1) -> 1.3191176 | G8: =IF(OR(Historicals!G33="",Historicals!F33=""),"",Historicals!G33/Historicals!F33-1) -> 1.4424012 | H8: =IF(OR(Historicals!H33="",Historicals!G33=""),"",Historicals!H33/Historicals!G33-1) | I8: =IF(OR(Historicals!I33="",Historicals!H33=""),"",Historicals!I33/Historicals!H33-1) | J8: =IF(OR(Historicals!J33="",Historicals!I33=""),"",Historicals!J33/Historicals!I33-1) | ... M8: =IF(OR(Historicals!M33="",Historicals!L33=""),"",Historicals!M33/Historicals!L33-1)
A9: % YoY growth | B9: ="–" -> – | C9: ="–" -> – | D9: ="–" -> – | E9: ="–" -> – | F9: =IF(OR(Historicals!F33="",Historicals!B33=""),"",Historicals!F33/Historicals!B33-1) -> 11.582447 | G9: =IF(OR(Historicals!G33="",Historicals!C33=""),"",Historicals!G33/Historicals!C33-1) -> 13.682338 | H9: =IF(OR(Historicals!H33="",Historicals!D33=""),"",Historicals!H33/Historicals!D33-1) | I9: =IF(OR(Historicals!I33="",Historicals!E33=""),"",Historicals!I33/Historicals!E33-1) | J9: =IF(OR(Historicals!J33="",Historicals!F33=""),"",Historicals!J33/Historicals!F33-1) | K9: =IF(OR(Historicals!K33="",Historicals!G33=""),"",Historicals!K33/Historicals!G33-1) | L9: =IF(OR(Historicals!L33="",Historicals!H33=""),"",Historicals!L33/Historicals!H33-1) | M9: =IF(OR(Historicals!M33="",Historicals!I33=""),"",Historicals!M33/Historicals!I33-1)
A10: Annualised revenue run-rate (quarter × 4) | B10: =IF(Historicals!B33="","",Historicals!B33*4) -> 1504 | C10: =IF(Historicals!C33="","",Historicals!C33*4) -> 3148 | D10: =IF(Historicals!D33="","",Historicals!D33*4) -> 5528 | E10: =IF(Historicals!E33="","",Historicals!E33*4) -> 8160 | F10: =IF(Historicals!F33="","",Historicals!F33*4) -> 18924 | G10: =IF(Historicals!G33="","",Historicals!G33*4) -> 46220 | H10: =IF(Historicals!H33="","",Historicals!H33*4) | I10: =IF(Historicals!I33="","",Historicals!I33*4) | ... M10: =IF(Historicals!M33="","",Historicals!M33*4)
A11: Compute & infrastructure % revenue | B11: =IF(Historicals!B33="","",Historicals!B35/Historicals!B33) -> 2.5106383 | C11: =IF(Historicals!C33="","",Historicals!C35/Historicals!C33) -> 1.7662008 | D11: =IF(Historicals!D33="","",Historicals!D35/Historicals!D33) -> 1.4811867 | E11: =IF(Historicals!E33="","",Historicals!E35/Historicals!E33) -> 1.4436275 | F11: =IF(Historicals!F33="","",Historicals!F35/Historicals!F33) -> 0.7159163 | G11: =IF(Historicals!G33="","",Historicals!G35/Historicals!G33) -> 0.48100389 | H11: =IF(Historicals!H33="","",Historicals!H35/Historicals!H33) | I11: =IF(Historicals!I33="","",Historicals!I35/Historicals!I33) | ... M11: =IF(Historicals!M33="","",Historicals!M35/Historicals!M33)
A12: Personnel % revenue | B12: =IF(Historicals!B33="","",Historicals!B36/Historicals!B33) -> 0.57978723 | C12: =IF(Historicals!C33="","",Historicals!C36/Historicals!C33) -> 0.40660737 | D12: =IF(Historicals!D33="","",Historicals!D36/Historicals!D33) -> 0.35383502 | E12: =IF(Historicals!E33="","",Historicals!E36/Historicals!E33) -> 0.39803922 | F12: =IF(Historicals!F33="","",Historicals!F36/Historicals!F33) -> 0.27372648 | G12: =IF(Historicals!G33="","",Historicals!G36/Historicals!G33) -> 0.16070965 | H12: =IF(Historicals!H33="","",Historicals!H36/Historicals!H33) | I12: =IF(Historicals!I33="","",Historicals!I36/Historicals!I33) | ... M12: =IF(Historicals!M33="","",Historicals!M36/Historicals!M33)
A13: Sales, marketing & partnerships % revenue | B13: =IF(Historicals!B33="","",Historicals!B38/Historicals!B33) -> 0.063829787 | C13: =IF(Historicals!C33="","",Historicals!C38/Historicals!C33) -> 0.12198221 | D13: =IF(Historicals!D33="","",Historicals!D38/Historicals!D33) -> 0.14616498 | E13: =IF(Historicals!E33="","",Historicals!E38/Historicals!E33) -> 0.12058824 | F13: =IF(Historicals!F33="","",Historicals!F38/Historicals!F33) -> 0.21834707 | G13: =IF(Historicals!G33="","",Historicals!G38/Historicals!G33) -> 0.1847685 | H13: =IF(Historicals!H33="","",Historicals!H38/Historicals!H33) | I13: =IF(Historicals!I33="","",Historicals!I38/Historicals!I33) | ... M13: =IF(Historicals!M33="","",Historicals!M38/Historicals!M33)
A14: Other operating & administrative % revenue | B14: =IF(Historicals!B33="","",Historicals!B39/Historicals!B33) -> 0.33244681 | C14: =IF(Historicals!C33="","",Historicals!C39/Historicals!C33) -> 0.22998729 | D14: =IF(Historicals!D33="","",Historicals!D39/Historicals!D33) -> 0.16859624 | E14: =IF(Historicals!E33="","",Historicals!E39/Historicals!E33) -> 0.42794118 | F14: =IF(Historicals!F33="","",Historicals!F39/Historicals!F33) -> 0.14436694 | G14: =IF(Historicals!G33="","",Historicals!G39/Historicals!G33) -> 0.089225444 | H14: =IF(Historicals!H33="","",Historicals!H39/Historicals!H33) | I14: =IF(Historicals!I33="","",Historicals!I39/Historicals!I33) | ... M14: =IF(Historicals!M33="","",Historicals!M39/Historicals!M33)
A15: Total operating expenses % revenue | B15: =IF(Historicals!B33="","",Historicals!B40/Historicals!B33) -> 3.4867021 | C15: =IF(Historicals!C33="","",Historicals!C40/Historicals!C33) -> 2.5247776 | D15: =IF(Historicals!D33="","",Historicals!D40/Historicals!D33) -> 3.2351664 | E15: =IF(Historicals!E33="","",Historicals!E40/Historicals!E33) -> 2.3901961 | F15: =IF(Historicals!F33="","",Historicals!F40/Historicals!F33) -> 1.3523568 | G15: =IF(Historicals!G33="","",Historicals!G40/Historicals!G33) -> 0.91570749 | H15: =IF(Historicals!H33="","",Historicals!H40/Historicals!H33) | I15: =IF(Historicals!I33="","",Historicals!I40/Historicals!I33) | ... M15: =IF(Historicals!M33="","",Historicals!M40/Historicals!M33)
A16: Operating margin (GAAP) | B16: =IF(Historicals!B33="","",Historicals!B41/Historicals!B33) -> -2.4867021 | C16: =IF(Historicals!C33="","",Historicals!C41/Historicals!C33) -> -1.5247776 | D16: =IF(Historicals!D33="","",Historicals!D41/Historicals!D33) -> -2.2351664 | E16: =IF(Historicals!E33="","",Historicals!E41/Historicals!E33) -> -1.3901961 | F16: =IF(Historicals!F33="","",Historicals!F41/Historicals!F33) -> -0.3523568 | G16: =IF(Historicals!G33="","",Historicals!G41/Historicals!G33) -> 0.084292514 | H16: =IF(Historicals!H33="","",Historicals!H41/Historicals!H33) | I16: =IF(Historicals!I33="","",Historicals!I41/Historicals!I33) | ... M16: =IF(Historicals!M33="","",Historicals!M41/Historicals!M33)
A17: Stock-based compensation % revenue | B17: =IF(Historicals!B33="","",Historicals!B51/Historicals!B33) -> 0.27925532 | C17: =IF(Historicals!C33="","",Historicals!C51/Historicals!C33) -> 0.22998729 | D17: =IF(Historicals!D33="","",Historicals!D51/Historicals!D33) -> 0.22069465 | E17: =IF(Historicals!E33="","",Historicals!E51/Historicals!E33) -> 0.28137255 | F17: =IF(Historicals!F33="","",Historicals!F51/Historicals!F33) -> 0.19530755 | G17: =IF(Historicals!G33="","",Historicals!G51/Historicals!G33) -> 0.10913025 | H17: =IF(Historicals!H33="","",Historicals!H51/Historicals!H33) | I17: =IF(Historicals!I33="","",Historicals!I51/Historicals!I33) | ... M17: =IF(Historicals!M33="","",Historicals!M51/Historicals!M33)
A18: Adjusted operating margin (non-GAAP, S-1 definition) | B18: =IF(Historicals!B33="","",Historicals!B54/Historicals!B33) -> -2.2074468 | C18: =IF(Historicals!C33="","",Historicals!C54/Historicals!C33) -> -1.2947903 | D18: =IF(Historicals!D33="","",Historicals!D54/Historicals!D33) -> -0.92908828 | E18: =IF(Historicals!E33="","",Historicals!E54/Historicals!E33) -> -0.84362745 | F18: =IF(Historicals!F33="","",Historicals!F54/Historicals!F33) -> -0.1304164 | G18: =IF(Historicals!G33="","",Historicals!G54/Historicals!G33) -> 0.19342276 | H18: =IF(Historicals!H33="","",Historicals!H54/Historicals!H33) | I18: =IF(Historicals!I33="","",Historicals!I54/Historicals!I33) | ... M18: =IF(Historicals!M33="","",Historicals!M54/Historicals!M33)
A19: Incremental adjusted operating margin (Δ adj. OI / Δ revenue, QoQ) | B19: ="–" -> – | C19: =IF(OR(Historicals!C33="",Historicals!B33=""),"",(Historicals!C54-Historicals!B54)/(Historicals!C33-Historicals!B33)) -> -0.45985401 | D19: =IF(OR(Historicals!D33="",Historicals!C33=""),"",(Historicals!D54-Historicals!C54)/(Historicals!D33-Historicals!C33)) -> -0.44537815 | E19: =IF(OR(Historicals!E33="",Historicals!D33=""),"",(Historicals!E54-Historicals!D54)/(Historicals!E33-Historicals!D33)) -> -0.66413374 | F19: =IF(OR(Historicals!F33="",Historicals!E33=""),"",(Historicals!F54-Historicals!E54)/(Historicals!F33-Historicals!E33)) -> 0.41025641 | G19: =IF(OR(Historicals!G33="",Historicals!F33=""),"",(Historicals!G54-Historicals!F54)/(Historicals!G33-Historicals!F33)) -> 0.41793669 | H19: =IF(OR(Historicals!H33="",Historicals!G33=""),"",(Historicals!H54-Historicals!G54)/(Historicals!H33-Historicals!G33)) | I19: =IF(OR(Historicals!I33="",Historicals!H33=""),"",(Historicals!I54-Historicals!H54)/(Historicals!I33-Historicals!H33)) | J19: =IF(OR(Historicals!J33="",Historicals!I33=""),"",(Historicals!J54-Historicals!I54)/(Historicals!J33-Historicals!I33)) | ... M19: =IF(OR(Historicals!M33="",Historicals!L33=""),"",(Historicals!M54-Historicals!L54)/(Historicals!M33-Historicals!L33))
A20: Contribution after compute (revenue − compute & infrastructure) margin | B20: =IF(Historicals!B33="","",1-Historicals!B35/Historicals!B33) -> -1.5106383 | C20: =IF(Historicals!C33="","",1-Historicals!C35/Historicals!C33) -> -0.76620076 | D20: =IF(Historicals!D33="","",1-Historicals!D35/Historicals!D33) -> -0.48118669 | E20: =IF(Historicals!E33="","",1-Historicals!E35/Historicals!E33) -> -0.44362745 | F20: =IF(Historicals!F33="","",1-Historicals!F35/Historicals!F33) -> 0.2840837 | G20: =IF(Historicals!G33="","",1-Historicals!G35/Historicals!G33) -> 0.51899611 | H20: =IF(Historicals!H33="","",1-Historicals!H35/Historicals!H33) | I20: =IF(Historicals!I33="","",1-Historicals!I35/Historicals!I33) | ... M20: =IF(Historicals!M33="","",1-Historicals!M35/Historicals!M33)
A21: Revenue per $1 of compute & infrastructure expense | B21: =IF(Historicals!B33="","",Historicals!B33/Historicals!B35) -> 0.39830508 | C21: =IF(Historicals!C33="","",Historicals!C33/Historicals!C35) -> 0.56618705 | D21: =IF(Historicals!D33="","",Historicals!D33/Historicals!D35) -> 0.67513434 | E21: =IF(Historicals!E33="","",Historicals!E33/Historicals!E35) -> 0.69269949 | F21: =IF(Historicals!F33="","",Historicals!F33/Historicals!F35) -> 1.3968113 | G21: =IF(Historicals!G33="","",Historicals!G33/Historicals!G35) -> 2.0789852 | H21: =IF(Historicals!H33="","",Historicals!H33/Historicals!H35) | I21: =IF(Historicals!I33="","",Historicals!I33/Historicals!I35) | ... M21: =IF(Historicals!M33="","",Historicals!M33/Historicals!M35)
A22: Customers with ≥$100K TTM revenue (#) | B22: =IF(Historicals!B168="","",Historicals!B168) -> 400 | C22: =IF(Historicals!C168="","",Historicals!C168) | D22: =IF(Historicals!D168="","",Historicals!D168) -> 950 | E22: =IF(Historicals!E168="","",Historicals!E168) -> 1500 | F22: =IF(Historicals!F168="","",Historicals!F168) | G22: =IF(Historicals!G168="","",Historicals!G168) -> 6000 | H22: =IF(Historicals!H168="","",Historicals!H168) -> 11900 | I22: =IF(Historicals!I168="","",Historicals!I168) | ... M22: =IF(Historicals!M168="","",Historicals!M168)
A23: Employees (approx., period end) | B23: =IF(Historicals!B172="","",Historicals!B172) | C23: =IF(Historicals!C172="","",Historicals!C172) | D23: =IF(Historicals!D172="","",Historicals!D172) | E23: =IF(Historicals!E172="","",Historicals!E172) | F23: =IF(Historicals!F172="","",Historicals!F172) | G23: =IF(Historicals!G172="","",Historicals!G172) | H23: =IF(Historicals!H172="","",Historicals!H172) -> 5300 | I23: =IF(Historicals!I172="","",Historicals!I172) | ... M23: =IF(Historicals!M172="","",Historicals!M172)
A24: Implied TTM revenue (employees × TTM revenue / employee) | B24: =IF(Historicals!B174="","",Historicals!B174) | C24: =IF(Historicals!C174="","",Historicals!C174) | D24: =IF(Historicals!D174="","",Historicals!D174) | E24: =IF(Historicals!E174="","",Historicals!E174) | F24: =IF(Historicals!F174="","",Historicals!F174) | G24: =IF(Historicals!G174="","",Historicals!G174) | H24: =IF(Historicals!H174="","",Historicals!H174) -> 34980 | I24: =IF(Historicals!I174="","",Historicals!I174) | ... M24: =IF(Historicals!M174="","",Historicals!M174)
A26: B. ANNUAL / YTD RATIOS (Historicals income statement, cash flow & revenue disaggregation)
A27: Metric | B27: =Historicals!B6 -> FY2023A | C27: =Historicals!C6 -> FY2024A | D27: =Historicals!D6 -> FY2025A | E27: =Historicals!E6 -> 6M 2025A | F27: =Historicals!F6 -> 6M 2026A | G27: =Historicals!G6 -> 9M 2026A | H27: =Historicals!H6 -> FY2026A | I27: =Historicals!I6 -> 3M 2027A | ... K27: =Historicals!K6 -> 9M 2027A
A28: Revenue | B28: =IF(Historicals!B7="","",Historicals!B7) -> 41 | C28: =IF(Historicals!C7="","",Historicals!C7) -> 386 | D28: =IF(Historicals!D7="","",Historicals!D7) -> 4585 | E28: =IF(Historicals!E7="","",Historicals!E7) -> 1163 | F28: =IF(Historicals!F7="","",Historicals!F7) -> 16286 | G28: =IF(Historicals!G7="","",Historicals!G7) | H28: =IF(Historicals!H7="","",Historicals!H7) | I28: =IF(Historicals!I7="","",Historicals!I7) | ... K28: =IF(Historicals!K7="","",Historicals!K7)
A29: Compute & infrastructure % revenue | B29: =IF(Historicals!B7="","",Historicals!B9/Historicals!B7) -> 10.560976 | C29: =IF(Historicals!C7="","",Historicals!C9/Historicals!C7) -> 6.5336788 | D29: =IF(Historicals!D7="","",Historicals!D9/Historicals!D7) -> 1.597819 | E29: =IF(Historicals!E7="","",Historicals!E9/Historicals!E7) -> 2.0068788 | F29: =IF(Historicals!F7="","",Historicals!F9/Historicals!F7) -> 0.54924475 | G29: =IF(Historicals!G7="","",Historicals!G9/Historicals!G7) | H29: =IF(Historicals!H7="","",Historicals!H9/Historicals!H7) | I29: =IF(Historicals!I7="","",Historicals!I9/Historicals!I7) | ... K29: =IF(Historicals!K7="","",Historicals!K9/Historicals!K7)
A30: Personnel % revenue | B30: =IF(Historicals!B7="","",Historicals!B10/Historicals!B7) -> 2.3170732 | C30: =IF(Historicals!C7="","",Historicals!C10/Historicals!C7) -> 1.1761658 | D30: =IF(Historicals!D7="","",Historicals!D10/Historicals!D7) -> 0.40109051 | E30: =IF(Historicals!E7="","",Historicals!E10/Historicals!E7) -> 0.46259673 | F30: =IF(Historicals!F7="","",Historicals!F10/Historicals!F7) -> 0.19354046 | G30: =IF(Historicals!G7="","",Historicals!G10/Historicals!G7) | H30: =IF(Historicals!H7="","",Historicals!H10/Historicals!H7) | I30: =IF(Historicals!I7="","",Historicals!I10/Historicals!I7) | ... K30: =IF(Historicals!K7="","",Historicals!K10/Historicals!K7)
A31: Sales, marketing & partnerships % revenue | B31: =IF(Historicals!B7="","",Historicals!B12/Historicals!B7) -> 0.048780488 | C31: =IF(Historicals!C7="","",Historicals!C12/Historicals!C7) -> 0.11139896 | D31: =IF(Historicals!D7="","",Historicals!D12/Historicals!D7) -> 0.12388222 | E31: =IF(Historicals!E7="","",Historicals!E12/Historicals!E7) -> 0.10318143 | F31: =IF(Historicals!F7="","",Historicals!F12/Historicals!F7) -> 0.1945229 | G31: =IF(Historicals!G7="","",Historicals!G12/Historicals!G7) | H31: =IF(Historicals!H7="","",Historicals!H12/Historicals!H7) | I31: =IF(Historicals!I7="","",Historicals!I12/Historicals!I7) | ... K31: =IF(Historicals!K7="","",Historicals!K12/Historicals!K7)
A32: Other operating & administrative % revenue | B32: =IF(Historicals!B7="","",Historicals!B13/Historicals!B7) -> 1.5121951 | C32: =IF(Historicals!C7="","",Historicals!C13/Historicals!C7) -> 0.89896373 | D32: =IF(Historicals!D7="","",Historicals!D13/Historicals!D7) -> 0.30796074 | E32: =IF(Historicals!E7="","",Historicals!E13/Historicals!E7) -> 0.26311264 | F32: =IF(Historicals!F7="","",Historicals!F13/Historicals!F7) -> 0.10524377 | G32: =IF(Historicals!G7="","",Historicals!G13/Historicals!G7) | H32: =IF(Historicals!H7="","",Historicals!H13/Historicals!H7) | I32: =IF(Historicals!I7="","",Historicals!I13/Historicals!I7) | ... K32: =IF(Historicals!K7="","",Historicals!K13/Historicals!K7)
A33: Operating margin (GAAP) | B33: =IF(Historicals!B7="","",Historicals!B15/Historicals!B7) -> -13.439024 | C33: =IF(Historicals!C7="","",Historicals!C15/Historicals!C7) -> -7.7202073 | D33: =IF(Historicals!D7="","",Historicals!D15/Historicals!D7) -> -1.7579062 | E33: =IF(Historicals!E7="","",Historicals!E15/Historicals!E7) -> -1.8357696 | F33: =IF(Historicals!F7="","",Historicals!F15/Historicals!F7) -> -0.042551885 | G33: =IF(Historicals!G7="","",Historicals!G15/Historicals!G7) | H33: =IF(Historicals!H7="","",Historicals!H15/Historicals!H7) | I33: =IF(Historicals!I7="","",Historicals!I15/Historicals!I7) | ... K33: =IF(Historicals!K7="","",Historicals!K15/Historicals!K7)
A34: Adjusted operating margin (non-GAAP) | B34: =IF(Historicals!B7="","",Historicals!B27/Historicals!B7) -> -12.731707 | C34: =IF(Historicals!C7="","",Historicals!C27/Historicals!C7) -> -7.2227979 | D34: =IF(Historicals!D7="","",Historicals!D27/Historicals!D7) -> -1.0586696 | E34: =IF(Historicals!E7="","",Historicals!E27/Historicals!E7) -> -1.5898538 | F34: =IF(Historicals!F7="","",Historicals!F27/Historicals!F7) -> 0.099349134 | G34: =IF(Historicals!G7="","",Historicals!G27/Historicals!G7) | H34: =IF(Historicals!H7="","",Historicals!H27/Historicals!H7) | I34: =IF(Historicals!I7="","",Historicals!I27/Historicals!I7) | ... K34: =IF(Historicals!K7="","",Historicals!K27/Historicals!K7)
A35: Stock-based compensation % revenue (cash flow statement) | B35: =IF(Historicals!B7="","",Historicals!B116/Historicals!B7) -> 0.70731707 | C35: =IF(Historicals!C7="","",Historicals!C116/Historicals!C7) -> 0.49740933 | D35: =IF(Historicals!D7="","",Historicals!D116/Historicals!D7) -> 0.2525627 | E35: =IF(Historicals!E7="","",Historicals!E116/Historicals!E7) -> 0.23989682 | F35: =IF(Historicals!F7="","",Historicals!F116/Historicals!F7) -> 0.13416431 | G35: =IF(Historicals!G7="","",Historicals!G116/Historicals!G7) | H35: =IF(Historicals!H7="","",Historicals!H116/Historicals!H7) | I35: =IF(Historicals!I7="","",Historicals!I116/Historicals!I7) | ... K35: =IF(Historicals!K7="","",Historicals!K116/Historicals!K7)
A36: Interest income % revenue | B36: =IF(Historicals!B7="","",Historicals!B16/Historicals!B7) -> 1.6829268 | C36: =IF(Historicals!C7="","",Historicals!C16/Historicals!C7) -> 0.2746114 | D36: =IF(Historicals!D7="","",Historicals!D16/Historicals!D7) -> 0.094002181 | E36: =IF(Historicals!E7="","",Historicals!E16/Historicals!E7) -> 0.098882201 | F36: =IF(Historicals!F7="","",Historicals!F16/Historicals!F7) -> 0.068218101 | G36: =IF(Historicals!G7="","",Historicals!G16/Historicals!G7) | H36: =IF(Historicals!H7="","",Historicals!H16/Historicals!H7) | I36: =IF(Historicals!I7="","",Historicals!I16/Historicals!I7) | ... K36: =IF(Historicals!K7="","",Historicals!K16/Historicals!K7)
